Workbook

Sheet 80109
B1: 商品センター | C1: 品番 | D1: 商品区分 | E1: カラー | F1: 72期 | G1: 73期 | H1: 74期(1期) | I1: 2023/10/1～2024/3/21（6か月） | J1: 75期(2期) | K1: 76期（３期 ） | L1: 77期（4期 7/1-12/18） | N1: 発注点 5ヶ月分なのでそのまま | O1: 在庫数 ロジザード | Q1: 入荷予定 ロジザード | S1: 確保数 弥生(在庫確保) | T1: 確保数チェック 0じゃなかったらロジザード修正 | U1: 有効数量 フリー在庫の数 | V1: 発注検討フラグ マイナスの場合発注検討 | W1: 在庫回転率 | X1: 前回決定事項（12/26） | Y1: 決定事項 | AE1: 前回決定事項（/） | AG1: 決定事項
A2: 1 | B2: 伊賀 | C2: APL-4312SBL | D2: ミニホイッスル付LEDアルミライトⅡ | H2: 192 | I2: =VLOOKUP(C2,'202310-202403出荷数total2403220951'!B:F,5,0) -> 71 | J2: =VLOOKUP(C2,'出荷数2307～2406total241008110618'!B:F,5,0) -> 281 | K2: =VLOOKUP(C2,'出荷数2407-2506total250730101950'!B:F,5,0) -> 902 | L2: =VLOOKUP(C:C,total251219111800!B:F,5,0) -> 386 | N2: =L2 -> 386 | O2: 427 | P2: 710 | Q2: 0 | R2: 0 | S2: 550 | T2: 160 | U2: -123 | V2: -509 | W2: 0.33948989
A3: 2 | B3: 伊賀 | C3: APL-4312SPK | D3: ミニホイッスル付LEDアルミライトⅡ | H3: 2161 | I3: =VLOOKUP(C3,'202310-202403出荷数total2403220951'!B:F,5,0) -> 1018 | J3: =VLOOKUP(C3,'出荷数2307～2406total241008110618'!B:F,5,0) -> 1930 | K3: =VLOOKUP(C3,'出荷数2407-2506total250730101950'!B:F,5,0) -> 3388 | L3: =VLOOKUP(C:C,total251219111800!B:F,5,0) -> 903 | N3: =L3 -> 903 | O3: 2232 | P3: 1980 | Q3: 0 | R3: 0 | S3: 1830 | T3: 150 | U3: 402 | V3: -501 | W3: 0.21438746
A4: 86 | B4: 伊賀 | C4: ABO-08BL | D4: ミニホイッスル | E4: ブルー | F4: 527 | G4: 2107 | H4: 796 | I4: =VLOOKUP(C4,'202310-202403出荷数total2403220951'!B:F,5,0) -> 1409 | J4: =VLOOKUP(C4,'出荷数2307～2406total241008110618'!B:F,5,0) -> 1708 | K4: =VLOOKUP(C4,'出荷数2407-2506total250730101950'!B:F,5,0) -> 1865 | L4: =VLOOKUP(C:C,total251219111800!B:F,5,0) -> 474 | M4: 1000 | N4: 1000 | O4: 6783 | P4: 0 | Q4: 0 | R4: 0 | S4: 0 | T4: 0 | U4: 6783 | V4: 5783 | W4: 0.14742739
A5: 107 | B5: 伊賀 | C5: ABO-08PK | D5: ミニホイッスル | E5: ピンク | F5: 3939 | G5: 5966 | H5: 5009 | I5: =VLOOKUP(C5,'202310-202403出荷数total2403220951'!B:F,5,0) -> 6490 | J5: =VLOOKUP(C5,'出荷数2307～2406total241008110618'!B:F,5,0) -> 17931 | K5: =VLOOKUP(C5,'出荷数2407-2506total250730101950'!B:F,5,0) -> 28387 | L5: =VLOOKUP(C:C,total251219111800!B:F,5,0) -> 4495 | N5: =L5 -> 4495 | O5: 31370 | P5: 35250 | Q5: 800 | R5: 0 | S5: 35250 | T5: 0 | U5: -3080 | V5: -7575 | W5: 0.067472231
A6: 109 | B6: 伊賀 | C6: APL-4302S | D6: ＬＥＤミニアルミライト | F6: 1094 | G6: 3475 | H6: 834 | I6: =VLOOKUP(C6,'202310-202403出荷数total2403220951'!B:F,5,0) -> 444 | J6: =VLOOKUP(C6,'出荷数2307～2406total241008110618'!B:F,5,0) -> 789 | K6: =VLOOKUP(C6,'出荷数2407-2506total250730101950'!B:F,5,0) -> 232 | L6: =VLOOKUP(C:C,total251219111800!B:F,5,0) -> 177 | N6: =L6 -> 177 | O6: 3754 | P6: 0 | Q6: 300 | R6: 0 | S6: 0 | T6: 0 | U6: 4054 | V6: 3877 | W6: 0.047149707
A7: 3 | B7: 伊賀 | C7: ASL-3308SK | D7: ウォールセンサーライト 箱 | E7: しかく | F7: 1 | G7: 0 | H7: 4 | I7: =VLOOKUP(C7,'202310-202403出荷数total2403220951'!B:F,5,0) -> #N/A | J7: =VLOOKUP(C7,'出荷数2307～2406total241008110618'!B:F,5,0) -> #N/A | K7: =VLOOKUP(C7,'出荷数2407-2506total250730101950'!B:F,5,0) -> #N/A | L7: =VLOOKUP(C:C,total251219111800!B:F,5,0) -> #N/A | N7: 0 | O7: 1 | P7: 0 | Q7: 0 | R7: 0 | S7: 0 | T7: 0 | U7: 1 | V7: 1 | W7: 0
A8: 4 | B8: 伊賀 | C8: AHL-3201RD | D8: LEDハンディライト | H8: 2048 | I8: =VLOOKUP(C8,'202310-202403出荷数total2403220951'!B:F,5,0) -> 2098 | J8: =VLOOKUP(C8,'出荷数2307～2406total241008110618'!B:F,5,0) -> 3644 | K8: =VLOOKUP(C8,'出荷数2407-2506total250730101950'!B:F,5,0) -> 2910 | L8: =VLOOKUP(C:C,total251219111800!B:F,5,0) -> 2559 | N8: =L8 -> 2559 | O8: 3061 | P8: 0 | Q8: 0 | R8: 0 | S8: 0 | T8: 0 | U8: 3061 | V8: 502 | W8: 0.83600131
A9: 5 | B9: 伊賀 | C9: AHL-3201WH | D9: LEDハンディライト | H9: 116 | I9: =VLOOKUP(C9,'202310-202403出荷数total2403220951'!B:F,5,0) -> 220 | J9: =VLOOKUP(C9,'出荷数2307～2406total241008110618'!B:F,5,0) -> 378 | K9: =VLOOKUP(C9,'出荷数2407-2506total250730101950'!B:F,5,0) -> 2016 | L9: =VLOOKUP(C:C,total251219111800!B:F,5,0) -> 281 | M9: 1000 | N9: 1000 | O9: 5196 | P9: 0 | Q9: 0 | R9: 0 | S9: 0 | T9: 0 | U9: 5196 | V9: 4196 | W9: 0.19245574
A10: 6 | B10: 伊賀 | C10: AHL-1400 | D10: LED強力ライト | H10: 15126 | I10: =VLOOKUP(C10,'202310-202403出荷数total2403220951'!B:F,5,0) -> 9163 | J10: =VLOOKUP(C10,'出荷数2307～2406total241008110618'!B:F,5,0) -> 19757 | K10: =VLOOKUP(C10,'出荷数2407-2506total250730101950'!B:F,5,0) -> 20812 | L10: =VLOOKUP(C:C,total251219111800!B:F,5,0) -> 4356 | N10: =L10 -> 4356 | O10: 2929 | P10: 13545 | Q10: 0 | R10: 0 | S10: 13175 | T10: 370 | U10: -10246 | V10: -14602 | W10: 0.26441666
A11: 7 | B11: 伊賀 | C11: AHL-1400T | D11: LED強力ライト(トップ) | H11: 2084 | I11: =VLOOKUP(C11,'202310-202403出荷数total2403220951'!B:F,5,0) -> 1160 | J11: =VLOOKUP(C11,'出荷数2307～2406total241008110618'!B:F,5,0) -> 1821 | K11: =VLOOKUP(C11,'出荷数2407-2506total250730101950'!B:F,5,0) -> 1120 | L11: =VLOOKUP(C:C,total251219111800!B:F,5,0) -> 160 | N11: =L11 -> 160 | O11: 2 | P11: 0 | Q11: 0 | R11: 0 | S11: 0 | T11: 0 | U11: 2 | V11: -158 | W11: 80
A12: 8 | B12: 伊賀 | C12: ASL-3308KU | D12: ウォールセンサーライト 箱 | E12: くも | F12: 193 | G12: 1 | H12: 100 | I12: =VLOOKUP(C12,'202310-202403出荷数total2403220951'!B:F,5,0) -> 43 | J12: =VLOOKUP(C12,'出荷数2307～2406total241008110618'!B:F,5,0) -> 51 | K12: =VLOOKUP(C12,'出荷数2407-2506total250730101950'!B:F,5,0) -> 12 | L12: =VLOOKUP(C:C,total251219111800!B:F,5,0) -> 3 | N12: =L12 -> 3 | O12: 999 | P12: 0 | Q12: 0 | R12: 0 | S12: 0 | T12: 0 | U12: 999 | V12: 996 | W12: 0.003003003
A13: 9 | B13: 伊賀 | C13: ANS-502 | D13: テレビ用手もとスピーカー | G13: 6 | H13: 2364 | I13: =VLOOKUP(C13,'202310-202403出荷数total2403220951'!B:F,5,0) -> 1052 | J13: =VLOOKUP(C13,'出荷数2307～2406total241008110618'!B:F,5,0) -> 1711 | K13: =VLOOKUP(C13,'出荷数2407-2506total250730101950'!B:F,5,0) -> 1026 | L13: =VLOOKUP(C:C,total251219111800!B:F,5,0) -> 587 | N13: =L13 -> 587 | O13: 3558 | P13: 0 | Q13: 0 | R13: 0 | S13: 0 | T13: 0 | U13: 3558 | V13: 2971 | W13: 0.16498033
A14: 10 | B14: 伊賀 | C14: ASL-3308US | D14: ウォールセンサーライト 箱 | E14: うさぎ | F14: 0 | G14: 3 | H14: 363 | I14: =VLOOKUP(C14,'202310-202403出荷数total2403220951'!B:F,5,0) -> #N/A | J14: =VLOOKUP(C14,'出荷数2307～2406total241008110618'!B:F,5,0) -> 1 | K14: =VLOOKUP(C14,'出荷数2407-2506total250730101950'!B:F,5,0) -> 7 | L14: =VLOOKUP(C:C,total251219111800!B:F,5,0) -> #N/A | N14: 0 | O14: 744 | P14: 0 | Q14: 0 | R14: 0 | S14: 0 | T14: 0 | U14: 744 | V14: 744 | W14: 0
A15: 11 | B15: 伊賀 | C15: ASL-3308CSK | D15: ウォールセンサーライト ブリスター | E15: しかく | F15: 23 | G15: 4 | H15: 0 | I15: =VLOOKUP(C15,'202310-202403出荷数total2403220951'!B:F,5,0) -> 1 | J15: =VLOOKUP(C15,'出荷数2307～2406total241008110618'!B:F,5,0) -> 705 | K15: =VLOOKUP(C15,'出荷数2407-2506total250730101950'!B:F,5,0) -> 1 | L15: =VLOOKUP(C:C,total251219111800!B:F,5,0) -> 1 | N15: =L15 -> 1 | O15: 0 | P15: 0 | Q15: 0 | R15: 0 | S15: 0 | T15: 0 | U15: 0 | V15: -1 | W15: #DIV/0!
A16: 12 | B16: 伊賀 | C16: ASL-3308CUS | D16: ウォールセンサーライト ブリスター | E16: うさぎ | F16: 35 | G16: 26 | H16: 5 | I16: =VLOOKUP(C16,'202310-202403出荷数total2403220951'!B:F,5,0) -> 3 | J16: =VLOOKUP(C16,'出荷数2307～2406total241008110618'!B:F,5,0) -> 6 | K16: =VLOOKUP(C16,'出荷数2407-2506total250730101950'!B:F,5,0) -> 3 | L16: =VLOOKUP(C:C,total251219111800!B:F,5,0) -> 142 | N16: =L16 -> 142 | O16: 4414 | P16: 0 | Q16: 0 | R16: 0 | S16: 0 | T16: 0 | U16: 4414 | V16: 4272 | W16: 0.032170367
A17: 13 | B17: 伊賀 | C17: AKM-3205PK | D17: 首ふり毛だまクリーナー | E17: ピンク | F17: 33 | G17: 24 | H17: 2990 | I17: =VLOOKUP(C17,'202310-202403出荷数total2403220951'!B:F,5,0) -> 66 | J17: =VLOOKUP(C17,'出荷数2307～2406total241008110618'!B:F,5,0) -> 189 | K17: =VLOOKUP(C17,'出荷数2407-2506total250730101950'!B:F,5,0) -> 97 | L17: =VLOOKUP(C:C,total251219111800!B:F,5,0) -> 77 | N17: =L17 -> 77 | O17: 2106 | P17: 0 | Q17: 0 | R17: 0 | S17: 0 | T17: 0 | U17: 2106 | V17: 2029 | W17: 0.036562203
A18: 14 | B18: 伊賀 | C18: ASN-4302 | D18: マグネット付ＬＥＤ信号灯 | F18: 149 | G18: 62 | H18: 132 | I18: =VLOOKUP(C18,'202310-202403出荷数total2403220951'!B:F,5,0) -> 245 | J18: =VLOOKUP(C18,'出荷数2307～2406total241008110618'!B:F,5,0) -> 322 | K18: =VLOOKUP(C18,'出荷数2407-2506total250730101950'!B:F,5,0) -> 206 | L18: =VLOOKUP(C:C,total251219111800!B:F,5,0) -> 17 | N18: =L18 -> 17 | O18: 2259 | P18: 0 | Q18: 0 | R18: 0 | S18: 0 | T18: 0 | U18: 2259 | V18: 2242 | W18: 0.0075254537 | X18: 売り切り廃盤予定 | Y18: 売り切り廃盤予定
A19: 15 | B19: 伊賀 | C19: AIC-01IV | D19: ｷｽﾞつきにくいｲｽ脚ｶﾊﾞｰ | E19: IV | F19: 228 | G19: 270 | H19: 231 | I19: =VLOOKUP(C19,'202310-202403出荷数total2403220951'!B:F,5,0) -> 121 | J19: =VLOOKUP(C19,'出荷数2307～2406total241008110618'!B:F,5,0) -> 177 | K19: =VLOOKUP(C19,'出荷数2407-2506total250730101950'!B:F,5,0) -> 110 | L19: =VLOOKUP(C:C,total251219111800!B:F,5,0) -> 53 | N19: =L19 -> 53 | O19: 8060 | P19: 0 | Q19: 0 | R19: 0 | S19: 0 | T19: 0 | U19: 8060 | V19: 8007 | W19: 0.0065756824
A20: 16 | B20: 伊賀 | C20: ANS-603 | D20: お経の流れるスピーカーⅡ | G20: 128 | H20: 470 | I20: =VLOOKUP(C20,'202310-202403出荷数total2403220951'!B:F,5,0) -> 149 | J20: =VLOOKUP(C20,'出荷数2307～2406total241008110618'!B:F,5,0) -> 418 | K20: =VLOOKUP(C20,'出荷数2407-2506total250730101950'!B:F,5,0) -> 818 | L20: =VLOOKUP(C:C,total251219111800!B:F,5,0) -> 491 | N20: =L20 -> 491 | O20: 617 | P20: 130 | Q20: 0 | R20: 0 | S20: 280 | T20: -150 | U20: 337 | V20: -154 | W20: 0.65729585 | X20: 様子見 | Y20: トップ確保3月末まで確保
A21: 17 | B21: 伊賀 | C21: APY-105 | D21: 迷惑電話お断りピンポン | F21: 543 | G21: 321 | H21: 270 | I21: =VLOOKUP(C21,'202310-202403出荷数total2403220951'!B:F,5,0) -> 73 | J21: =VLOOKUP(C21,'出荷数2307～2406total241008110618'!B:F,5,0) -> 181 | K21: =VLOOKUP(C21,'出荷数2407-2506total250730101950'!B:F,5,0) -> 277 | L21: =VLOOKUP(C:C,total251219111800!B:F,5,0) -> 141 | N21: =L21 -> 141 | O21: 3326 | P21: 370 | Q21: 0 | R21: 0 | S21: 370 | T21: 0 | U21: 2956 | V21: 2815 | W21: 0.038149351
A22: 18 | B22: 伊賀 | C22: APL-3207S | D22: LEDのインテリア常備灯 | F22: 904 | G22: 638 | H22: 81 | I22: =VLOOKUP(C22,'202310-202403出荷数total2403220951'!B:F,5,0) -> 2 | J22: =VLOOKUP(C22,'出荷数2307～2406total241008110618'!B:F,5,0) -> 904 | K22: =VLOOKUP(C22,'出荷数2407-2506total250730101950'!B:F,5,0) -> 25 | L22: =VLOOKUP(C:C,total251219111800!B:F,5,0) -> 2 | N22: =L22 -> 2 | O22: 6861 | P22: 0 | Q22: 0 | R22: 0 | S22: 0 | T22: 0 | U22: 6861 | V22: 6859 | W22: 0.0002915027
A23: 19 | B23: 伊賀 | C23: ALA-4308BK-D | D23: ひっぱり点灯ライト 電球色ＬＥＤ | F23: 1137 | G23: 270 | H23: 272 | I23: =VLOOKUP(C23,'202310-202403出荷数total2403220951'!B:F,5,0) -> 153 | J23: =VLOOKUP(C23,'出荷数2307～2406total241008110618'!B:F,5,0) -> 657 | K23: =VLOOKUP(C23,'出荷数2407-2506total250730101950'!B:F,5,0) -> 101 | L23: =VLOOKUP(C:C,total251219111800!B:F,5,0) -> 88 | N23: =L23 -> 88 | O23: 1782 | P23: 0 | Q23: 0 | R23: 0 | S23: 0 | T23: 0 | U23: 1782 | V23: 1694 | W23: 0.049382716
A24: 20 | B24: 伊賀 | C24: ACA-101 | D24: ＬＥＤ帽子ライト | F24: 787 | G24: 450 | H24: 417 | I24: =VLOOKUP(C24,'202310-202403出荷数total2403220951'!B:F,5,0) -> 450 | J24: =VLOOKUP(C24,'出荷数2307～2406total241008110618'!B:F,5,0) -> 550 | K24: =VLOOKUP(C24,'出荷数2407-2506total250730101950'!B:F,5,0) -> 160 | L24: =VLOOKUP(C:C,total251219111800!B:F,5,0) -> 89 | N24: =L24 -> 89 | O24: 3706 | P24: 0 | Q24: 0 | R24: 0 | S24: 0 | T24: 0 | U24: 3706 | V24: 3617 | W24: 0.024015111
A25: 21 | B25: 伊賀 | C25: ASL-3308NE | D25: ウォールセンサーライト 箱 | E25: ねこ | F25: 13 | G25: 4 | H25: 8 | I25: =VLOOKUP(C25,'202310-202403出荷数total2403220951'!B:F,5,0) -> 1 | J25: =VLOOKUP(C25,'出荷数2307～2406total241008110618'!B:F,5,0) -> 4 | K25: =VLOOKUP(C25,'出荷数2407-2506total250730101950'!B:F,5,0) -> 6 | L25: =VLOOKUP(C:C,total251219111800!B:F,5,0) -> #N/A | N25: 0 | O25: 24 | P25: 0 | Q25: 0 | R25: 0 | S25: 0 | T25: 0 | U25: 24 | V25: 24 | W25: 0
A26: 22 | B26: 伊賀 | C26: AKD-20 | D26: アニマルシリコンバンド | F26: 1809 | G26: 790 | H26: 1042 | I26: =VLOOKUP(C26,'202310-202403出荷数total2403220951'!B:F,5,0) -> 164 | J26: =VLOOKUP(C26,'出荷数2307～2406total241008110618'!B:F,5,0) -> 312 | K26: =VLOOKUP(C26,'出荷数2407-2506total250730101950'!B:F,5,0) -> 454 | L26: =VLOOKUP(C:C,total251219111800!B:F,5,0) -> 168 | N26: =L26 -> 168 | O26: 5727 | P26: 300 | Q26: 0 | R26: 0 | S26: 300 | T26: 0 | U26: 5427 | V26: 5259 | W26: 0.027874564
A27: 23 | B27: 伊賀 | C27: ARA-4301 | D27: スマートフォンが使えるラジオライト | F27: 549 | G27: 303 | H27: 236 | I27: =VLOOKUP(C27,'202310-202403出荷数total2403220951'!B:F,5,0) -> 241 | J27: =VLOOKUP(C27,'出荷数2307～2406total241008110618'!B:F,5,0) -> 358 | K27: =VLOOKUP(C27,'出荷数2407-2506total250730101950'!B:F,5,0) -> 392 | L27: =VLOOKUP(C:C,total251219111800!B:F,5,0) -> 29 | N27: =L27 -> 29 | O27: 1917 | P27: 0 | Q27: 0 | R27: 0 | S27: 0 | T27: 0 | U27: 1917 | V27: 1888 | W27: 0.015127804
A28: 24 | B28: 伊賀 | C28: ASK-11BOR | D28: 巻きつく安全反射バンド(OR) | E28: オレンジ | F28: 1160 | G28: 148 | H28: 651 | I28: =VLOOKUP(C28,'202310-202403出荷数total2403220951'!B:F,5,0) -> 60 | J28: =VLOOKUP(C28,'出荷数2307～2406total241008110618'!B:F,5,0) -> 125 | K28: =VLOOKUP(C28,'出荷数2407-2506total250730101950'!B:F,5,0) -> 265 | L28: =VLOOKUP(C:C,total251219111800!B:F,5,0) -> 38 | M28: 500 | N28: 500 | O28: 2313 | P28: 0 | Q28: 0 | R28: 0 | S28: 0 | T28: 0 | U28: 2313 | V28: 1813 | W28: 0.21616948
A29: 25 | B29: 伊賀 | C29: ASK-10YE | D29: 光るホイール反射シール | E29: イエロー | F29: 935 | G29: 77 | H29: 731 | I29: =VLOOKUP(C29,'202310-202403出荷数total2403220951'!B:F,5,0) -> 163 | J29: =VLOOKUP(C29,'出荷数2307～2406total241008110618'!B:F,5,0) -> 235 | K29: =VLOOKUP(C29,'出荷数2407-2506total250730101950'!B:F,5,0) -> 20 | L29: =VLOOKUP(C:C,total251219111800!B:F,5,0) -> 2 | N29: =L29 -> 2 | O29: 5 | P29: 0 | Q29: 0 | R29: 0 | S29: 0 | T29: 0 | U29: 5 | V29: 3 | W29: 0.4
A30: 26 | B30: 伊賀 | C30: ARO-530GD | D30: 自動消灯安心のろうそく | E30: GD | F30: 224 | G30: 198 | H30: 230 | I30: =VLOOKUP(C30,'202310-202403出荷数total2403220951'!B:F,5,0) -> 91 | J30: =VLOOKUP(C30,'出荷数2307～2406total241008110618'!B:F,5,0) -> 168 | K30: =VLOOKUP(C30,'出荷数2407-2506total250730101950'!B:F,5,0) -> 52 | L30: =VLOOKUP(C:C,total251219111800!B:F,5,0) -> 28 | N30: =L30 -> 28 | O30: 920 | P30: 0 | Q30: 0 | R30: 0 | S30: 0 | T30: 0 | U30: 920 | V30: 892 | W30: 0.030434783
A31: 27 | B31: 伊賀 | C31: ALA-4308MO-W | D31: ひっぱり点灯ライト 木目 | E31: 木目 | F31: 714 | G31: 368 | H31: 496 | I31: =VLOOKUP(C31,'202310-202403出荷数total2403220951'!B:F,5,0) -> 150 | J31: =VLOOKUP(C31,'出荷数2307～2406total241008110618'!B:F,5,0) -> 247 | K31: =VLOOKUP(C31,'出荷数2407-2506total250730101950'!B:F,5,0) -> 43 | L31: =VLOOKUP(C:C,total251219111800!B:F,5,0) -> 29 | N31: =L31 -> 29 | O31: 1947 | P31: 0 | Q31: 0 | R31: 0 | S31: 0 | T31: 0 | U31: 1947 | V31: 1918 | W31: 0.01489471
A32: 28 | B32: 伊賀 | C32: AIC-06IV | D32: ｽﾞﾚにくいｲｽ脚ｶﾊﾞｰ 2脚用 | E32: IV | F32: 1116 | G32: 928 | H32: 1098 | I32: =VLOOKUP(C32,'202310-202403出荷数total2403220951'!B:F,5,0) -> 427 | J32: =VLOOKUP(C32,'出荷数2307～2406total241008110618'!B:F,5,0) -> 1008 | K32: =VLOOKUP(C32,'出荷数2407-2506total250730101950'!B:F,5,0) -> 854 | L32: =VLOOKUP(C:C,total251219111800!B:F,5,0) -> 345 | N32: =L32 -> 345 | O32: 3124 | P32: 0 | Q32: 0 | R32: 0 | S32: 0 | T32: 0 | U32: 3124 | V32: 2779 | W32: 0.11043534 | X32: 88％発注点よりﾏｲﾅｽ 345→41 | Y32: 88％発注点よりﾏｲﾅｽ 345→41
A33: 29 | B33: 伊賀 | C33: ANS-701AD | D33: ＡＣアダプター701用 | F33: 120 | G33: 98 | H33: 141 | I33: =VLOOKUP(C33,'202310-202403出荷数total2403220951'!B:F,5,0) -> 41 | J33: =VLOOKUP(C33,'出荷数2307～2406total241008110618'!B:F,5,0) -> 89 | K33: =VLOOKUP(C33,'出荷数2407-2506total250730101950'!B:F,5,0) -> 92 | L33: =VLOOKUP(C:C,total251219111800!B:F,5,0) -> 49 | N33: =L33 -> 49 | O33: 319 | P33: 0 | Q33: 0 | R33: 0 | S33: 0 | T33: 0 | U33: 319 | V33: 270 | W33: 0.15360502
A34: 30 | B34: 伊賀 | C34: ANS-702 | D34: 大きな手もとスピーカー | F34: 1030 | G34: 390 | H34: 221 | I34: =VLOOKUP(C34,'202310-202403出荷数total2403220951'!B:F,5,0) -> 53 | J34: =VLOOKUP(C34,'出荷数2307～2406total241008110618'!B:F,5,0) -> 103 | K34: =VLOOKUP(C34,'出荷数2407-2506total250730101950'!B:F,5,0) -> 224 | L34: =VLOOKUP(C:C,total251219111800!B:F,5,0) -> 45 | N34: =L34 -> 45 | O34: 2078 | P34: 0 | Q34: 0 | R34: 0 | S34: 0 | T34: 0 | U34: 2078 | V34: 2033 | W34: 0.021655438
A35: 31 | B35: 伊賀 | C35: AKN-15 | D35: ハローキティ コンセントカバー | F35: 1322 | G35: 1075 | H35: 946 | I35: =VLOOKUP(C35,'202310-202403出荷数total2403220951'!B:F,5,0) -> 348 | J35: =VLOOKUP(C35,'出荷数2307～2406total241008110618'!B:F,5,0) -> 766 | K35: =VLOOKUP(C35,'出荷数2407-2506total250730101950'!B:F,5,0) -> 1074 | L35: =VLOOKUP(C:C,total251219111800!B:F,5,0) -> 327 | N35: =L35 -> 327 | O35: 3683 | P35: 0 | Q35: 0 | R35: 0 | S35: 0 | T35: 0 | U35: 3683 | V35: 3356 | W35: 0.088786316
A36: 32 | B36: 伊賀 | C36: ACA-3101 | D36: ＬＥＤアルミヘッドランプ | F36: 1781 | G36: 1472 | H36: 1360 | I36: =VLOOKUP(C36,'202310-202403出荷数total2403220951'!B:F,5,0) -> 3651 | J36: =VLOOKUP(C36,'出荷数2307～2406total241008110618'!B:F,5,0) -> 4452 | K36: =VLOOKUP(C36,'出荷数2407-2506total250730101950'!B:F,5,0) -> 4054 | L36: =VLOOKUP(C:C,total251219111800!B:F,5,0) -> 524 | N36: =L36 -> 524 | O36: 12996 | P36: 0 | Q36: 100 | R36: 0 | S36: 0 | T36: 0 | U36: 13096 | V36: 12572 | W36: 0.040320098
A37: 33 | B37: 伊賀 | C37: ASK-06SI | D37: はめるだけ光る 足腕バンド | E37: シルバー | F37: 1210 | G37: 214 | H37: 13 | I37: =VLOOKUP(C37,'202310-202403出荷数total2403220951'!B:F,5,0) -> 75 | J37: =VLOOKUP(C37,'出荷数2307～2406total241008110618'!B:F,5,0) -> 79 | K37: =VLOOKUP(C37,'出荷数2407-2506total250730101950'!B:F,5,0) -> 1 | L37: =VLOOKUP(C:C,total251219111800!B:F,5,0) -> 3 | N37: =L37 -> 3 | O37: 881 | P37: 0 | Q37: 0 | R37: 0 | S37: 0 | T37: 0 | U37: 881 | V37: 878 | W37: 0.0034052213
A38: 34 | B38: 伊賀 | C38: ASL-3308CNE | D38: ウォールセンサーライト ブリスター | E38: ねこ | F38: 271 | G38: 200 | H38: 124 | I38: =VLOOKUP(C38,'202310-202403出荷数total2403220951'!B:F,5,0) -> 63 | J38: =VLOOKUP(C38,'出荷数2307～2406total241008110618'!B:F,5,0) -> 93 | K38: =VLOOKUP(C38,'出荷数2407-2506total250730101950'!B:F,5,0) -> 14 | L38: =VLOOKUP(C:C,total251219111800!B:F,5,0) -> 140 | N38: =L38 -> 140 | O38: 797 | P38: 0 | Q38: 0 | R38: 0 | S38: 0 | T38: 0 | U38: 797 | V38: 657 | W38: 0.17565872
A39: 35 | B39: 伊賀 | C39: ASL-33082 | D39: ウォールセンサーライト（ショップチャンネル専用） | G39: 9 | H39: 1109 | I39: =VLOOKUP(C39,'202310-202403出荷数total2403220951'!B:F,5,0) -> #N/A | J39: =VLOOKUP(C39,'出荷数2307～2406total241008110618'!B:F,5,0) -> #N/A | K39: =VLOOKUP(C39,'出荷数2407-2506total250730101950'!B:F,5,0) -> #N/A | L39: =VLOOKUP(C:C,total251219111800!B:F,5,0) -> #N/A | M39: 470 | N39: 470 | O39: 106 | P39: 0 | Q39: 0 | R39: 0 | S39: 0 | T39: 0 | U39: 106 | V39: -364 | W39: 4.4339623
A40: 36 | B40: 伊賀 | C40: ADR-3401 | D40: 電動角質リムーバー | F40: 19 | G40: 1283 | H40: 7 | I40: =VLOOKUP(C40,'202310-202403出荷数total2403220951'!B:F,5,0) -> 223 | J40: =VLOOKUP(C40,'出荷数2307～2406total241008110618'!B:F,5,0) -> 598 | K40: =VLOOKUP(C40,'出荷数2407-2506total250730101950'!B:F,5,0) -> 73 | L40: =VLOOKUP(C:C,total251219111800!B:F,5,0) -> 5 | N40: =L40 -> 5 | O40: 4152 | P40: 0 | Q40: 0 | R40: 0 | S40: 0 | T40: 0 | U40: 4152 | V40: 4147 | W40: 0.0012042389
A41: 37 | B41: 伊賀 | C41: ASL-3309 | D41: センサーライト付防犯ダミーカメラ | F41: 825 | G41: 660 | H41: 1314 | I41: =VLOOKUP(C41,'202310-202403出荷数total2403220951'!B:F,5,0) -> 262 | J41: =VLOOKUP(C41,'出荷数2307～2406total241008110618'!B:F,5,0) -> 723 | K41: =VLOOKUP(C41,'出荷数2407-2506total250730101950'!B:F,5,0) -> 1443 | L41: =VLOOKUP(C:C,total251219111800!B:F,5,0) -> 305 | N41: =L41 -> 305 | O41: 3065 | P41: 190 | Q41: 0 | R41: 0 | S41: 300 | T41: -110 | U41: 2765 | V41: 2460 | W41: 0.093701997
A42: 38 | B42: 伊賀 | C42: ADR-3401KR | D42: 電動角質リムーバー交換用ローラー（2PCS) | F42: 33 | G42: 994 | H42: 20 | I42: =VLOOKUP(C42,'202310-202403出荷数total2403220951'!B:F,5,0) -> 14 | J42: =VLOOKUP(C42,'出荷数2307～2406total241008110618'!B:F,5,0) -> 26 | K42: =VLOOKUP(C42,'出荷数2407-2506total250730101950'!B:F,5,0) -> 8 | L42: =VLOOKUP(C:C,total251219111800!B:F,5,0) -> 4 | N42: =L42 -> 4 | O42: 4564 | P42: 0 | Q42: 0 | R42: 0 | S42: 0 | T42: 0 | U42: 4564 | V42: 4560 | W42: 0.00087642419
A43: 39 | B43: 伊賀 | C43: KCA-003 | D43: キューベルク 充電式ヘッドライト340 | F43: 15 | G43: 257 | H43: 96 | I43: =VLOOKUP(C43,'202310-202403出荷数total2403220951'!B:F,5,0) -> 18 | J43: =VLOOKUP(C43,'出荷数2307～2406total241008110618'!B:F,5,0) -> 45 | K43: =VLOOKUP(C43,'出荷数2407-2506total250730101950'!B:F,5,0) -> 101 | L43: =VLOOKUP(C:C,total251219111800!B:F,5,0) -> 21 | N43: =L43 -> 21 | O43: 793 | P43: 0 | Q43: 0 | R43: 0 | S43: 0 | T43: 0 | U43: 793 | V43: 772 | W43: 0.026481715
B44: 伊賀 | C44: KCA-004H | D44: ロータリー式ヘッドライト500 | L44: =VLOOKUP(C:C,total251219111800!B:F,5,0) -> 3 | N44: =L44 -> 3 | O44: 493 | P44: 0 | Q44: 1000 | R44: 0 | S44: 0 | T44: 0 | U44: 1493 | V44: 1490 | W44: 0.0060851927
A45: 40 | B45: 伊賀 | C45: ABO-180 | D45: エアーマット1800 | F45: 940 | G45: 457 | H45: 1013 | I45: =VLOOKUP(C45,'202310-202403出荷数total2403220951'!B:F,5,0) -> 669 | J45: =VLOOKUP(C45,'出荷数2307～2406total241008110618'!B:F,5,0) -> 4147 | K45: =VLOOKUP(C45,'出荷数2407-2506total250730101950'!B:F,5,0) -> 4439 | L45: =VLOOKUP(C:C,total251219111800!B:F,5,0) -> 49 | N45: =L45 -> 49 | O45: 307 | P45: 0 | Q45: 0 | R45: 0 | S45: 0 | T45: 0 | U45: 307 | V45: 258 | W45: 0.15960912
A46: 41 | B46: 伊賀 | C46: ABO-120 | D46: エアーマット1200 | F46: 149 | G46: 373 | H46: 66 | I46: =VLOOKUP(C46,'202310-202403出荷数total2403220951'!B:F,5,0) -> 150 | J46: =VLOOKUP(C46,'出荷数2307～2406total241008110618'!B:F,5,0) -> 203 | K46: =VLOOKUP(C46,'出荷数2407-2506total250730101950'!B:F,5,0) -> 212 | L46: =VLOOKUP(C:C,total251219111800!B:F,5,0) -> 39 | N46: =L46 -> 39 | O46: 965 | P46: 0 | Q46: 0 | R46: 0 | S46: 0 | T46: 0 | U46: 965 | V46: 926 | W46: 0.040414508
A47: 42 | B47: 伊賀 | C47: AIC-01BR | D47: ｷｽﾞつきにくいｲｽ脚ｶﾊﾞｰ | E47: BR | F47: 2264 | G47: 1923 | H47: 1776 | I47: =VLOOKUP(C47,'202310-202403出荷数total2403220951'!B:F,5,0) -> 535 | J47: =VLOOKUP(C47,'出荷数2307～2406total241008110618'!B:F,5,0) -> 2161 | K47: =VLOOKUP(C47,'出荷数2407-2506total250730101950'!B:F,5,0) -> 933 | L47: =VLOOKUP(C:C,total251219111800!B:F,5,0) -> 398 | N47: =L47 -> 398 | O47: 2688 | P47: 0 | Q47: 0 | R47: 0 | S47: 0 | T47: 0 | U47: 2688 | V47: 2290 | W47: 0.14806548
A48: 43 | B48: 伊賀 | C48: AHL-1207 | D48: 単1形LED防雨ライト | F48: 3482 | G48: 1186 | H48: 1004 | I48: =VLOOKUP(C48,'202310-202403出荷数total2403220951'!B:F,5,0) -> 594 | J48: =VLOOKUP(C48,'出荷数2307～2406total241008110618'!B:F,5,0) -> 1198 | K48: =VLOOKUP(C48,'出荷数2407-2506total250730101950'!B:F,5,0) -> 1234 | L48: =VLOOKUP(C:C,total251219111800!B:F,5,0) -> 693 | N48: =L48 -> 693 | O48: 646 | P48: 0 | Q48: 0 | R48: 0 | S48: 0 | T48: 0 | U48: 646 | V48: -47 | W48: 1.0727554 | X48: 廃版予定
A49: 44 | B49: 伊賀 | C49: ABO-11 | D49: 防炎非常持出袋 | F49: 5224 | G49: 1145 | H49: 1174 | I49: =VLOOKUP(C49,'202310-202403出荷数total2403220951'!B:F,5,0) -> 435 | J49: =VLOOKUP(C49,'出荷数2307～2406total241008110618'!B:F,5,0) -> 653 | K49: =VLOOKUP(C49,'出荷数2407-2506total250730101950'!B:F,5,0) -> 1213 | L49: =VLOOKUP(C:C,total251219111800!B:F,5,0) -> 373 | N49: =L49 -> 373 | O49: 3582 | P49: 0 | Q49: 0 | R49: 0 | S49: 0 | T49: 0 | U49: 3582 | V49: 3209 | W49: 0.10413177
A50: 45 | B50: 伊賀 | C50: ANS-302BK | D50: テレビの音も聞こえる 手もとスピーカーⅡ | G50: 537 | H50: 3033 | I50: =VLOOKUP(C50,'202310-202403出荷数total2403220951'!B:F,5,0) -> 1920 | J50: =VLOOKUP(C50,'出荷数2307～2406total241008110618'!B:F,5,0) -> 4184 | K50: =VLOOKUP(C50,'出荷数2407-2506total250730101950'!B:F,5,0) -> 3497 | L50: =VLOOKUP(C:C,total251219111800!B:F,5,0) -> 1086 | M50: 750 | N50: =L50 -> 1086 | O50: 4656 | P50: 840 | Q50: 0 | R50: 0 | S50: 900 | T50: -60 | U50: 3756 | V50: 2670 | W50: 0.19759825
A51: 46 | B51: 伊賀 | C51: APL-3207SMO | D51: LEDのインテリア常備灯(化粧箱) | E51: 木目 | F51: 1023 | G51: 517 | H51: 437 | I51: =VLOOKUP(C51,'202310-202403出荷数total2403220951'!B:F,5,0) -> 346 | J51: =VLOOKUP(C51,'出荷数2307～2406total241008110618'!B:F,5,0) -> 396 | K51: =VLOOKUP(C51,'出荷数2407-2506total250730101950'!B:F,5,0) -> 187 | L51: =VLOOKUP(C:C,total251219111800!B:F,5,0) -> 6 | N51: =L51 -> 6 | O51: 1257 | P51: 600 | Q51: 0 | R51: 0 | S51: 600 | T51: 0 | U51: 657 | V51: 651 | W51: 0.0032310178 | X51: 廃版予定
A52: 47 | B52: 伊賀 | C52: AST-3304 | D52: LEDスタンドライト | F52: 843 | G52: 647 | H52: 2107 | I52: =VLOOKUP(C52,'202310-202403出荷数total2403220951'!B:F,5,0) -> #N/A | J52: =VLOOKUP(C52,'出荷数2307～2406total241008110618'!B:F,5,0) -> #N/A | K52: =VLOOKUP(C52,'出荷数2407-2506total250730101950'!B:F,5,0) -> #N/A | L52: =VLOOKUP(C:C,total251219111800!B:F,5,0) -> #N/A | M52: 890 | N52: 890 | O52: 0 | P52: 0 | Q52: 0 | R52: 0 | S52: 0 | T52: 0 | U52: 0 | V52: -890 | W52: #DIV/0!
A53: 48 | B53: 伊賀 | C53: ASL-3305 | D53: 足もと安心防雨センサーライト | F53: 1465 | G53: 1744 | H53: 888 | I53: =VLOOKUP(C53,'202310-202403出荷数total2403220951'!B:F,5,0) -> 559 | J53: =VLOOKUP(C53,'出荷数2307～2406total241008110618'!B:F,5,0) -> 1133 | K53: =VLOOKUP(C53,'出荷数2407-2506total250730101950'!B:F,5,0) -> 829 | L53: =VLOOKUP(C:C,total251219111800!B:F,5,0) -> 200 | N53: =L53 -> 200 | O53: 3367 | P53: 0 | Q53: 0 | R53: 0 | S53: 0 | T53: 0 | U53: 3367 | V53: 3167 | W53: 0.059400059
A54: 49 | B54: 伊賀 | C54: AHA-43ENAUTO | D54: 自動点灯ｻｲｸﾙﾗｲﾄ(ﾊﾝﾄﾞﾙﾀﾞｲﾅﾓ取付) | F54: 1087 | G54: 665 | H54: 2030 | I54: =VLOOKUP(C54,'202310-202403出荷数total2403220951'!B:F,5,0) -> #N/A | J54: =VLOOKUP(C54,'出荷数2307～2406total241008110618'!B:F,5,0) -> #N/A | K54: =VLOOKUP(C54,'出荷数2407-2506total250730101950'!B:F,5,0) -> #N/A | L54: =VLOOKUP(C:C,total251219111800!B:F,5,0) -> #N/A | M54: 850 | N54: 850 | O54: 2 | P54: 0 | Q54: 0 | R54: 0 | S54: 0 | T54: 0 | U54: 2 | V54: -848 | W54: 425
A55: 50 | B55: 伊賀 | C55: AIC-04IV | D55: ｽﾞﾚにくいｲｽ脚ｶﾊﾞｰ 4脚用 | E55: IV | F55: 2129 | G55: 2065 | H55: 2439 | I55: =VLOOKUP(C55,'202310-202403出荷数total2403220951'!B:F,5,0) -> 805 | J55: =VLOOKUP(C55,'出荷数2307～2406total241008110618'!B:F,5,0) -> 1939 | K55: =VLOOKUP(C55,'出荷数2407-2506total250730101950'!B:F,5,0) -> 1171 | L55: =VLOOKUP(C:C,total251219111800!B:F,5,0) -> 566 | N55: =L55 -> 566 | O55: 830 | P55: 0 | Q55: 0 | R55: 0 | S55: 0 | T55: 0 | U55: 830 | V55: 264 | W55: 0.68192771 | X55: 48％発注点よりﾏｲﾅｽ 566→295 | Y55: 48％発注点よりﾏｲﾅｽ 566→295
A56: 51 | B56: 伊賀 | C56: ABO-13M | D56: ぬげにくい安全スリッパM | F56: 1540 | G56: 597 | H56: 361 | I56: =VLOOKUP(C56,'202310-202403出荷数total2403220951'!B:F,5,0) -> 533 | J56: =VLOOKUP(C56,'出荷数2307～2406total241008110618'!B:F,5,0) -> 858 | K56: =VLOOKUP(C56,'出荷数2407-2506total250730101950'!B:F,5,0) -> 574 | L56: =VLOOKUP(C:C,total251219111800!B:F,5,0) -> #N/A | N56: =L56 -> #N/A | O56: 0 | P56: 0 | Q56: 0 | R56: 0 | S56: 0 | T56: 0 | U56: 0 | V56: #N/A | W56: #N/A
A57: 52 | B57: 伊賀 | C57: ABO-2907 | D57: 水タンクにもなる水のう袋 7枚入り | G57: 2665 | H57: 2710 | I57: =VLOOKUP(C57,'202310-202403出荷数total2403220951'!B:F,5,0) -> 1020 | J57: =VLOOKUP(C57,'出荷数2307～2406total241008110618'!B:F,5,0) -> 7751 | K57: =VLOOKUP(C57,'出荷数2407-2506total250730101950'!B:F,5,0) -> 21996 | L57: =VLOOKUP(C:C,total251219111800!B:F,5,0) -> 8163 | M57: 10000 | N57: 10000 | O57: 21214 | P57: 600 | Q57: 0 | R57: 0 | S57: 2110 | T57: -1510 | U57: 19104 | V57: 9104 | W57: 0.4584212
A58: 53 | B58: 伊賀 | C58: ALA-4306 | D58: ＬＥＤポケットランタンⅡ 廃版 | F58: 756 | G58: 52 | H58: 44 | I58: =VLOOKUP(C58,'202310-202403出荷数total2403220951'!B:F,5,0) -> 47 | J58: =VLOOKUP(C58,'出荷数2307～2406total241008110618'!B:F,5,0) -> 67 | K58: =VLOOKUP(C58,'出荷数2407-2506total250730101950'!B:F,5,0) -> 12 | L58: =VLOOKUP(C:C,total251219111800!B:F,5,0) -> 2 | N58: =L58 -> 2 | O58: 37 | P58: 0 | Q58: 0 | R58: 0 | S58: 0 | T58: 0 | U58: 37 | V58: 35 | W58: 0.054054054
A59: 54 | B59: 伊賀 | C59: ADC-311WH | D59: 単３が３個で単１電池アダプター | F59: 5239 | G59: 4870 | H59: 3762 | I59: =VLOOKUP(C59,'202310-202403出荷数total2403220951'!B:F,5,0) -> 1545 | J59: =VLOOKUP(C59,'出荷数2307～2406total241008110618'!B:F,5,0) -> 2638 | K59: =VLOOKUP(C59,'出荷数2407-2506total250730101950'!B:F,5,0) -> 3321 | L59: =VLOOKUP(C:C,total251219111800!B:F,5,0) -> 1045 | N59: =L59 -> 1045 | O59: 7386 | P59: 0 | Q59: 0 | R59: 0 | S59: 0 | T59: 0 | U59: 7386 | V59: 6341 | W59: 0.14148389
A60: 55 | B60: 伊賀 | C60: AKO-10 | D60: こたつ専用収納ポケットS | E60: BR | F60: 1332 | G60: 1490 | H60: 2200 | I60: =VLOOKUP(C60,'202310-202403出荷数total2403220951'!B:F,5,0) -> 339 | J60: =VLOOKUP(C60,'出荷数2307～2406total241008110618'!B:F,5,0) -> 1289 | K60: =VLOOKUP(C60,'出荷数2407-2506total250730101950'!B:F,5,0) -> 1155 | L60: =VLOOKUP(C:C,total251219111800!B:F,5,0) -> 362 | N60: =L60 -> 362 | O60: 3819 | P60: 0 | Q60: 0 | R60: 0 | S60: 0 | T60: 0 | U60: 3819 | V60: 3457 | W60: 0.094789212
A61: 56 | B61: 伊賀 | C61: AHM-108 | D61: 録音できるハンドメガホン | F61: 1177 | G61: 1274 | H61: 1310 | I61: =VLOOKUP(C61,'202310-202403出荷数total2403220951'!B:F,5,0) -> 484 | J61: =VLOOKUP(C61,'出荷数2307～2406total241008110618'!B:F,5,0) -> 984 | K61: =VLOOKUP(C61,'出荷数2407-2506total250730101950'!B:F,5,0) -> 1414 | L61: =VLOOKUP(C:C,total251219111800!B:F,5,0) -> 852 | N61: =L61 -> 852 | O61: 1103 | P61: 100 | Q61: 0 | R61: 0 | S61: 100 | T61: 0 | U61: 1003 | V61: 151 | W61: 0.70822943
A62: 57 | B62: 伊賀 | C62: ASK-04 | D62: 光るスポークかざり ビーズ | F62: 2501 | G62: 1137 | H62: 1254 | I62: =VLOOKUP(C62,'202310-202403出荷数total2403220951'!B:F,5,0) -> 1064 | J62: =VLOOKUP(C62,'出荷数2307～2406total241008110618'!B:F,5,0) -> 1296 | K62: =VLOOKUP(C62,'出荷数2407-2506total250730101950'!B:F,5,0) -> 172 | L62: =VLOOKUP(C:C,total251219111800!B:F,5,0) -> 765 | N62: =L62 -> 765 | O62: 2110 | P62: 2000 | Q62: 0 | R62: 0 | S62: 2000 | T62: 0 | U62: 110 | V62: -655 | W62: 0.18613139 | Y62: 様子見
A63: 58 | B63: 伊賀 | C63: ASK-10SI | D63: 光るホイール反射シール | E63: シルバー | F63: 600 | G63: 225 | H63: 22 | I63: =VLOOKUP(C63,'202310-202403出荷数total2403220951'!B:F,5,0) -> 1 | J63: =VLOOKUP(C63,'出荷数2307～2406total241008110618'!B:F,5,0) -> 1 | K63: =VLOOKUP(C63,'出荷数2407-2506total250730101950'!B:F,5,0) -> #N/A | L63: =VLOOKUP(C:C,total251219111800!B:F,5,0) -> #N/A | N63: =L63 -> #N/A | O63: 552 | P63: 0 | Q63: 0 | R63: 0 | S63: 0 | T63: 0 | U63: 552 | V63: #N/A | W63: #N/A
A64: 59 | B64: 伊賀 | C64: ASK-13 | D64: 光るホイール反射シール | F64: 600 | G64: 225 | H64: 0 | I64: =VLOOKUP(C64,'202310-202403出荷数total2403220951'!B:F,5,0) -> 10 | J64: =VLOOKUP(C64,'出荷数2307～2406total241008110618'!B:F,5,0) -> 11 | K64: =VLOOKUP(C64,'出荷数2407-2506total250730101950'!B:F,5,0) -> 8 | L64: =VLOOKUP(C:C,total251219111800!B:F,5,0) -> 13 | N64: =L64 -> 13 | O64: 1965 | P64: 0 | Q64: 0 | R64: 0 | S64: 0 | T64: 0 | U64: 1965 | V64: 1952 | W64: 0.0066157761
A65: 60 | B65: 伊賀 | C65: ASK-06YE | D65: はめるだけ光る 足腕バンド | E65: イエロー | F65: 46 | G65: 271 | H65: 10 | I65: =VLOOKUP(C65,'202310-202403出荷数total2403220951'!B:F,5,0) -> 50 | J65: =VLOOKUP(C65,'出荷数2307～2406total241008110618'!B:F,5,0) -> 53 | K65: =VLOOKUP(C65,'出荷数2407-2506total250730101950'!B:F,5,0) -> 93 | L65: =VLOOKUP(C:C,total251219111800!B:F,5,0) -> 13 | M65: 500 | N65: 500 | O65: 2320 | P65: 0 | Q65: 0 | R65: 0 | S65: 0 | T65: 0 | U65: 2320 | V65: 1820 | W65: 0.21551724
A66: 61 | B66: 伊賀 | C66: AHA-4307 | D66: 自動点灯サイクルライトⅡ | F66: 1006 | G66: 417 | H66: 772 | I66: =VLOOKUP(C66,'202310-202403出荷数total2403220951'!B:F,5,0) -> 650 | J66: =VLOOKUP(C66,'出荷数2307～2406total241008110618'!B:F,5,0) -> 1155 | K66: =VLOOKUP(C66,'出荷数2407-2506total250730101950'!B:F,5,0) -> 373 | L66: =VLOOKUP(C:C,total251219111800!B:F,5,0) -> 484 | N66: =L66 -> 484 | O66: 1330 | P66: 0 | Q66: 0 | R66: 0 | S66: 0 | T66: 0 | U66: 1330 | V66: 846 | W66: 0.36390977
A67: 62 | B67: 伊賀 | C67: ALA-4311 | D67: くるっとハンディランタンライト | F67: 856 | G67: 1296 | H67: 948 | I67: =VLOOKUP(C67,'202310-202403出荷数total2403220951'!B:F,5,0) -> 92 | J67: =VLOOKUP(C67,'出荷数2307～2406total241008110618'!B:F,5,0) -> 191 | K67: =VLOOKUP(C67,'出荷数2407-2506total250730101950'!B:F,5,0) -> 1768 | L67: =VLOOKUP(C:C,total251219111800!B:F,5,0) -> 749 | M67: 500 | N67: =L67 -> 749 | O67: 2735 | P67: 0 | Q67: 0 | R67: 0 | S67: 180 | T67: -180 | U67: 2555 | V67: 1806 | W67: 0.2738574
A68: 63 | B68: 伊賀 | C68: AIC-05IV | D68: ｽﾞﾚにくいｲｽ脚ｶﾊﾞｰ 1脚用 | E68: IV | F68: 2715 | G68: 1898 | H68: 1974 | I68: =VLOOKUP(C68,'202310-202403出荷数total2403220951'!B:F,5,0) -> 822 | J68: =VLOOKUP(C68,'出荷数2307～2406total241008110618'!B:F,5,0) -> 1831 | K68: =VLOOKUP(C68,'出荷数2407-2506total250730101950'!B:F,5,0) -> 1431 | L68: =VLOOKUP(C:C,total251219111800!B:F,5,0) -> 874 | N68: =L68 -> 874 | O68: 4074 | P68: 0 | Q68: 0 | R68: 0 | S68: 0 | T68: 0 | U68: 4074 | V68: 3200 | W68: 0.21453117 | X68: 23％発注点よりﾏｲﾅｽ 874→672 | Y68: 23％発注点よりﾏｲﾅｽ 874→672
A69: 64 | B69: 伊賀 | C69: ABO-19 | D69: 防災用薄型ウォーターバッグ9L | F69: 680 | G69: 2488 | H69: 824 | I69: =VLOOKUP(C69,'202310-202403出荷数total2403220951'!B:F,5,0) -> 454 | J69: =VLOOKUP(C69,'出荷数2307～2406total241008110618'!B:F,5,0) -> 939 | K69: =VLOOKUP(C69,'出荷数2407-2506total250730101950'!B:F,5,0) -> 1427 | L69: =VLOOKUP(C:C,total251219111800!B:F,5,0) -> 203 | N69: =L69 -> 203 | O69: 2685 | P69: 0 | Q69: 0 | R69: 0 | S69: 0 | T69: 0 | U69: 2685 | V69: 2482 | W69: 0.075605214
A70: 65 | B70: 伊賀 | C70: AYC-101PK | D70: 耳すっきりクリーナー | E70: ピンク | F70: 1433 | G70: 1030 | H70: 1015 | I70: =VLOOKUP(C70,'202310-202403出荷数total2403220951'!B:F,5,0) -> 273 | J70: =VLOOKUP(C70,'出荷数2307～2406total241008110618'!B:F,5,0) -> 828 | K70: =VLOOKUP(C70,'出荷数2407-2506total250730101950'!B:F,5,0) -> 776 | L70: =VLOOKUP(C:C,total251219111800!B:F,5,0) -> 430 | N70: =L70 -> 430 | O70: 1908 | P70: 90 | Q70: 0 | R70: 0 | S70: 90 | T70: 0 | U70: 1818 | V70: 1388 | W70: 0.21521522
A71: 66 | B71: 伊賀 | C71: AUV-3301 | D71: 見えにくい汚れの発見ライト | G71: 600 | H71: 106 | I71: =VLOOKUP(C71,'202310-202403出荷数total2403220951'!B:F,5,0) -> 250 | J71: =VLOOKUP(C71,'出荷数2307～2406total241008110618'!B:F,5,0) -> 351 | K71: =VLOOKUP(C71,'出荷数2407-2506total250730101950'!B:F,5,0) -> 157 | L71: =VLOOKUP(C:C,total251219111800!B:F,5,0) -> #N/A | N71: =L71 -> #N/A | O71: 2381 | P71: 0 | Q71: 0 | R71: 0 | S71: 0 | T71: 0 | U71: 2381 | V71: #N/A | W71: #N/A
B72: 伊賀 | C72: AUV-3301C | D72: 365nmUVﾗｲﾄ | H72: 100 | I72: =VLOOKUP(C72,'202310-202403出荷数total2403220951'!B:F,5,0) -> 17 | J72: =VLOOKUP(C72,'出荷数2307～2406total241008110618'!B:F,5,0) -> 35 | K72: =VLOOKUP(C72,'出荷数2407-2506total250730101950'!B:F,5,0) -> 80 | L72: =VLOOKUP(C:C,total251219111800!B:F,5,0) -> 16 | N72: =L72 -> 16 | O72: 303 | P72: 0 | Q72: 0 | R72: 0 | S72: 0 | T72: 0 | U72: 303 | V72: 287 | W72: 0.052805281
A73: 67 | B73: 伊賀 | C73: AHL-1101 | D73: 単３と単１が使ええる防水ライト | F73: 4431 | G73: 2178 | H73: 3224 | I73: =VLOOKUP(C73,'202310-202403出荷数total2403220951'!B:F,5,0) -> 2952 | J73: =VLOOKUP(C73,'出荷数2307～2406total241008110618'!B:F,5,0) -> 5989 | K73: =VLOOKUP(C73,'出荷数2407-2506total250730101950'!B:F,5,0) -> 4689 | L73: =VLOOKUP(C:C,total251219111800!B:F,5,0) -> 1757 | N73: =L73 -> 1757 | O73: 6106 | P73: 200 | Q73: 0 | R73: 0 | S73: 200 | T73: 0 | U73: 5906 | V73: 4149 | W73: 0.27862353
A74: 68 | B74: 伊賀 | C74: ABO-03 | D74: 防災用ポリバケツ | F74: 3496 | G74: 2391 | H74: 1985 | I74: =VLOOKUP(C74,'202310-202403出荷数total2403220951'!B:F,5,0) -> 1236 | J74: =VLOOKUP(C74,'出荷数2307～2406total241008110618'!B:F,5,0) -> 2298 | K74: =VLOOKUP(C74,'出荷数2407-2506total250730101950'!B:F,5,0) -> 8616 | L74: =VLOOKUP(C:C,total251219111800!B:F,5,0) -> 1136 | M74: 8000 | N74: 8000 | O74: 14699 | P74: 3200 | Q74: 0 | R74: 0 | S74: 5200 | T74: -2000 | U74: 9499 | V74: 1499 | W74: 0.44695234
A75: 69 | B75: 伊賀 | C75: KCA-002 | D75: キューベルク 充電式ヘッドライト270 | F75: 44 | G75: 866 | H75: 614 | I75: =VLOOKUP(C75,'202310-202403出荷数total2403220951'!B:F,5,0) -> 333 | J75: =VLOOKUP(C75,'出荷数2307～2406total241008110618'!B:F,5,0) -> 1142 | K75: =VLOOKUP(C75,'出荷数2407-2506total250730101950'!B:F,5,0) -> 925 | L75: =VLOOKUP(C:C,total251219111800!B:F,5,0) -> 135 | N75: =L75 -> 135 | O75: 1771 | P75: 0 | Q75: 0 | R75: 0 | S75: 0 | T75: 0 | U75: 1771 | V75: 1636 | W75: 0.07622812
A76: 70 | B76: 伊賀 | C76: AHM-201 | D76: 防雨ハンドメガホン | F76: 410 | G76: 741 | H76: 1112 | I76: =VLOOKUP(C76,'202310-202403出荷数total2403220951'!B:F,5,0) -> 662 | J76: =VLOOKUP(C76,'出荷数2307～2406total241008110618'!B:F,5,0) -> 1332 | K76: =VLOOKUP(C76,'出荷数2407-2506total250730101950'!B:F,5,0) -> 2848 | L76: =VLOOKUP(C:C,total251219111800!B:F,5,0) -> 1014 | M76: 1000 | N76: =L76 -> 1014 | O76: 1665 | P76: 200 | Q76: 3000 | R76: 0 | S76: 200 | T76: 0 | U76: 4465 | V76: 3451 | W76: 0.54369973
A77: 71 | B77: 伊賀 | C77: AAM-200 | D77: 雨ふりセンサーⅡ | F77: 1477 | G77: 1110 | H77: 696 | I77: =VLOOKUP(C77,'202310-202403出荷数total2403220951'!B:F,5,0) -> 116 | J77: =VLOOKUP(C77,'出荷数2307～2406total241008110618'!B:F,5,0) -> 801 | K77: =VLOOKUP(C77,'出荷数2407-2506total250730101950'!B:F,5,0) -> 703 | L77: =VLOOKUP(C:C,total251219111800!B:F,5,0) -> 319 | N77: =L77 -> 319 | O77: 429 | P77: 0 | Q77: 0 | R77: 0 | S77: 0 | T77: 0 | U77: 429 | V77: 110 | W77: 0.74358974 | X77: 在庫減ってから発注。発注ロット2000希望 | Y77: 在庫減ってから発注。発注ロット2000希望
A78: 72 | B78: 伊賀 | C78: AHA-4306 | D78: 自動点灯前かごクリップライト | F78: 1324 | G78: 1622 | H78: 1792 | I78: =VLOOKUP(C78,'202310-202403出荷数total2403220951'!B:F,5,0) -> 1087 | J78: =VLOOKUP(C78,'出荷数2307～2406total241008110618'!B:F,5,0) -> 1970 | K78: =VLOOKUP(C78,'出荷数2407-2506total250730101950'!B:F,5,0) -> 1824 | L78: =VLOOKUP(C:C,total251219111800!B:F,5,0) -> 900 | N78: =L78 -> 900 | O78: 2935 | P78: 0 | Q78: 0 | R78: 0 | S78: 0 | T78: 0 | U78: 2935 | V78: 2035 | W78: 0.30664395
A79: 73 | B79: 伊賀 | C79: KCA-001 | D79: キューベルク 充電式ヘッドライト220 | F79: 30 | G79: 1288 | H79: 1790 | I79: =VLOOKUP(C79,'202310-202403出荷数total2403220951'!B:F,5,0) -> 845 | J79: =VLOOKUP(C79,'出荷数2307～2406total241008110618'!B:F,5,0) -> 1682 | K79: =VLOOKUP(C79,'出荷数2407-2506total250730101950'!B:F,5,0) -> 1326 | L79: =VLOOKUP(C:C,total251219111800!B:F,5,0) -> 366 | N79: =L79 -> 366 | O79: 1753 | P79: 0 | Q79: 0 | R79: 0 | S79: 0 | T79: 0 | U79: 1753 | V79: 1387 | W79: 0.20878494
A80: 74 | B80: 伊賀 | C80: AOM-01 | D80: かんたんお話メモ | F80: 6851 | G80: 3631 | H80: 3310 | I80: =VLOOKUP(C80,'202310-202403出荷数total2403220951'!B:F,5,0) -> 2276 | J80: =VLOOKUP(C80,'出荷数2307～2406total241008110618'!B:F,5,0) -> 2977 | K80: =VLOOKUP(C80,'出荷数2407-2506total250730101950'!B:F,5,0) -> 1413 | L80: =VLOOKUP(C:C,total251219111800!B:F,5,0) -> 456 | N80: =L80 -> 456 | O80: 2273 | P80: 200 | Q80: 0 | R80: 0 | S80: 200 | T80: 0 | U80: 2073 | V80: 1617 | W80: 0.18439143
A81: 75 | B81: 伊賀 | C81: AKM-3205BL | D81: 首ふり毛だまクリーナー | E81: ブルー | F81: 7367 | G81: 4388 | H81: 521 | I81: =VLOOKUP(C81,'202310-202403出荷数total2403220951'!B:F,5,0) -> 2848 | J81: =VLOOKUP(C81,'出荷数2307～2406total241008110618'!B:F,5,0) -> 3288 | K81: =VLOOKUP(C81,'出荷数2407-2506total250730101950'!B:F,5,0) -> 2304 | L81: =VLOOKUP(C:C,total251219111800!B:F,5,0) -> 744 | N81: =L81 -> 744 | O81: 4645 | P81: 3880 | Q81: 0 | R81: 0 | S81: 3880 | T81: 0 | U81: 765 | V81: 21 | W81: 0.087272727
A82: 76 | B82: 伊賀 | C82: ABO-12 | D82: 防災用ポリタンク 10L | F82: 10633 | G82: 6065 | H82: 2945 | I82: =VLOOKUP(C82,'202310-202403出荷数total2403220951'!B:F,5,0) -> 3324 | J82: =VLOOKUP(C82,'出荷数2307～2406total241008110618'!B:F,5,0) -> 5243 | K82: =VLOOKUP(C82,'出荷数2407-2506total250730101950'!B:F,5,0) -> 13654 | L82: =VLOOKUP(C:C,total251219111800!B:F,5,0) -> 1335 | M82: 4500 | N82: 3000 | O82: 6972 | P82: 3060 | Q82: 0 | R82: 0 | S82: 3160 | T82: -100 | U82: 3812 | V82: 812 | W82: 0.29904306
A83: 77 | B83: 伊賀 | C83: ALA-4310 | D83: ゆれたら点灯ライト(クリアケース) | F83: 270 | G83: 814 | H83: 677 | I83: =VLOOKUP(C83,'202310-202403出荷数total2403220951'!B:F,5,0) -> 269 | J83: =VLOOKUP(C83,'出荷数2307～2406total241008110618'!B:F,5,0) -> 668 | K83: =VLOOKUP(C83,'出荷数2407-2506total250730101950'!B:F,5,0) -> 826 | L83: =VLOOKUP(C:C,total251219111800!B:F,5,0) -> 90 | N83: =L83 -> 90 | O83: 2443 | P83: 0 | Q83: 0 | R83: 0 | S83: 0 | T83: 0 | U83: 2443 | V83: 2353 | W83: 0.036839951
A84: 78 | B84: 伊賀 | C84: ALA-3301 | D84: てるてるランタン | F84: 3306 | G84: 2817 | H84: 1743 | I84: =VLOOKUP(C84,'202310-202403出荷数total2403220951'!B:F,5,0) -> 273 | J84: =VLOOKUP(C84,'出荷数2307～2406total241008110618'!B:F,5,0) -> 477 | K84: =VLOOKUP(C84,'出荷数2407-2506total250730101950'!B:F,5,0) -> 351 | L84: =VLOOKUP(C:C,total251219111800!B:F,5,0) -> 211 | N84: =L84 -> 211 | O84: 7233 | P84: 0 | Q84: 0 | R84: 0 | S84: 0 | T84: 0 | U84: 7233 | V84: 7022 | W84: 0.029171851
A85: 79 | B85: 伊賀 | C85: ARO-02 | D85: 自動消灯安心のろうそくミニ | F85: 1177 | G85: 2128 | H85: 1537 | I85: =VLOOKUP(C85,'202310-202403出荷数total2403220951'!B:F,5,0) -> 834 | J85: =VLOOKUP(C85,'出荷数2307～2406total241008110618'!B:F,5,0) -> 1486 | K85: =VLOOKUP(C85,'出荷数2407-2506total250730101950'!B:F,5,0) -> 1411 | L85: =VLOOKUP(C:C,total251219111800!B:F,5,0) -> 822 | N85: =L85 -> 822 | O85: 2538 | P85: 0 | Q85: 0 | R85: 0 | S85: 0 | T85: 0 | U85: 2538 | V85: 1716 | W85: 0.32387707
A86: 80 | B86: 伊賀 | C86: ACR-01 | D86: スイッチ付きコードリール | F86: 1511 | G86: 1031 | H86: 1052 | I86: =VLOOKUP(C86,'202310-202403出荷数total2403220951'!B:F,5,0) -> 513 | J86: =VLOOKUP(C86,'出荷数2307～2406total241008110618'!B:F,5,0) -> 546 | K86: =VLOOKUP(C86,'出荷数2407-2506total250730101950'!B:F,5,0) -> #N/A | L86: =VLOOKUP(C:C,total251219111800!B:F,5,0) -> #N/A | N86: =L86 -> #N/A | O86: 0 | P86: 0 | Q86: 0 | R86: 0 | S86: 0 | T86: 0 | U86: 0 | V86: #N/A | W86: #N/A
A87: 81 | B87: 伊賀 | C87: AKR-20 | D87: ねこのキーカバー | F87: 3121 | G87: 3233 | H87: 3120 | I87: =VLOOKUP(C87,'202310-202403出荷数total2403220951'!B:F,5,0) -> 1553 | J87: =VLOOKUP(C87,'出荷数2307～2406total241008110618'!B:F,5,0) -> 3072 | K87: =VLOOKUP(C87,'出荷数2407-2506total250730101950'!B:F,5,0) -> 3947 | L87: =VLOOKUP(C:C,total251219111800!B:F,5,0) -> 1574 | N87: =L87 -> 1574 | O87: 4224 | P87: 0 | Q87: 0 | R87: 0 | S87: 0 | T87: 0 | U87: 4224 | V87: 2650 | W87: 0.37263258
A88: 82 | B88: 伊賀 | C88: AYD-102AD | D88: 電話の拡声器 ⅡＡＣアダプター | F88: 1334 | G88: 1879 | H88: 908 | I88: =VLOOKUP(C88,'202310-202403出荷数total2403220951'!B:F,5,0) -> 222 | J88: =VLOOKUP(C88,'出荷数2307～2406total241008110618'!B:F,5,0) -> 732 | K88: =VLOOKUP(C88,'出荷数2407-2506total250730101950'!B:F,5,0) -> 817 | L88: =VLOOKUP(C:C,total251219111800!B:F,5,0) -> 295 | N88: =L88 -> 295 | O88: 293 | P88: 0 | Q88: 0 | R88: 0 | S88: 0 | T88: 0 | U88: 293 | V88: -2 | W88: 1.0068259
A89: 83 | B89: 伊賀 | C89: AKR-11 | D89: シリコンキーカバー | F89: 3215 | G89: 3856 | H89: 4252 | I89: =VLOOKUP(C89,'202310-202403出荷数total2403220951'!B:F,5,0) -> 2413 | J89: =VLOOKUP(C89,'出荷数2307～2406total241008110618'!B:F,5,0) -> 4143 | K89: =VLOOKUP(C89,'出荷数2407-2506total250730101950'!B:F,5,0) -> 6112 | L89: =VLOOKUP(C:C,total251219111800!B:F,5,0) -> 2918 | N89: =L89 -> 2918 | O89: 4033 | P89: 0 | Q89: 0 | R89: 0 | S89: 0 | T89: 0 | U89: 4033 | V89: 1115 | W89: 0.72353087
A90: 84 | B90: 伊賀 | C90: AST-3401 | D90: スマホが充電できるスタンドライト | F90: 102 | G90: 340 | H90: 49 | I90: =VLOOKUP(C90,'202310-202403出荷数total2403220951'!B:F,5,0) -> 6 | J90: =VLOOKUP(C90,'出荷数2307～2406total241008110618'!B:F,5,0) -> 434 | K90: =VLOOKUP(C90,'出荷数2407-2506total250730101950'!B:F,5,0) -> #N/A | L90: =VLOOKUP(C:C,total251219111800!B:F,5,0) -> #N/A | N90: =L90 -> #N/A | O90: 0 | P90: 0 | Q90: 0 | R90: 0 | S90: 0 | T90: 0 | U90: 0 | V90: #N/A | W90: #N/A
A91: 85 | B91: 伊賀 | C91: ASL-3310 | D91: マグネット付くるっと回るセンサーライト | F91: 1538 | G91: 2587 | H91: 571 | I91: =VLOOKUP(C91,'202310-202403出荷数total2403220951'!B:F,5,0) -> 874 | J91: =VLOOKUP(C91,'出荷数2307～2406total241008110618'!B:F,5,0) -> 1045 | K91: =VLOOKUP(C91,'出荷数2407-2506total250730101950'!B:F,5,0) -> 429 | L91: =VLOOKUP(C:C,total251219111800!B:F,5,0) -> 22 | M91: 1400 | N91: 1400 | O91: 4435 | P91: 100 | Q91: 0 | R91: 0 | S91: 100 | T91: 0 | U91: 4335 | V91: 2935 | W91: 0.30871003
A92: 87 | B92: 伊賀 | C92: ASL-3303 | D92: ドア用センサーライト | F92: 8125 | G92: 7398 | H92: 4528 | I92: =VLOOKUP(C92,'202310-202403出荷数total2403220951'!B:F,5,0) -> 1614 | J92: =VLOOKUP(C92,'出荷数2307～2406total241008110618'!B:F,5,0) -> 3692 | K92: =VLOOKUP(C92,'出荷数2407-2506total250730101950'!B:F,5,0) -> 3180 | L92: =VLOOKUP(C:C,total251219111800!B:F,5,0) -> 1448 | N92: =L92 -> 1448 | O92: 5615 | P92: 715 | Q92: 40 | R92: 0 | S92: 1245 | T92: -530 | U92: 4410 | V92: 2962 | W92: 0.22875197
A93: 88 | B93: 伊賀 | C93: ASL-33032 | D93: ドア用センサーライト（ｼｮｯﾌﾟﾁｬﾝﾈﾙ） | F93: 0 | G93: 5 | H93: 904 | I93: =VLOOKUP(C93,'202310-202403出荷数total2403220951'!B:F,5,0) -> #N/A | J93: =VLOOKUP(C93,'出荷数2307～2406total241008110618'!B:F,5,0) -> #N/A | K93: =VLOOKUP(C93,'出荷数2407-2506total250730101950'!B:F,5,0) -> #N/A | L93: =VLOOKUP(C:C,total251219111800!B:F,5,0) -> #N/A | M93: 380 | N93: 380 | O93: 781 | P93: 0 | Q93: 0 | R93: 0 | S93: 0 | T93: 0 | U93: 781 | V93: 401 | W93: 0.4865557
A94: 89 | B94: 伊賀 | C94: ASL-3303K | D94: ドア用センサーライト（ケーズ） | F94: 684 | G94: 626 | H94: 772 | I94: =VLOOKUP(C94,'202310-202403出荷数total2403220951'!B:F,5,0) -> 81 | J94: =VLOOKUP(C94,'出荷数2307～2406total241008110618'!B:F,5,0) -> 221 | K94: =VLOOKUP(C94,'出荷数2407-2506total250730101950'!B:F,5,0) -> #N/A | L94: =VLOOKUP(C:C,total251219111800!B:F,5,0) -> #N/A | N94: =L94 -> #N/A | O94: 3 | P94: 0 | Q94: 0 | R94: 0 | S94: 0 | T94: 0 | U94: 3 | V94: #N/A | W94: #N/A
A95: 90 | B95: 伊賀 | C95: AIC-04BE | D95: ｽﾞﾚにくいｲｽ脚ｶﾊﾞｰ 4脚用 | E95: BE | F95: 4518 | G95: 3870 | H95: 3467 | I95: =VLOOKUP(C95,'202310-202403出荷数total2403220951'!B:F,5,0) -> 1429 | J95: =VLOOKUP(C95,'出荷数2307～2406total241008110618'!B:F,5,0) -> 3078 | K95: =VLOOKUP(C95,'出荷数2407-2506total250730101950'!B:F,5,0) -> 3161 | L95: =VLOOKUP(C:C,total251219111800!B:F,5,0) -> 1695 | N95: =L95 -> 1695 | O95: 647 | P95: 0 | Q95: 3000 | R95: 0 | S95: 0 | T95: 0 | U95: 3647 | V95: 1952 | W95: 2.6197836 | X95: 48％発注点よりﾏｲﾅｽ 1695→881 | Y95: 48％発注点よりﾏｲﾅｽ 1695→881
A96: 91 | B96: 伊賀 | C96: AST-3303 | D96: スマホが置けるスタンドライト | F96: 12335 | G96: 8441 | H96: 3599 | I96: =VLOOKUP(C96,'202310-202403出荷数total2403220951'!B:F,5,0) -> 3021 | J96: =VLOOKUP(C96,'出荷数2307～2406total241008110618'!B:F,5,0) -> 4038 | K96: =VLOOKUP(C96,'出荷数2407-2506total250730101950'!B:F,5,0) -> 1769 | L96: =VLOOKUP(C:C,total251219111800!B:F,5,0) -> 560 | N96: =L96 -> 560 | O96: 9028 | P96: 1500 | Q96: 0 | R96: 0 | S96: 1500 | T96: 0 | U96: 7528 | V96: 6968 | W96: 0.053191489
A97: 92 | B97: 伊賀 | C97: AKM-3204PK | D97: 立てて置ける毛だまクリーナー | E97: ピンク | F97: 2663 | G97: 4626 | H97: 4263 | I97: =VLOOKUP(C97,'202310-202403出荷数total2403220951'!B:F,5,0) -> 1415 | J97: =VLOOKUP(C97,'出荷数2307～2406total241008110618'!B:F,5,0) -> 2582 | K97: =VLOOKUP(C97,'出荷数2407-2506total250730101950'!B:F,5,0) -> 2814 | L97: =VLOOKUP(C:C,total251219111800!B:F,5,0) -> 1960 | N97: =L97 -> 1960 | O97: 4443 | P97: 800 | Q97: 0 | R97: 0 | S97: 1250 | T97: -450 | U97: 3193 | V97: 1233 | W97: 0.37383178
A98: 93 | B98: 伊賀 | C98: ADR-100 | D98: ドライヤースタンド | F98: 3167 | G98: 3686 | H98: 4490 | I98: =VLOOKUP(C98,'202310-202403出荷数total2403220951'!B:F,5,0) -> 1027 | J98: =VLOOKUP(C98,'出荷数2307～2406total241008110618'!B:F,5,0) -> 2480 | K98: =VLOOKUP(C98,'出荷数2407-2506total250730101950'!B:F,5,0) -> 1578 | L98: =VLOOKUP(C:C,total251219111800!B:F,5,0) -> 247 | N98: =L98 -> 247 | O98: 2780 | P98: 0 | Q98: 0 | R98: 0 | S98: 0 | T98: 0 | U98: 2780 | V98: 2533 | W98: 0.088848921
A99: 94 | B99: 伊賀 | C99: AYC-101BL | D99: 耳すっきりクリーナー | E99: ブルー | F99: 5717 | H99: 3844 | I99: =VLOOKUP(C99,'202310-202403出荷数total2403220951'!B:F,5,0) -> 1058 | J99: =VLOOKUP(C99,'出荷数2307～2406total241008110618'!B:F,5,0) -> 2412 | K99: =VLOOKUP(C99,'出荷数2407-2506total250730101950'!B:F,5,0) -> 2874 | L99: =VLOOKUP(C:C,total251219111800!B:F,5,0) -> 1317 | N99: =L99 -> 1317 | O99: 2300 | P99: 220 | Q99: 0 | R99: 0 | S99: 340 | T99: -120 | U99: 1960 | V99: 643 | W99: 0.52261905
A100: 95 | B100: 伊賀 | C100: AHL-2203 | D100: 単2形LED防雨ライト | F100: 15469 | G100: 8369 | H100: 9994 | I100: =VLOOKUP(C100,'202310-202403出荷数total2403220951'!B:F,5,0) -> 2524 | J100: =VLOOKUP(C100,'出荷数2307～2406total241008110618'!B:F,5,0) -> 7246 | K100: =VLOOKUP(C100,'出荷数2407-2506total250730101950'!B:F,5,0) -> 19015 | L100: =VLOOKUP(C:C,total251219111800!B:F,5,0) -> 3771 | M100: 4500 | N100: 3000 | O100: 8009 | P100: 6870 | Q100: 3000 | R100: 0 | S100: 6870 | T100: 0 | U100: 4139 | V100: 1139 | W100: 0.20162645
...

Sheet 80116
B1: 商品センター | C1: 品番 | D1: 商品区分 | E1: カラー | F1: 72期 | G1: 73期 | H1: 74期(1期) | I1: 2023/10/1～2024/3/21（6か月） | J1: 75期(2期) | K1: 76期（３期 ） | L1: 77期（4期 7/1-12/18） | N1: 発注点 5ヶ月分なのでそのまま | O1: 在庫数 ロジザード | Q1: 入荷予定 ロジザード | S1: 確保数 弥生(在庫確保) | T1: 確保数チェック 0じゃなかったらロジザード修正 | U1: 有効数量 フリー在庫の数 | V1: 発注検討フラグ マイナスの場合発注検討 | W1: 在庫回転率 | X1: 前回決定事項（1/9/） | Y1: 決定事項 | AE1: 前回決定事項（/） | AG1: 決定事項
A2: 1 | B2: 伊賀 | C2: APL-4312SBL | D2: ミニホイッスル付LEDアルミライトⅡ | H2: 192 | I2: =VLOOKUP(C2,'202310-202403出荷数total2403220951'!B:F,5,0) -> 71 | J2: =VLOOKUP(C2,'出荷数2307～2406total241008110618'!B:F,5,0) -> 281 | K2: =VLOOKUP(C2,'出荷数2407-2506total250730101950'!B:F,5,0) -> 902 | L2: =VLOOKUP(C:C,total251219111800!B:F,5,0) -> 386 | N2: =L2 -> 386 | O2: 427 | P2: 710 | Q2: 0 | R2: 0 | S2: 550 | T2: 160 | U2: -123 | V2: -509 | W2: 0.33948989
A3: 2 | B3: 伊賀 | C3: APL-4312SPK | D3: ミニホイッスル付LEDアルミライトⅡ | H3: 2161 | I3: =VLOOKUP(C3,'202310-202403出荷数total2403220951'!B:F,5,0) -> 1018 | J3: =VLOOKUP(C3,'出荷数2307～2406total241008110618'!B:F,5,0) -> 1930 | K3: =VLOOKUP(C3,'出荷数2407-2506total250730101950'!B:F,5,0) -> 3388 | L3: =VLOOKUP(C:C,total251219111800!B:F,5,0) -> 903 | N3: =L3 -> 903 | O3: 2082 | P3: 1980 | Q3: 0 | R3: 0 | S3: 1830 | T3: 150 | U3: 252 | V3: -651 | W3: 0.22230428
A4: 86 | B4: 伊賀 | C4: ABO-08BL | D4: ミニホイッスル | E4: ブルー | F4: 527 | G4: 2107 | H4: 796 | I4: =VLOOKUP(C4,'202310-202403出荷数total2403220951'!B:F,5,0) -> 1409 | J4: =VLOOKUP(C4,'出荷数2307～2406total241008110618'!B:F,5,0) -> 1708 | K4: =VLOOKUP(C4,'出荷数2407-2506total250730101950'!B:F,5,0) -> 1865 | L4: =VLOOKUP(C:C,total251219111800!B:F,5,0) -> 474 | M4: 1000 | N4: 1000 | O4: 6772 | P4: 0 | Q4: 0 | R4: 0 | S4: 0 | T4: 0 | U4: 6772 | V4: 5772 | W4: 0.14766686
A5: 107 | B5: 伊賀 | C5: ABO-08PK | D5: ミニホイッスル | E5: ピンク | F5: 3939 | G5: 5966 | H5: 5009 | I5: =VLOOKUP(C5,'202310-202403出荷数total2403220951'!B:F,5,0) -> 6490 | J5: =VLOOKUP(C5,'出荷数2307～2406total241008110618'!B:F,5,0) -> 17931 | K5: =VLOOKUP(C5,'出荷数2407-2506total250730101950'!B:F,5,0) -> 28387 | L5: =VLOOKUP(C:C,total251219111800!B:F,5,0) -> 4495 | N5: =L5 -> 4495 | O5: 31152 | P5: 35250 | Q5: 800 | R5: 0 | S5: 24430 | T5: 10820 | U5: 7522 | V5: 3027 | W5: 0.067693744
A6: 109 | B6: 伊賀 | C6: APL-4302S | D6: ＬＥＤミニアルミライト | F6: 1094 | G6: 3475 | H6: 834 | I6: =VLOOKUP(C6,'202310-202403出荷数total2403220951'!B:F,5,0) -> 444 | J6: =VLOOKUP(C6,'出荷数2307～2406total241008110618'!B:F,5,0) -> 789 | K6: =VLOOKUP(C6,'出荷数2407-2506total250730101950'!B:F,5,0) -> 232 | L6: =VLOOKUP(C:C,total251219111800!B:F,5,0) -> 177 | N6: =L6 -> 177 | O6: 3754 | P6: 0 | Q6: 300 | R6: 0 | S6: 0 | T6: 0 | U6: 4054 | V6: 3877 | W6: 0.047149707
A7: 3 | B7: 伊賀 | C7: ASL-3308SK | D7: ウォールセンサーライト 箱 | E7: しかく | F7: 1 | G7: 0 | H7: 4 | I7: =VLOOKUP(C7,'202310-202403出荷数total2403220951'!B:F,5,0) -> #N/A | J7: =VLOOKUP(C7,'出荷数2307～2406total241008110618'!B:F,5,0) -> #N/A | K7: =VLOOKUP(C7,'出荷数2407-2506total250730101950'!B:F,5,0) -> #N/A | L7: =VLOOKUP(C:C,total251219111800!B:F,5,0) -> #N/A | N7: 0 | O7: 1 | P7: 0 | Q7: 0 | R7: 0 | S7: 0 | T7: 0 | U7: 1 | V7: 1 | W7: 0
A8: 4 | B8: 伊賀 | C8: AHL-3201RD | D8: LEDハンディライト | H8: 2048 | I8: =VLOOKUP(C8,'202310-202403出荷数total2403220951'!B:F,5,0) -> 2098 | J8: =VLOOKUP(C8,'出荷数2307～2406total241008110618'!B:F,5,0) -> 3644 | K8: =VLOOKUP(C8,'出荷数2407-2506total250730101950'!B:F,5,0) -> 2910 | L8: =VLOOKUP(C:C,total251219111800!B:F,5,0) -> 2559 | N8: =L8 -> 2559 | O8: 3061 | P8: 0 | Q8: 0 | R8: 0 | S8: 0 | T8: 0 | U8: 3061 | V8: 502 | W8: 0.83600131
A9: 5 | B9: 伊賀 | C9: AHL-3201WH | D9: LEDハンディライト | H9: 116 | I9: =VLOOKUP(C9,'202310-202403出荷数total2403220951'!B:F,5,0) -> 220 | J9: =VLOOKUP(C9,'出荷数2307～2406total241008110618'!B:F,5,0) -> 378 | K9: =VLOOKUP(C9,'出荷数2407-2506total250730101950'!B:F,5,0) -> 2016 | L9: =VLOOKUP(C:C,total251219111800!B:F,5,0) -> 281 | M9: 1000 | N9: 1000 | O9: 5198 | P9: 0 | Q9: 0 | R9: 0 | S9: 0 | T9: 0 | U9: 5198 | V9: 4198 | W9: 0.19238169
A10: 6 | B10: 伊賀 | C10: AHL-1400 | D10: LED強力ライト | H10: 15126 | I10: =VLOOKUP(C10,'202310-202403出荷数total2403220951'!B:F,5,0) -> 9163 | J10: =VLOOKUP(C10,'出荷数2307～2406total241008110618'!B:F,5,0) -> 19757 | K10: =VLOOKUP(C10,'出荷数2407-2506total250730101950'!B:F,5,0) -> 20812 | L10: =VLOOKUP(C:C,total251219111800!B:F,5,0) -> 4356 | N10: =L10 -> 4356 | O10: 2676 | P10: 13545 | Q10: 0 | R10: 0 | S10: 13225 | T10: 320 | U10: -10549 | V10: -14905 | W10: 0.26854078
A11: 7 | B11: 伊賀 | C11: AHL-1400T | D11: LED強力ライト(トップ) | H11: 2084 | I11: =VLOOKUP(C11,'202310-202403出荷数total2403220951'!B:F,5,0) -> 1160 | J11: =VLOOKUP(C11,'出荷数2307～2406total241008110618'!B:F,5,0) -> 1821 | K11: =VLOOKUP(C11,'出荷数2407-2506total250730101950'!B:F,5,0) -> 1120 | L11: =VLOOKUP(C:C,total251219111800!B:F,5,0) -> 160 | N11: =L11 -> 160 | O11: 2 | P11: 0 | Q11: 0 | R11: 0 | S11: 0 | T11: 0 | U11: 2 | V11: -158 | W11: 80
A12: 8 | B12: 伊賀 | C12: ASL-3308KU | D12: ウォールセンサーライト 箱 | E12: くも | F12: 193 | G12: 1 | H12: 100 | I12: =VLOOKUP(C12,'202310-202403出荷数total2403220951'!B:F,5,0) -> 43 | J12: =VLOOKUP(C12,'出荷数2307～2406total241008110618'!B:F,5,0) -> 51 | K12: =VLOOKUP(C12,'出荷数2407-2506total250730101950'!B:F,5,0) -> 12 | L12: =VLOOKUP(C:C,total251219111800!B:F,5,0) -> 3 | N12: =L12 -> 3 | O12: 999 | P12: 0 | Q12: 0 | R12: 0 | S12: 0 | T12: 0 | U12: 999 | V12: 996 | W12: 0.003003003
A13: 9 | B13: 伊賀 | C13: ANS-502 | D13: テレビ用手もとスピーカー | G13: 6 | H13: 2364 | I13: =VLOOKUP(C13,'202310-202403出荷数total2403220951'!B:F,5,0) -> 1052 | J13: =VLOOKUP(C13,'出荷数2307～2406total241008110618'!B:F,5,0) -> 1711 | K13: =VLOOKUP(C13,'出荷数2407-2506total250730101950'!B:F,5,0) -> 1026 | L13: =VLOOKUP(C:C,total251219111800!B:F,5,0) -> 587 | N13: =L13 -> 587 | O13: 3558 | P13: 0 | Q13: 0 | R13: 0 | S13: 0 | T13: 0 | U13: 3558 | V13: 2971 | W13: 0.16498033
A14: 10 | B14: 伊賀 | C14: ASL-3308US | D14: ウォールセンサーライト 箱 | E14: うさぎ | F14: 0 | G14: 3 | H14: 363 | I14: =VLOOKUP(C14,'202310-202403出荷数total2403220951'!B:F,5,0) -> #N/A | J14: =VLOOKUP(C14,'出荷数2307～2406total241008110618'!B:F,5,0) -> 1 | K14: =VLOOKUP(C14,'出荷数2407-2506total250730101950'!B:F,5,0) -> 7 | L14: =VLOOKUP(C:C,total251219111800!B:F,5,0) -> #N/A | N14: 0 | O14: 744 | P14: 0 | Q14: 0 | R14: 0 | S14: 0 | T14: 0 | U14: 744 | V14: 744 | W14: 0
A15: 11 | B15: 伊賀 | C15: ASL-3308CSK | D15: ウォールセンサーライト ブリスター | E15: しかく | F15: 23 | G15: 4 | H15: 0 | I15: =VLOOKUP(C15,'202310-202403出荷数total2403220951'!B:F,5,0) -> 1 | J15: =VLOOKUP(C15,'出荷数2307～2406total241008110618'!B:F,5,0) -> 705 | K15: =VLOOKUP(C15,'出荷数2407-2506total250730101950'!B:F,5,0) -> 1 | L15: =VLOOKUP(C:C,total251219111800!B:F,5,0) -> 1 | N15: =L15 -> 1 | O15: 0 | P15: 0 | Q15: 0 | R15: 0 | S15: 0 | T15: 0 | U15: 0 | V15: -1 | W15: #DIV/0!
A16: 12 | B16: 伊賀 | C16: ASL-3308CUS | D16: ウォールセンサーライト ブリスター | E16: うさぎ | F16: 35 | G16: 26 | H16: 5 | I16: =VLOOKUP(C16,'202310-202403出荷数total2403220951'!B:F,5,0) -> 3 | J16: =VLOOKUP(C16,'出荷数2307～2406total241008110618'!B:F,5,0) -> 6 | K16: =VLOOKUP(C16,'出荷数2407-2506total250730101950'!B:F,5,0) -> 3 | L16: =VLOOKUP(C:C,total251219111800!B:F,5,0) -> 142 | N16: =L16 -> 142 | O16: 4414 | P16: 0 | Q16: 0 | R16: 0 | S16: 0 | T16: 0 | U16: 4414 | V16: 4272 | W16: 0.032170367
A17: 13 | B17: 伊賀 | C17: AKM-3205PK | D17: 首ふり毛だまクリーナー | E17: ピンク | F17: 33 | G17: 24 | H17: 2990 | I17: =VLOOKUP(C17,'202310-202403出荷数total2403220951'!B:F,5,0) -> 66 | J17: =VLOOKUP(C17,'出荷数2307～2406total241008110618'!B:F,5,0) -> 189 | K17: =VLOOKUP(C17,'出荷数2407-2506total250730101950'!B:F,5,0) -> 97 | L17: =VLOOKUP(C:C,total251219111800!B:F,5,0) -> 77 | N17: =L17 -> 77 | O17: 2106 | P17: 0 | Q17: 0 | R17: 0 | S17: 0 | T17: 0 | U17: 2106 | V17: 2029 | W17: 0.036562203
A18: 14 | B18: 伊賀 | C18: ASN-4302 | D18: マグネット付ＬＥＤ信号灯 | F18: 149 | G18: 62 | H18: 132 | I18: =VLOOKUP(C18,'202310-202403出荷数total2403220951'!B:F,5,0) -> 245 | J18: =VLOOKUP(C18,'出荷数2307～2406total241008110618'!B:F,5,0) -> 322 | K18: =VLOOKUP(C18,'出荷数2407-2506total250730101950'!B:F,5,0) -> 206 | L18: =VLOOKUP(C:C,total251219111800!B:F,5,0) -> 17 | N18: =L18 -> 17 | O18: 2258 | P18: 0 | Q18: 0 | R18: 0 | S18: 0 | T18: 0 | U18: 2258 | V18: 2241 | W18: 0.0075287865 | X18: 売り切り廃盤予定
A19: 15 | B19: 伊賀 | C19: AIC-01IV | D19: ｷｽﾞつきにくいｲｽ脚ｶﾊﾞｰ | E19: IV | F19: 228 | G19: 270 | H19: 231 | I19: =VLOOKUP(C19,'202310-202403出荷数total2403220951'!B:F,5,0) -> 121 | J19: =VLOOKUP(C19,'出荷数2307～2406total241008110618'!B:F,5,0) -> 177 | K19: =VLOOKUP(C19,'出荷数2407-2506total250730101950'!B:F,5,0) -> 110 | L19: =VLOOKUP(C:C,total251219111800!B:F,5,0) -> 53 | N19: =L19 -> 53 | O19: 8060 | P19: 0 | Q19: 0 | R19: 0 | S19: 0 | T19: 0 | U19: 8060 | V19: 8007 | W19: 0.0065756824
A20: 16 | B20: 伊賀 | C20: ANS-603 | D20: お経の流れるスピーカーⅡ | G20: 128 | H20: 470 | I20: =VLOOKUP(C20,'202310-202403出荷数total2403220951'!B:F,5,0) -> 149 | J20: =VLOOKUP(C20,'出荷数2307～2406total241008110618'!B:F,5,0) -> 418 | K20: =VLOOKUP(C20,'出荷数2407-2506total250730101950'!B:F,5,0) -> 818 | L20: =VLOOKUP(C:C,total251219111800!B:F,5,0) -> 491 | N20: =L20 -> 491 | O20: 614 | P20: 130 | Q20: 0 | R20: 0 | S20: 280 | T20: -150 | U20: 334 | V20: -157 | W20: 0.65994624 | X20: トップ確保3月末まで確保
A21: 17 | B21: 伊賀 | C21: APY-105 | D21: 迷惑電話お断りピンポン | F21: 543 | G21: 321 | H21: 270 | I21: =VLOOKUP(C21,'202310-202403出荷数total2403220951'!B:F,5,0) -> 73 | J21: =VLOOKUP(C21,'出荷数2307～2406total241008110618'!B:F,5,0) -> 181 | K21: =VLOOKUP(C21,'出荷数2407-2506total250730101950'!B:F,5,0) -> 277 | L21: =VLOOKUP(C:C,total251219111800!B:F,5,0) -> 141 | N21: =L21 -> 141 | O21: 3326 | P21: 370 | Q21: 0 | R21: 0 | S21: 370 | T21: 0 | U21: 2956 | V21: 2815 | W21: 0.038149351
A22: 18 | B22: 伊賀 | C22: APL-3207S | D22: LEDのインテリア常備灯 | F22: 904 | G22: 638 | H22: 81 | I22: =VLOOKUP(C22,'202310-202403出荷数total2403220951'!B:F,5,0) -> 2 | J22: =VLOOKUP(C22,'出荷数2307～2406total241008110618'!B:F,5,0) -> 904 | K22: =VLOOKUP(C22,'出荷数2407-2506total250730101950'!B:F,5,0) -> 25 | L22: =VLOOKUP(C:C,total251219111800!B:F,5,0) -> 2 | N22: =L22 -> 2 | O22: 6860 | P22: 0 | Q22: 0 | R22: 0 | S22: 0 | T22: 0 | U22: 6860 | V22: 6858 | W22: 0.00029154519
A23: 19 | B23: 伊賀 | C23: ALA-4308BK-D | D23: ひっぱり点灯ライト 電球色ＬＥＤ | F23: 1137 | G23: 270 | H23: 272 | I23: =VLOOKUP(C23,'202310-202403出荷数total2403220951'!B:F,5,0) -> 153 | J23: =VLOOKUP(C23,'出荷数2307～2406total241008110618'!B:F,5,0) -> 657 | K23: =VLOOKUP(C23,'出荷数2407-2506total250730101950'!B:F,5,0) -> 101 | L23: =VLOOKUP(C:C,total251219111800!B:F,5,0) -> 88 | N23: =L23 -> 88 | O23: 1782 | P23: 0 | Q23: 0 | R23: 0 | S23: 0 | T23: 0 | U23: 1782 | V23: 1694 | W23: 0.049382716
A24: 20 | B24: 伊賀 | C24: ACA-101 | D24: ＬＥＤ帽子ライト | F24: 787 | G24: 450 | H24: 417 | I24: =VLOOKUP(C24,'202310-202403出荷数total2403220951'!B:F,5,0) -> 450 | J24: =VLOOKUP(C24,'出荷数2307～2406total241008110618'!B:F,5,0) -> 550 | K24: =VLOOKUP(C24,'出荷数2407-2506total250730101950'!B:F,5,0) -> 160 | L24: =VLOOKUP(C:C,total251219111800!B:F,5,0) -> 89 | N24: =L24 -> 89 | O24: 3706 | P24: 0 | Q24: 0 | R24: 0 | S24: 0 | T24: 0 | U24: 3706 | V24: 3617 | W24: 0.024015111
A25: 21 | B25: 伊賀 | C25: ASL-3308NE | D25: ウォールセンサーライト 箱 | E25: ねこ | F25: 13 | G25: 4 | H25: 8 | I25: =VLOOKUP(C25,'202310-202403出荷数total2403220951'!B:F,5,0) -> 1 | J25: =VLOOKUP(C25,'出荷数2307～2406total241008110618'!B:F,5,0) -> 4 | K25: =VLOOKUP(C25,'出荷数2407-2506total250730101950'!B:F,5,0) -> 6 | L25: =VLOOKUP(C:C,total251219111800!B:F,5,0) -> #N/A | N25: 0 | O25: 24 | P25: 0 | Q25: 0 | R25: 0 | S25: 0 | T25: 0 | U25: 24 | V25: 24 | W25: 0
A26: 22 | B26: 伊賀 | C26: AKD-20 | D26: アニマルシリコンバンド | F26: 1809 | G26: 790 | H26: 1042 | I26: =VLOOKUP(C26,'202310-202403出荷数total2403220951'!B:F,5,0) -> 164 | J26: =VLOOKUP(C26,'出荷数2307～2406total241008110618'!B:F,5,0) -> 312 | K26: =VLOOKUP(C26,'出荷数2407-2506total250730101950'!B:F,5,0) -> 454 | L26: =VLOOKUP(C:C,total251219111800!B:F,5,0) -> 168 | N26: =L26 -> 168 | O26: 5703 | P26: 300 | Q26: 0 | R26: 0 | S26: 300 | T26: 0 | U26: 5403 | V26: 5235 | W26: 0.027986007
A27: 23 | B27: 伊賀 | C27: ARA-4301 | D27: スマートフォンが使えるラジオライト | F27: 549 | G27: 303 | H27: 236 | I27: =VLOOKUP(C27,'202310-202403出荷数total2403220951'!B:F,5,0) -> 241 | J27: =VLOOKUP(C27,'出荷数2307～2406total241008110618'!B:F,5,0) -> 358 | K27: =VLOOKUP(C27,'出荷数2407-2506total250730101950'!B:F,5,0) -> 392 | L27: =VLOOKUP(C:C,total251219111800!B:F,5,0) -> 29 | N27: =L27 -> 29 | O27: 1917 | P27: 0 | Q27: 0 | R27: 0 | S27: 0 | T27: 0 | U27: 1917 | V27: 1888 | W27: 0.015127804
A28: 24 | B28: 伊賀 | C28: ASK-11BOR | D28: 巻きつく安全反射バンド(OR) | E28: オレンジ | F28: 1160 | G28: 148 | H28: 651 | I28: =VLOOKUP(C28,'202310-202403出荷数total2403220951'!B:F,5,0) -> 60 | J28: =VLOOKUP(C28,'出荷数2307～2406total241008110618'!B:F,5,0) -> 125 | K28: =VLOOKUP(C28,'出荷数2407-2506total250730101950'!B:F,5,0) -> 265 | L28: =VLOOKUP(C:C,total251219111800!B:F,5,0) -> 38 | M28: 500 | N28: 500 | O28: 2310 | P28: 0 | Q28: 0 | R28: 0 | S28: 0 | T28: 0 | U28: 2310 | V28: 1810 | W28: 0.21645022
A29: 25 | B29: 伊賀 | C29: ASK-10YE | D29: 光るホイール反射シール | E29: イエロー | F29: 935 | G29: 77 | H29: 731 | I29: =VLOOKUP(C29,'202310-202403出荷数total2403220951'!B:F,5,0) -> 163 | J29: =VLOOKUP(C29,'出荷数2307～2406total241008110618'!B:F,5,0) -> 235 | K29: =VLOOKUP(C29,'出荷数2407-2506total250730101950'!B:F,5,0) -> 20 | L29: =VLOOKUP(C:C,total251219111800!B:F,5,0) -> 2 | N29: =L29 -> 2 | O29: 5 | P29: 0 | Q29: 0 | R29: 0 | S29: 0 | T29: 0 | U29: 5 | V29: 3 | W29: 0.4
A30: 26 | B30: 伊賀 | C30: ARO-530GD | D30: 自動消灯安心のろうそく | E30: GD | F30: 224 | G30: 198 | H30: 230 | I30: =VLOOKUP(C30,'202310-202403出荷数total2403220951'!B:F,5,0) -> 91 | J30: =VLOOKUP(C30,'出荷数2307～2406total241008110618'!B:F,5,0) -> 168 | K30: =VLOOKUP(C30,'出荷数2407-2506total250730101950'!B:F,5,0) -> 52 | L30: =VLOOKUP(C:C,total251219111800!B:F,5,0) -> 28 | N30: =L30 -> 28 | O30: 920 | P30: 0 | Q30: 0 | R30: 0 | S30: 0 | T30: 0 | U30: 920 | V30: 892 | W30: 0.030434783
A31: 27 | B31: 伊賀 | C31: ALA-4308MO-W | D31: ひっぱり点灯ライト 木目 | E31: 木目 | F31: 714 | G31: 368 | H31: 496 | I31: =VLOOKUP(C31,'202310-202403出荷数total2403220951'!B:F,5,0) -> 150 | J31: =VLOOKUP(C31,'出荷数2307～2406total241008110618'!B:F,5,0) -> 247 | K31: =VLOOKUP(C31,'出荷数2407-2506total250730101950'!B:F,5,0) -> 43 | L31: =VLOOKUP(C:C,total251219111800!B:F,5,0) -> 29 | N31: =L31 -> 29 | O31: 1947 | P31: 0 | Q31: 0 | R31: 0 | S31: 0 | T31: 0 | U31: 1947 | V31: 1918 | W31: 0.01489471
A32: 28 | B32: 伊賀 | C32: AIC-06IV | D32: ｽﾞﾚにくいｲｽ脚ｶﾊﾞｰ 2脚用 | E32: IV | F32: 1116 | G32: 928 | H32: 1098 | I32: =VLOOKUP(C32,'202310-202403出荷数total2403220951'!B:F,5,0) -> 427 | J32: =VLOOKUP(C32,'出荷数2307～2406total241008110618'!B:F,5,0) -> 1008 | K32: =VLOOKUP(C32,'出荷数2407-2506total250730101950'!B:F,5,0) -> 854 | L32: =VLOOKUP(C:C,total251219111800!B:F,5,0) -> 345 | N32: =L32 -> 345 | O32: 3124 | P32: 0 | Q32: 0 | R32: 0 | S32: 0 | T32: 0 | U32: 3124 | V32: 2779 | W32: 0.11043534 | X32: 88％発注点よりﾏｲﾅｽ 345→41
A33: 29 | B33: 伊賀 | C33: ANS-701AD | D33: ＡＣアダプター701用 | F33: 120 | G33: 98 | H33: 141 | I33: =VLOOKUP(C33,'202310-202403出荷数total2403220951'!B:F,5,0) -> 41 | J33: =VLOOKUP(C33,'出荷数2307～2406total241008110618'!B:F,5,0) -> 89 | K33: =VLOOKUP(C33,'出荷数2407-2506total250730101950'!B:F,5,0) -> 92 | L33: =VLOOKUP(C:C,total251219111800!B:F,5,0) -> 49 | N33: =L33 -> 49 | O33: 319 | P33: 0 | Q33: 0 | R33: 0 | S33: 0 | T33: 0 | U33: 319 | V33: 270 | W33: 0.15360502
A34: 30 | B34: 伊賀 | C34: ANS-702 | D34: 大きな手もとスピーカー | F34: 1030 | G34: 390 | H34: 221 | I34: =VLOOKUP(C34,'202310-202403出荷数total2403220951'!B:F,5,0) -> 53 | J34: =VLOOKUP(C34,'出荷数2307～2406total241008110618'!B:F,5,0) -> 103 | K34: =VLOOKUP(C34,'出荷数2407-2506total250730101950'!B:F,5,0) -> 224 | L34: =VLOOKUP(C:C,total251219111800!B:F,5,0) -> 45 | N34: =L34 -> 45 | O34: 2080 | P34: 0 | Q34: 0 | R34: 0 | S34: 0 | T34: 0 | U34: 2080 | V34: 2035 | W34: 0.021634615
A35: 31 | B35: 伊賀 | C35: AKN-15 | D35: ハローキティ コンセントカバー | F35: 1322 | G35: 1075 | H35: 946 | I35: =VLOOKUP(C35,'202310-202403出荷数total2403220951'!B:F,5,0) -> 348 | J35: =VLOOKUP(C35,'出荷数2307～2406total241008110618'!B:F,5,0) -> 766 | K35: =VLOOKUP(C35,'出荷数2407-2506total250730101950'!B:F,5,0) -> 1074 | L35: =VLOOKUP(C:C,total251219111800!B:F,5,0) -> 327 | N35: =L35 -> 327 | O35: 3568 | P35: 0 | Q35: 0 | R35: 0 | S35: 0 | T35: 0 | U35: 3568 | V35: 3241 | W35: 0.091647982
A36: 32 | B36: 伊賀 | C36: ACA-3101 | D36: ＬＥＤアルミヘッドランプ | F36: 1781 | G36: 1472 | H36: 1360 | I36: =VLOOKUP(C36,'202310-202403出荷数total2403220951'!B:F,5,0) -> 3651 | J36: =VLOOKUP(C36,'出荷数2307～2406total241008110618'!B:F,5,0) -> 4452 | K36: =VLOOKUP(C36,'出荷数2407-2506total250730101950'!B:F,5,0) -> 4054 | L36: =VLOOKUP(C:C,total251219111800!B:F,5,0) -> 524 | N36: =L36 -> 524 | O36: 12996 | P36: 0 | Q36: 100 | R36: 0 | S36: 0 | T36: 0 | U36: 13096 | V36: 12572 | W36: 0.040320098
A37: 33 | B37: 伊賀 | C37: ASK-06SI | D37: はめるだけ光る 足腕バンド | E37: シルバー | F37: 1210 | G37: 214 | H37: 13 | I37: =VLOOKUP(C37,'202310-202403出荷数total2403220951'!B:F,5,0) -> 75 | J37: =VLOOKUP(C37,'出荷数2307～2406total241008110618'!B:F,5,0) -> 79 | K37: =VLOOKUP(C37,'出荷数2407-2506total250730101950'!B:F,5,0) -> 1 | L37: =VLOOKUP(C:C,total251219111800!B:F,5,0) -> 3 | N37: =L37 -> 3 | O37: 880 | P37: 0 | Q37: 0 | R37: 0 | S37: 0 | T37: 0 | U37: 880 | V37: 877 | W37: 0.0034090909
A38: 34 | B38: 伊賀 | C38: ASL-3308CNE | D38: ウォールセンサーライト ブリスター | E38: ねこ | F38: 271 | G38: 200 | H38: 124 | I38: =VLOOKUP(C38,'202310-202403出荷数total2403220951'!B:F,5,0) -> 63 | J38: =VLOOKUP(C38,'出荷数2307～2406total241008110618'!B:F,5,0) -> 93 | K38: =VLOOKUP(C38,'出荷数2407-2506total250730101950'!B:F,5,0) -> 14 | L38: =VLOOKUP(C:C,total251219111800!B:F,5,0) -> 140 | N38: =L38 -> 140 | O38: 797 | P38: 0 | Q38: 0 | R38: 0 | S38: 0 | T38: 0 | U38: 797 | V38: 657 | W38: 0.17565872
A39: 35 | B39: 伊賀 | C39: ASL-33082 | D39: ウォールセンサーライト（ショップチャンネル専用） | G39: 9 | H39: 1109 | I39: =VLOOKUP(C39,'202310-202403出荷数total2403220951'!B:F,5,0) -> #N/A | J39: =VLOOKUP(C39,'出荷数2307～2406total241008110618'!B:F,5,0) -> #N/A | K39: =VLOOKUP(C39,'出荷数2407-2506total250730101950'!B:F,5,0) -> #N/A | L39: =VLOOKUP(C:C,total251219111800!B:F,5,0) -> #N/A | M39: 470 | N39: 470 | O39: 106 | P39: 0 | Q39: 0 | R39: 0 | S39: 0 | T39: 0 | U39: 106 | V39: -364 | W39: 4.4339623
A40: 36 | B40: 伊賀 | C40: ADR-3401 | D40: 電動角質リムーバー | F40: 19 | G40: 1283 | H40: 7 | I40: =VLOOKUP(C40,'202310-202403出荷数total2403220951'!B:F,5,0) -> 223 | J40: =VLOOKUP(C40,'出荷数2307～2406total241008110618'!B:F,5,0) -> 598 | K40: =VLOOKUP(C40,'出荷数2407-2506total250730101950'!B:F,5,0) -> 73 | L40: =VLOOKUP(C:C,total251219111800!B:F,5,0) -> 5 | N40: =L40 -> 5 | O40: 4160 | P40: 0 | Q40: 0 | R40: 0 | S40: 0 | T40: 0 | U40: 4160 | V40: 4155 | W40: 0.0012019231
A41: 37 | B41: 伊賀 | C41: ASL-3309 | D41: センサーライト付防犯ダミーカメラ | F41: 825 | G41: 660 | H41: 1314 | I41: =VLOOKUP(C41,'202310-202403出荷数total2403220951'!B:F,5,0) -> 262 | J41: =VLOOKUP(C41,'出荷数2307～2406total241008110618'!B:F,5,0) -> 723 | K41: =VLOOKUP(C41,'出荷数2407-2506total250730101950'!B:F,5,0) -> 1443 | L41: =VLOOKUP(C:C,total251219111800!B:F,5,0) -> 305 | N41: =L41 -> 305 | O41: 3056 | P41: 190 | Q41: 0 | R41: 0 | S41: 300 | T41: -110 | U41: 2756 | V41: 2451 | W41: 0.093961799
A42: 38 | B42: 伊賀 | C42: ADR-3401KR | D42: 電動角質リムーバー交換用ローラー（2PCS) | F42: 33 | G42: 994 | H42: 20 | I42: =VLOOKUP(C42,'202310-202403出荷数total2403220951'!B:F,5,0) -> 14 | J42: =VLOOKUP(C42,'出荷数2307～2406total241008110618'!B:F,5,0) -> 26 | K42: =VLOOKUP(C42,'出荷数2407-2506total250730101950'!B:F,5,0) -> 8 | L42: =VLOOKUP(C:C,total251219111800!B:F,5,0) -> 4 | N42: =L42 -> 4 | O42: 4564 | P42: 0 | Q42: 0 | R42: 0 | S42: 0 | T42: 0 | U42: 4564 | V42: 4560 | W42: 0.00087642419
A43: 39 | B43: 伊賀 | C43: KCA-003 | D43: キューベルク 充電式ヘッドライト340 | F43: 15 | G43: 257 | H43: 96 | I43: =VLOOKUP(C43,'202310-202403出荷数total2403220951'!B:F,5,0) -> 18 | J43: =VLOOKUP(C43,'出荷数2307～2406total241008110618'!B:F,5,0) -> 45 | K43: =VLOOKUP(C43,'出荷数2407-2506total250730101950'!B:F,5,0) -> 101 | L43: =VLOOKUP(C:C,total251219111800!B:F,5,0) -> 21 | N43: =L43 -> 21 | O43: 792 | P43: 0 | Q43: 0 | R43: 0 | S43: 0 | T43: 0 | U43: 792 | V43: 771 | W43: 0.026515152
B44: 伊賀 | C44: KCA-004H | D44: ロータリー式ヘッドライト500 | L44: =VLOOKUP(C:C,total251219111800!B:F,5,0) -> 3 | N44: =L44 -> 3 | O44: 493 | P44: 0 | Q44: 1000 | R44: 0 | S44: 0 | T44: 0 | U44: 1493 | V44: 1490 | W44: 0.0060851927
A45: 40 | B45: 伊賀 | C45: ABO-180 | D45: エアーマット1800 | F45: 940 | G45: 457 | H45: 1013 | I45: =VLOOKUP(C45,'202310-202403出荷数total2403220951'!B:F,5,0) -> 669 | J45: =VLOOKUP(C45,'出荷数2307～2406total241008110618'!B:F,5,0) -> 4147 | K45: =VLOOKUP(C45,'出荷数2407-2506total250730101950'!B:F,5,0) -> 4439 | L45: =VLOOKUP(C:C,total251219111800!B:F,5,0) -> 49 | N45: =L45 -> 49 | O45: 307 | P45: 0 | Q45: 0 | R45: 0 | S45: 0 | T45: 0 | U45: 307 | V45: 258 | W45: 0.15960912
A46: 41 | B46: 伊賀 | C46: ABO-120 | D46: エアーマット1200 | F46: 149 | G46: 373 | H46: 66 | I46: =VLOOKUP(C46,'202310-202403出荷数total2403220951'!B:F,5,0) -> 150 | J46: =VLOOKUP(C46,'出荷数2307～2406total241008110618'!B:F,5,0) -> 203 | K46: =VLOOKUP(C46,'出荷数2407-2506total250730101950'!B:F,5,0) -> 212 | L46: =VLOOKUP(C:C,total251219111800!B:F,5,0) -> 39 | N46: =L46 -> 39 | O46: 960 | P46: 0 | Q46: 0 | R46: 0 | S46: 0 | T46: 0 | U46: 960 | V46: 921 | W46: 0.040625
A47: 42 | B47: 伊賀 | C47: AIC-01BR | D47: ｷｽﾞつきにくいｲｽ脚ｶﾊﾞｰ | E47: BR | F47: 2264 | G47: 1923 | H47: 1776 | I47: =VLOOKUP(C47,'202310-202403出荷数total2403220951'!B:F,5,0) -> 535 | J47: =VLOOKUP(C47,'出荷数2307～2406total241008110618'!B:F,5,0) -> 2161 | K47: =VLOOKUP(C47,'出荷数2407-2506total250730101950'!B:F,5,0) -> 933 | L47: =VLOOKUP(C:C,total251219111800!B:F,5,0) -> 398 | N47: =L47 -> 398 | O47: 2658 | P47: 0 | Q47: 0 | R47: 0 | S47: 0 | T47: 0 | U47: 2658 | V47: 2260 | W47: 0.14973664
A48: 43 | B48: 伊賀 | C48: AHL-1207 | D48: 単1形LED防雨ライト | F48: 3482 | G48: 1186 | H48: 1004 | I48: =VLOOKUP(C48,'202310-202403出荷数total2403220951'!B:F,5,0) -> 594 | J48: =VLOOKUP(C48,'出荷数2307～2406total241008110618'!B:F,5,0) -> 1198 | K48: =VLOOKUP(C48,'出荷数2407-2506total250730101950'!B:F,5,0) -> 1234 | L48: =VLOOKUP(C:C,total251219111800!B:F,5,0) -> 693 | N48: =L48 -> 693 | O48: 600 | P48: 0 | Q48: 0 | R48: 0 | S48: 0 | T48: 0 | U48: 600 | V48: -93 | W48: 1.155
A49: 44 | B49: 伊賀 | C49: ABO-11 | D49: 防炎非常持出袋 | F49: 5224 | G49: 1145 | H49: 1174 | I49: =VLOOKUP(C49,'202310-202403出荷数total2403220951'!B:F,5,0) -> 435 | J49: =VLOOKUP(C49,'出荷数2307～2406total241008110618'!B:F,5,0) -> 653 | K49: =VLOOKUP(C49,'出荷数2407-2506total250730101950'!B:F,5,0) -> 1213 | L49: =VLOOKUP(C:C,total251219111800!B:F,5,0) -> 373 | N49: =L49 -> 373 | O49: 3847 | P49: 0 | Q49: 0 | R49: 0 | S49: 0 | T49: 0 | U49: 3847 | V49: 3474 | W49: 0.096958669
A50: 45 | B50: 伊賀 | C50: ANS-302BK | D50: テレビの音も聞こえる 手もとスピーカーⅡ | G50: 537 | H50: 3033 | I50: =VLOOKUP(C50,'202310-202403出荷数total2403220951'!B:F,5,0) -> 1920 | J50: =VLOOKUP(C50,'出荷数2307～2406total241008110618'!B:F,5,0) -> 4184 | K50: =VLOOKUP(C50,'出荷数2407-2506total250730101950'!B:F,5,0) -> 3497 | L50: =VLOOKUP(C:C,total251219111800!B:F,5,0) -> 1086 | M50: 750 | N50: =L50 -> 1086 | O50: 4655 | P50: 840 | Q50: 0 | R50: 0 | S50: 840 | T50: 0 | U50: 3815 | V50: 2729 | W50: 0.19763421
A51: 46 | B51: 伊賀 | C51: APL-3207SMO | D51: LEDのインテリア常備灯(化粧箱) | E51: 木目 | F51: 1023 | G51: 517 | H51: 437 | I51: =VLOOKUP(C51,'202310-202403出荷数total2403220951'!B:F,5,0) -> 346 | J51: =VLOOKUP(C51,'出荷数2307～2406total241008110618'!B:F,5,0) -> 396 | K51: =VLOOKUP(C51,'出荷数2407-2506total250730101950'!B:F,5,0) -> 187 | L51: =VLOOKUP(C:C,total251219111800!B:F,5,0) -> 6 | N51: =L51 -> 6 | O51: 1255 | P51: 600 | Q51: 0 | R51: 0 | S51: 600 | T51: 0 | U51: 655 | V51: 649 | W51: 0.0032345013
A52: 47 | B52: 伊賀 | C52: AST-3304 | D52: LEDスタンドライト | F52: 843 | G52: 647 | H52: 2107 | I52: =VLOOKUP(C52,'202310-202403出荷数total2403220951'!B:F,5,0) -> #N/A | J52: =VLOOKUP(C52,'出荷数2307～2406total241008110618'!B:F,5,0) -> #N/A | K52: =VLOOKUP(C52,'出荷数2407-2506total250730101950'!B:F,5,0) -> #N/A | L52: =VLOOKUP(C:C,total251219111800!B:F,5,0) -> #N/A | M52: 890 | N52: 890 | O52: 0 | P52: 0 | Q52: 0 | R52: 0 | S52: 0 | T52: 0 | U52: 0 | V52: -890 | W52: #DIV/0!
A53: 48 | B53: 伊賀 | C53: ASL-3305 | D53: 足もと安心防雨センサーライト | F53: 1465 | G53: 1744 | H53: 888 | I53: =VLOOKUP(C53,'202310-202403出荷数total2403220951'!B:F,5,0) -> 559 | J53: =VLOOKUP(C53,'出荷数2307～2406total241008110618'!B:F,5,0) -> 1133 | K53: =VLOOKUP(C53,'出荷数2407-2506total250730101950'!B:F,5,0) -> 829 | L53: =VLOOKUP(C:C,total251219111800!B:F,5,0) -> 200 | N53: =L53 -> 200 | O53: 3367 | P53: 0 | Q53: 0 | R53: 0 | S53: 0 | T53: 0 | U53: 3367 | V53: 3167 | W53: 0.059400059
A54: 49 | B54: 伊賀 | C54: AHA-43ENAUTO | D54: 自動点灯ｻｲｸﾙﾗｲﾄ(ﾊﾝﾄﾞﾙﾀﾞｲﾅﾓ取付) | F54: 1087 | G54: 665 | H54: 2030 | I54: =VLOOKUP(C54,'202310-202403出荷数total2403220951'!B:F,5,0) -> #N/A | J54: =VLOOKUP(C54,'出荷数2307～2406total241008110618'!B:F,5,0) -> #N/A | K54: =VLOOKUP(C54,'出荷数2407-2506total250730101950'!B:F,5,0) -> #N/A | L54: =VLOOKUP(C:C,total251219111800!B:F,5,0) -> #N/A | M54: 850 | N54: 850 | O54: 2 | P54: 0 | Q54: 0 | R54: 0 | S54: 0 | T54: 0 | U54: 2 | V54: -848 | W54: 425
A55: 50 | B55: 伊賀 | C55: AIC-04IV | D55: ｽﾞﾚにくいｲｽ脚ｶﾊﾞｰ 4脚用 | E55: IV | F55: 2129 | G55: 2065 | H55: 2439 | I55: =VLOOKUP(C55,'202310-202403出荷数total2403220951'!B:F,5,0) -> 805 | J55: =VLOOKUP(C55,'出荷数2307～2406total241008110618'!B:F,5,0) -> 1939 | K55: =VLOOKUP(C55,'出荷数2407-2506total250730101950'!B:F,5,0) -> 1171 | L55: =VLOOKUP(C:C,total251219111800!B:F,5,0) -> 566 | N55: =L55 -> 566 | O55: 830 | P55: 0 | Q55: 0 | R55: 0 | S55: 0 | T55: 0 | U55: 830 | V55: 264 | W55: 0.68192771 | X55: 48％発注点よりﾏｲﾅｽ 566→295
A56: 51 | B56: 伊賀 | C56: ABO-13M | D56: ぬげにくい安全スリッパM | F56: 1540 | G56: 597 | H56: 361 | I56: =VLOOKUP(C56,'202310-202403出荷数total2403220951'!B:F,5,0) -> 533 | J56: =VLOOKUP(C56,'出荷数2307～2406total241008110618'!B:F,5,0) -> 858 | K56: =VLOOKUP(C56,'出荷数2407-2506total250730101950'!B:F,5,0) -> 574 | L56: =VLOOKUP(C:C,total251219111800!B:F,5,0) -> #N/A | N56: =L56 -> #N/A | O56: 0 | P56: 0 | Q56: 0 | R56: 0 | S56: 0 | T56: 0 | U56: 0 | V56: #N/A | W56: #N/A
A57: 52 | B57: 伊賀 | C57: ABO-2907 | D57: 水タンクにもなる水のう袋 7枚入り | G57: 2665 | H57: 2710 | I57: =VLOOKUP(C57,'202310-202403出荷数total2403220951'!B:F,5,0) -> 1020 | J57: =VLOOKUP(C57,'出荷数2307～2406total241008110618'!B:F,5,0) -> 7751 | K57: =VLOOKUP(C57,'出荷数2407-2506total250730101950'!B:F,5,0) -> 21996 | L57: =VLOOKUP(C:C,total251219111800!B:F,5,0) -> 8163 | M57: 10000 | N57: 10000 | O57: 21206 | P57: 600 | Q57: 0 | R57: 0 | S57: 2110 | T57: -1510 | U57: 19096 | V57: 9096 | W57: 0.45858938
A58: 53 | B58: 伊賀 | C58: ALA-4306 | D58: ＬＥＤポケットランタンⅡ 廃版 | F58: 756 | G58: 52 | H58: 44 | I58: =VLOOKUP(C58,'202310-202403出荷数total2403220951'!B:F,5,0) -> 47 | J58: =VLOOKUP(C58,'出荷数2307～2406total241008110618'!B:F,5,0) -> 67 | K58: =VLOOKUP(C58,'出荷数2407-2506total250730101950'!B:F,5,0) -> 12 | L58: =VLOOKUP(C:C,total251219111800!B:F,5,0) -> 2 | N58: =L58 -> 2 | O58: 37 | P58: 0 | Q58: 0 | R58: 0 | S58: 0 | T58: 0 | U58: 37 | V58: 35 | W58: 0.054054054
A59: 54 | B59: 伊賀 | C59: ADC-311WH | D59: 単３が３個で単１電池アダプター | F59: 5239 | G59: 4870 | H59: 3762 | I59: =VLOOKUP(C59,'202310-202403出荷数total2403220951'!B:F,5,0) -> 1545 | J59: =VLOOKUP(C59,'出荷数2307～2406total241008110618'!B:F,5,0) -> 2638 | K59: =VLOOKUP(C59,'出荷数2407-2506total250730101950'!B:F,5,0) -> 3321 | L59: =VLOOKUP(C:C,total251219111800!B:F,5,0) -> 1045 | N59: =L59 -> 1045 | O59: 7230 | P59: 0 | Q59: 0 | R59: 0 | S59: 0 | T59: 0 | U59: 7230 | V59: 6185 | W59: 0.14453665
A60: 55 | B60: 伊賀 | C60: AKO-10 | D60: こたつ専用収納ポケットS | E60: BR | F60: 1332 | G60: 1490 | H60: 2200 | I60: =VLOOKUP(C60,'202310-202403出荷数total2403220951'!B:F,5,0) -> 339 | J60: =VLOOKUP(C60,'出荷数2307～2406total241008110618'!B:F,5,0) -> 1289 | K60: =VLOOKUP(C60,'出荷数2407-2506total250730101950'!B:F,5,0) -> 1155 | L60: =VLOOKUP(C:C,total251219111800!B:F,5,0) -> 362 | N60: =L60 -> 362 | O60: 3814 | P60: 0 | Q60: 0 | R60: 0 | S60: 0 | T60: 0 | U60: 3814 | V60: 3452 | W60: 0.094913477
A61: 56 | B61: 伊賀 | C61: AHM-108 | D61: 録音できるハンドメガホン | F61: 1177 | G61: 1274 | H61: 1310 | I61: =VLOOKUP(C61,'202310-202403出荷数total2403220951'!B:F,5,0) -> 484 | J61: =VLOOKUP(C61,'出荷数2307～2406total241008110618'!B:F,5,0) -> 984 | K61: =VLOOKUP(C61,'出荷数2407-2506total250730101950'!B:F,5,0) -> 1414 | L61: =VLOOKUP(C:C,total251219111800!B:F,5,0) -> 852 | N61: =L61 -> 852 | O61: 1096 | P61: 100 | Q61: 0 | R61: 0 | S61: 100 | T61: 0 | U61: 996 | V61: 144 | W61: 0.71237458
A62: 57 | B62: 伊賀 | C62: ASK-04 | D62: 光るスポークかざり ビーズ | F62: 2501 | G62: 1137 | H62: 1254 | I62: =VLOOKUP(C62,'202310-202403出荷数total2403220951'!B:F,5,0) -> 1064 | J62: =VLOOKUP(C62,'出荷数2307～2406total241008110618'!B:F,5,0) -> 1296 | K62: =VLOOKUP(C62,'出荷数2407-2506total250730101950'!B:F,5,0) -> 172 | L62: =VLOOKUP(C:C,total251219111800!B:F,5,0) -> 765 | N62: =L62 -> 765 | O62: 2106 | P62: 2000 | Q62: 0 | R62: 0 | S62: 2000 | T62: 0 | U62: 106 | V62: -659 | W62: 0.18631271 | X62: 様子見
A63: 58 | B63: 伊賀 | C63: ASK-10SI | D63: 光るホイール反射シール | E63: シルバー | F63: 600 | G63: 225 | H63: 22 | I63: =VLOOKUP(C63,'202310-202403出荷数total2403220951'!B:F,5,0) -> 1 | J63: =VLOOKUP(C63,'出荷数2307～2406total241008110618'!B:F,5,0) -> 1 | K63: =VLOOKUP(C63,'出荷数2407-2506total250730101950'!B:F,5,0) -> #N/A | L63: =VLOOKUP(C:C,total251219111800!B:F,5,0) -> #N/A | N63: =L63 -> #N/A | O63: 552 | P63: 0 | Q63: 0 | R63: 0 | S63: 0 | T63: 0 | U63: 552 | V63: #N/A | W63: #N/A
A64: 59 | B64: 伊賀 | C64: ASK-13 | D64: 光るホイール反射シール | F64: 600 | G64: 225 | H64: 0 | I64: =VLOOKUP(C64,'202310-202403出荷数total2403220951'!B:F,5,0) -> 10 | J64: =VLOOKUP(C64,'出荷数2307～2406total241008110618'!B:F,5,0) -> 11 | K64: =VLOOKUP(C64,'出荷数2407-2506total250730101950'!B:F,5,0) -> 8 | L64: =VLOOKUP(C:C,total251219111800!B:F,5,0) -> 13 | N64: =L64 -> 13 | O64: 1965 | P64: 0 | Q64: 0 | R64: 0 | S64: 0 | T64: 0 | U64: 1965 | V64: 1952 | W64: 0.0066157761
A65: 60 | B65: 伊賀 | C65: ASK-06YE | D65: はめるだけ光る 足腕バンド | E65: イエロー | F65: 46 | G65: 271 | H65: 10 | I65: =VLOOKUP(C65,'202310-202403出荷数total2403220951'!B:F,5,0) -> 50 | J65: =VLOOKUP(C65,'出荷数2307～2406total241008110618'!B:F,5,0) -> 53 | K65: =VLOOKUP(C65,'出荷数2407-2506total250730101950'!B:F,5,0) -> 93 | L65: =VLOOKUP(C:C,total251219111800!B:F,5,0) -> 13 | M65: 500 | N65: 500 | O65: 2320 | P65: 0 | Q65: 0 | R65: 0 | S65: 0 | T65: 0 | U65: 2320 | V65: 1820 | W65: 0.21551724
A66: 61 | B66: 伊賀 | C66: AHA-4307 | D66: 自動点灯サイクルライトⅡ | F66: 1006 | G66: 417 | H66: 772 | I66: =VLOOKUP(C66,'202310-202403出荷数total2403220951'!B:F,5,0) -> 650 | J66: =VLOOKUP(C66,'出荷数2307～2406total241008110618'!B:F,5,0) -> 1155 | K66: =VLOOKUP(C66,'出荷数2407-2506total250730101950'!B:F,5,0) -> 373 | L66: =VLOOKUP(C:C,total251219111800!B:F,5,0) -> 484 | N66: =L66 -> 484 | O66: 1329 | P66: 0 | Q66: 0 | R66: 0 | S66: 0 | T66: 0 | U66: 1329 | V66: 845 | W66: 0.3641836
A67: 62 | B67: 伊賀 | C67: ALA-4311 | D67: くるっとハンディランタンライト | F67: 856 | G67: 1296 | H67: 948 | I67: =VLOOKUP(C67,'202310-202403出荷数total2403220951'!B:F,5,0) -> 92 | J67: =VLOOKUP(C67,'出荷数2307～2406total241008110618'!B:F,5,0) -> 191 | K67: =VLOOKUP(C67,'出荷数2407-2506total250730101950'!B:F,5,0) -> 1768 | L67: =VLOOKUP(C:C,total251219111800!B:F,5,0) -> 749 | M67: 500 | N67: =L67 -> 749 | O67: 2738 | P67: 0 | Q67: 0 | R67: 0 | S67: 180 | T67: -180 | U67: 2558 | V67: 1809 | W67: 0.27355734
A68: 63 | B68: 伊賀 | C68: AIC-05IV | D68: ｽﾞﾚにくいｲｽ脚ｶﾊﾞｰ 1脚用 | E68: IV | F68: 2715 | G68: 1898 | H68: 1974 | I68: =VLOOKUP(C68,'202310-202403出荷数total2403220951'!B:F,5,0) -> 822 | J68: =VLOOKUP(C68,'出荷数2307～2406total241008110618'!B:F,5,0) -> 1831 | K68: =VLOOKUP(C68,'出荷数2407-2506total250730101950'!B:F,5,0) -> 1431 | L68: =VLOOKUP(C:C,total251219111800!B:F,5,0) -> 874 | N68: =L68 -> 874 | O68: 4053 | P68: 0 | Q68: 0 | R68: 0 | S68: 0 | T68: 0 | U68: 4053 | V68: 3179 | W68: 0.21564273 | X68: 23％発注点よりﾏｲﾅｽ 874→672
A69: 64 | B69: 伊賀 | C69: ABO-19 | D69: 防災用薄型ウォーターバッグ9L | F69: 680 | G69: 2488 | H69: 824 | I69: =VLOOKUP(C69,'202310-202403出荷数total2403220951'!B:F,5,0) -> 454 | J69: =VLOOKUP(C69,'出荷数2307～2406total241008110618'!B:F,5,0) -> 939 | K69: =VLOOKUP(C69,'出荷数2407-2506total250730101950'!B:F,5,0) -> 1427 | L69: =VLOOKUP(C:C,total251219111800!B:F,5,0) -> 203 | N69: =L69 -> 203 | O69: 2681 | P69: 0 | Q69: 0 | R69: 0 | S69: 0 | T69: 0 | U69: 2681 | V69: 2478 | W69: 0.075718016
A70: 65 | B70: 伊賀 | C70: AYC-101PK | D70: 耳すっきりクリーナー | E70: ピンク | F70: 1433 | G70: 1030 | H70: 1015 | I70: =VLOOKUP(C70,'202310-202403出荷数total2403220951'!B:F,5,0) -> 273 | J70: =VLOOKUP(C70,'出荷数2307～2406total241008110618'!B:F,5,0) -> 828 | K70: =VLOOKUP(C70,'出荷数2407-2506total250730101950'!B:F,5,0) -> 776 | L70: =VLOOKUP(C:C,total251219111800!B:F,5,0) -> 430 | N70: =L70 -> 430 | O70: 1894 | P70: 90 | Q70: 0 | R70: 0 | S70: 0 | T70: 90 | U70: 1894 | V70: 1464 | W70: 0.21673387
A71: 66 | B71: 伊賀 | C71: AUV-3301 | D71: 見えにくい汚れの発見ライト | G71: 600 | H71: 106 | I71: =VLOOKUP(C71,'202310-202403出荷数total2403220951'!B:F,5,0) -> 250 | J71: =VLOOKUP(C71,'出荷数2307～2406total241008110618'!B:F,5,0) -> 351 | K71: =VLOOKUP(C71,'出荷数2407-2506total250730101950'!B:F,5,0) -> 157 | L71: =VLOOKUP(C:C,total251219111800!B:F,5,0) -> #N/A | N71: =L71 -> #N/A | O71: 2381 | P71: 0 | Q71: 0 | R71: 0 | S71: 0 | T71: 0 | U71: 2381 | V71: #N/A | W71: #N/A
B72: 伊賀 | C72: AUV-3301C | D72: 365nmUVﾗｲﾄ | H72: 100 | I72: =VLOOKUP(C72,'202310-202403出荷数total2403220951'!B:F,5,0) -> 17 | J72: =VLOOKUP(C72,'出荷数2307～2406total241008110618'!B:F,5,0) -> 35 | K72: =VLOOKUP(C72,'出荷数2407-2506total250730101950'!B:F,5,0) -> 80 | L72: =VLOOKUP(C:C,total251219111800!B:F,5,0) -> 16 | N72: =L72 -> 16 | O72: 303 | P72: 0 | Q72: 0 | R72: 0 | S72: 0 | T72: 0 | U72: 303 | V72: 287 | W72: 0.052805281
A73: 67 | B73: 伊賀 | C73: AHL-1101 | D73: 単３と単１が使ええる防水ライト | F73: 4431 | G73: 2178 | H73: 3224 | I73: =VLOOKUP(C73,'202310-202403出荷数total2403220951'!B:F,5,0) -> 2952 | J73: =VLOOKUP(C73,'出荷数2307～2406total241008110618'!B:F,5,0) -> 5989 | K73: =VLOOKUP(C73,'出荷数2407-2506total250730101950'!B:F,5,0) -> 4689 | L73: =VLOOKUP(C:C,total251219111800!B:F,5,0) -> 1757 | N73: =L73 -> 1757 | O73: 6057 | P73: 200 | Q73: 0 | R73: 0 | S73: 200 | T73: 0 | U73: 5857 | V73: 4100 | W73: 0.2808055
A74: 68 | B74: 伊賀 | C74: ABO-03 | D74: 防災用ポリバケツ | F74: 3496 | G74: 2391 | H74: 1985 | I74: =VLOOKUP(C74,'202310-202403出荷数total2403220951'!B:F,5,0) -> 1236 | J74: =VLOOKUP(C74,'出荷数2307～2406total241008110618'!B:F,5,0) -> 2298 | K74: =VLOOKUP(C74,'出荷数2407-2506total250730101950'!B:F,5,0) -> 8616 | L74: =VLOOKUP(C:C,total251219111800!B:F,5,0) -> 1136 | M74: 8000 | N74: 8000 | O74: 14689 | P74: 3200 | Q74: 0 | R74: 0 | S74: 5200 | T74: -2000 | U74: 9489 | V74: 1489 | W74: 0.44720219
A75: 69 | B75: 伊賀 | C75: KCA-002 | D75: キューベルク 充電式ヘッドライト270 | F75: 44 | G75: 866 | H75: 614 | I75: =VLOOKUP(C75,'202310-202403出荷数total2403220951'!B:F,5,0) -> 333 | J75: =VLOOKUP(C75,'出荷数2307～2406total241008110618'!B:F,5,0) -> 1142 | K75: =VLOOKUP(C75,'出荷数2407-2506total250730101950'!B:F,5,0) -> 925 | L75: =VLOOKUP(C:C,total251219111800!B:F,5,0) -> 135 | N75: =L75 -> 135 | O75: 1771 | P75: 0 | Q75: 0 | R75: 0 | S75: 0 | T75: 0 | U75: 1771 | V75: 1636 | W75: 0.07622812
A76: 70 | B76: 伊賀 | C76: AHM-201 | D76: 防雨ハンドメガホン | F76: 410 | G76: 741 | H76: 1112 | I76: =VLOOKUP(C76,'202310-202403出荷数total2403220951'!B:F,5,0) -> 662 | J76: =VLOOKUP(C76,'出荷数2307～2406total241008110618'!B:F,5,0) -> 1332 | K76: =VLOOKUP(C76,'出荷数2407-2506total250730101950'!B:F,5,0) -> 2848 | L76: =VLOOKUP(C:C,total251219111800!B:F,5,0) -> 1014 | M76: 1000 | N76: =L76 -> 1014 | O76: 1653 | P76: 200 | Q76: 3000 | R76: 0 | S76: 200 | T76: 0 | U76: 4453 | V76: 3439 | W76: 0.54722072
A77: 71 | B77: 伊賀 | C77: AAM-200 | D77: 雨ふりセンサーⅡ | F77: 1477 | G77: 1110 | H77: 696 | I77: =VLOOKUP(C77,'202310-202403出荷数total2403220951'!B:F,5,0) -> 116 | J77: =VLOOKUP(C77,'出荷数2307～2406total241008110618'!B:F,5,0) -> 801 | K77: =VLOOKUP(C77,'出荷数2407-2506total250730101950'!B:F,5,0) -> 703 | L77: =VLOOKUP(C:C,total251219111800!B:F,5,0) -> 319 | N77: =L77 -> 319 | O77: 453 | P77: 0 | Q77: 0 | R77: 0 | S77: 0 | T77: 0 | U77: 453 | V77: 134 | W77: 0.70419426 | X77: 在庫減ってから発注。発注ロット2000希望
A78: 72 | B78: 伊賀 | C78: AHA-4306 | D78: 自動点灯前かごクリップライト | F78: 1324 | G78: 1622 | H78: 1792 | I78: =VLOOKUP(C78,'202310-202403出荷数total2403220951'!B:F,5,0) -> 1087 | J78: =VLOOKUP(C78,'出荷数2307～2406total241008110618'!B:F,5,0) -> 1970 | K78: =VLOOKUP(C78,'出荷数2407-2506total250730101950'!B:F,5,0) -> 1824 | L78: =VLOOKUP(C:C,total251219111800!B:F,5,0) -> 900 | N78: =L78 -> 900 | O78: 2934 | P78: 0 | Q78: 0 | R78: 0 | S78: 0 | T78: 0 | U78: 2934 | V78: 2034 | W78: 0.30674847
A79: 73 | B79: 伊賀 | C79: KCA-001 | D79: キューベルク 充電式ヘッドライト220 | F79: 30 | G79: 1288 | H79: 1790 | I79: =VLOOKUP(C79,'202310-202403出荷数total2403220951'!B:F,5,0) -> 845 | J79: =VLOOKUP(C79,'出荷数2307～2406total241008110618'!B:F,5,0) -> 1682 | K79: =VLOOKUP(C79,'出荷数2407-2506total250730101950'!B:F,5,0) -> 1326 | L79: =VLOOKUP(C:C,total251219111800!B:F,5,0) -> 366 | N79: =L79 -> 366 | O79: 1744 | P79: 0 | Q79: 0 | R79: 0 | S79: 0 | T79: 0 | U79: 1744 | V79: 1378 | W79: 0.20986239
A80: 74 | B80: 伊賀 | C80: AOM-01 | D80: かんたんお話メモ | F80: 6851 | G80: 3631 | H80: 3310 | I80: =VLOOKUP(C80,'202310-202403出荷数total2403220951'!B:F,5,0) -> 2276 | J80: =VLOOKUP(C80,'出荷数2307～2406total241008110618'!B:F,5,0) -> 2977 | K80: =VLOOKUP(C80,'出荷数2407-2506total250730101950'!B:F,5,0) -> 1413 | L80: =VLOOKUP(C:C,total251219111800!B:F,5,0) -> 456 | N80: =L80 -> 456 | O80: 2271 | P80: 200 | Q80: 0 | R80: 0 | S80: 200 | T80: 0 | U80: 2071 | V80: 1615 | W80: 0.18454067
A81: 75 | B81: 伊賀 | C81: AKM-3205BL | D81: 首ふり毛だまクリーナー | E81: ブルー | F81: 7367 | G81: 4388 | H81: 521 | I81: =VLOOKUP(C81,'202310-202403出荷数total2403220951'!B:F,5,0) -> 2848 | J81: =VLOOKUP(C81,'出荷数2307～2406total241008110618'!B:F,5,0) -> 3288 | K81: =VLOOKUP(C81,'出荷数2407-2506total250730101950'!B:F,5,0) -> 2304 | L81: =VLOOKUP(C:C,total251219111800!B:F,5,0) -> 744 | N81: =L81 -> 744 | O81: 4645 | P81: 3880 | Q81: 0 | R81: 0 | S81: 3880 | T81: 0 | U81: 765 | V81: 21 | W81: 0.087272727
A82: 76 | B82: 伊賀 | C82: ABO-12 | D82: 防災用ポリタンク 10L | F82: 10633 | G82: 6065 | H82: 2945 | I82: =VLOOKUP(C82,'202310-202403出荷数total2403220951'!B:F,5,0) -> 3324 | J82: =VLOOKUP(C82,'出荷数2307～2406total241008110618'!B:F,5,0) -> 5243 | K82: =VLOOKUP(C82,'出荷数2407-2506total250730101950'!B:F,5,0) -> 13654 | L82: =VLOOKUP(C:C,total251219111800!B:F,5,0) -> 1335 | M82: 4500 | N82: 3000 | O82: 6938 | P82: 3060 | Q82: 0 | R82: 0 | S82: 3160 | T82: -100 | U82: 3778 | V82: 778 | W82: 0.30006001
A83: 77 | B83: 伊賀 | C83: ALA-4310 | D83: ゆれたら点灯ライト(クリアケース) | F83: 270 | G83: 814 | H83: 677 | I83: =VLOOKUP(C83,'202310-202403出荷数total2403220951'!B:F,5,0) -> 269 | J83: =VLOOKUP(C83,'出荷数2307～2406total241008110618'!B:F,5,0) -> 668 | K83: =VLOOKUP(C83,'出荷数2407-2506total250730101950'!B:F,5,0) -> 826 | L83: =VLOOKUP(C:C,total251219111800!B:F,5,0) -> 90 | N83: =L83 -> 90 | O83: 2443 | P83: 0 | Q83: 0 | R83: 0 | S83: 0 | T83: 0 | U83: 2443 | V83: 2353 | W83: 0.036839951
A84: 78 | B84: 伊賀 | C84: ALA-3301 | D84: てるてるランタン | F84: 3306 | G84: 2817 | H84: 1743 | I84: =VLOOKUP(C84,'202310-202403出荷数total2403220951'!B:F,5,0) -> 273 | J84: =VLOOKUP(C84,'出荷数2307～2406total241008110618'!B:F,5,0) -> 477 | K84: =VLOOKUP(C84,'出荷数2407-2506total250730101950'!B:F,5,0) -> 351 | L84: =VLOOKUP(C:C,total251219111800!B:F,5,0) -> 211 | N84: =L84 -> 211 | O84: 7233 | P84: 0 | Q84: 0 | R84: 0 | S84: 0 | T84: 0 | U84: 7233 | V84: 7022 | W84: 0.029171851
A85: 79 | B85: 伊賀 | C85: ARO-02 | D85: 自動消灯安心のろうそくミニ | F85: 1177 | G85: 2128 | H85: 1537 | I85: =VLOOKUP(C85,'202310-202403出荷数total2403220951'!B:F,5,0) -> 834 | J85: =VLOOKUP(C85,'出荷数2307～2406total241008110618'!B:F,5,0) -> 1486 | K85: =VLOOKUP(C85,'出荷数2407-2506total250730101950'!B:F,5,0) -> 1411 | L85: =VLOOKUP(C:C,total251219111800!B:F,5,0) -> 822 | N85: =L85 -> 822 | O85: 2515 | P85: 0 | Q85: 0 | R85: 0 | S85: 0 | T85: 0 | U85: 2515 | V85: 1693 | W85: 0.32683897
A86: 80 | B86: 伊賀 | C86: ACR-01 | D86: スイッチ付きコードリール | F86: 1511 | G86: 1031 | H86: 1052 | I86: =VLOOKUP(C86,'202310-202403出荷数total2403220951'!B:F,5,0) -> 513 | J86: =VLOOKUP(C86,'出荷数2307～2406total241008110618'!B:F,5,0) -> 546 | K86: =VLOOKUP(C86,'出荷数2407-2506total250730101950'!B:F,5,0) -> #N/A | L86: =VLOOKUP(C:C,total251219111800!B:F,5,0) -> #N/A | N86: =L86 -> #N/A | O86: 0 | P86: 0 | Q86: 0 | R86: 0 | S86: 0 | T86: 0 | U86: 0 | V86: #N/A | W86: #N/A
A87: 81 | B87: 伊賀 | C87: AKR-20 | D87: ねこのキーカバー | F87: 3121 | G87: 3233 | H87: 3120 | I87: =VLOOKUP(C87,'202310-202403出荷数total2403220951'!B:F,5,0) -> 1553 | J87: =VLOOKUP(C87,'出荷数2307～2406total241008110618'!B:F,5,0) -> 3072 | K87: =VLOOKUP(C87,'出荷数2407-2506total250730101950'!B:F,5,0) -> 3947 | L87: =VLOOKUP(C:C,total251219111800!B:F,5,0) -> 1574 | N87: =L87 -> 1574 | O87: 4200 | P87: 0 | Q87: 0 | R87: 0 | S87: 0 | T87: 0 | U87: 4200 | V87: 2626 | W87: 0.3747619
A88: 82 | B88: 伊賀 | C88: AYD-102AD | D88: 電話の拡声器 ⅡＡＣアダプター | F88: 1334 | G88: 1879 | H88: 908 | I88: =VLOOKUP(C88,'202310-202403出荷数total2403220951'!B:F,5,0) -> 222 | J88: =VLOOKUP(C88,'出荷数2307～2406total241008110618'!B:F,5,0) -> 732 | K88: =VLOOKUP(C88,'出荷数2407-2506total250730101950'!B:F,5,0) -> 817 | L88: =VLOOKUP(C:C,total251219111800!B:F,5,0) -> 295 | N88: =L88 -> 295 | O88: 258 | P88: 0 | Q88: 0 | R88: 0 | S88: 0 | T88: 0 | U88: 258 | V88: -37 | W88: 1.1434109
A89: 83 | B89: 伊賀 | C89: AKR-11 | D89: シリコンキーカバー | F89: 3215 | G89: 3856 | H89: 4252 | I89: =VLOOKUP(C89,'202310-202403出荷数total2403220951'!B:F,5,0) -> 2413 | J89: =VLOOKUP(C89,'出荷数2307～2406total241008110618'!B:F,5,0) -> 4143 | K89: =VLOOKUP(C89,'出荷数2407-2506total250730101950'!B:F,5,0) -> 6112 | L89: =VLOOKUP(C:C,total251219111800!B:F,5,0) -> 2918 | N89: =L89 -> 2918 | O89: 3878 | P89: 0 | Q89: 0 | R89: 0 | S89: 0 | T89: 0 | U89: 3878 | V89: 960 | W89: 0.75244972
A90: 84 | B90: 伊賀 | C90: AST-3401 | D90: スマホが充電できるスタンドライト | F90: 102 | G90: 340 | H90: 49 | I90: =VLOOKUP(C90,'202310-202403出荷数total2403220951'!B:F,5,0) -> 6 | J90: =VLOOKUP(C90,'出荷数2307～2406total241008110618'!B:F,5,0) -> 434 | K90: =VLOOKUP(C90,'出荷数2407-2506total250730101950'!B:F,5,0) -> #N/A | L90: =VLOOKUP(C:C,total251219111800!B:F,5,0) -> #N/A | N90: =L90 -> #N/A | O90: 0 | P90: 0 | Q90: 0 | R90: 0 | S90: 0 | T90: 0 | U90: 0 | V90: #N/A | W90: #N/A
A91: 85 | B91: 伊賀 | C91: ASL-3310 | D91: マグネット付くるっと回るセンサーライト | F91: 1538 | G91: 2587 | H91: 571 | I91: =VLOOKUP(C91,'202310-202403出荷数total2403220951'!B:F,5,0) -> 874 | J91: =VLOOKUP(C91,'出荷数2307～2406total241008110618'!B:F,5,0) -> 1045 | K91: =VLOOKUP(C91,'出荷数2407-2506total250730101950'!B:F,5,0) -> 429 | L91: =VLOOKUP(C:C,total251219111800!B:F,5,0) -> 22 | M91: 1400 | N91: 1400 | O91: 4440 | P91: 100 | Q91: 0 | R91: 0 | S91: 100 | T91: 0 | U91: 4340 | V91: 2940 | W91: 0.30837004
A92: 87 | B92: 伊賀 | C92: ASL-3303 | D92: ドア用センサーライト | F92: 8125 | G92: 7398 | H92: 4528 | I92: =VLOOKUP(C92,'202310-202403出荷数total2403220951'!B:F,5,0) -> 1614 | J92: =VLOOKUP(C92,'出荷数2307～2406total241008110618'!B:F,5,0) -> 3692 | K92: =VLOOKUP(C92,'出荷数2407-2506total250730101950'!B:F,5,0) -> 3180 | L92: =VLOOKUP(C:C,total251219111800!B:F,5,0) -> 1448 | N92: =L92 -> 1448 | O92: 5564 | P92: 715 | Q92: 40 | R92: 0 | S92: 1200 | T92: -485 | U92: 4404 | V92: 2956 | W92: 0.23060997
A93: 88 | B93: 伊賀 | C93: ASL-33032 | D93: ドア用センサーライト（ｼｮｯﾌﾟﾁｬﾝﾈﾙ） | F93: 0 | G93: 5 | H93: 904 | I93: =VLOOKUP(C93,'202310-202403出荷数total2403220951'!B:F,5,0) -> #N/A | J93: =VLOOKUP(C93,'出荷数2307～2406total241008110618'!B:F,5,0) -> #N/A | K93: =VLOOKUP(C93,'出荷数2407-2506total250730101950'!B:F,5,0) -> #N/A | L93: =VLOOKUP(C:C,total251219111800!B:F,5,0) -> #N/A | M93: 380 | N93: 380 | O93: 781 | P93: 0 | Q93: 0 | R93: 0 | S93: 0 | T93: 0 | U93: 781 | V93: 401 | W93: 0.4865557
A94: 89 | B94: 伊賀 | C94: ASL-3303K | D94: ドア用センサーライト（ケーズ） | F94: 684 | G94: 626 | H94: 772 | I94: =VLOOKUP(C94,'202310-202403出荷数total2403220951'!B:F,5,0) -> 81 | J94: =VLOOKUP(C94,'出荷数2307～2406total241008110618'!B:F,5,0) -> 221 | K94: =VLOOKUP(C94,'出荷数2407-2506total250730101950'!B:F,5,0) -> #N/A | L94: =VLOOKUP(C:C,total251219111800!B:F,5,0) -> #N/A | N94: =L94 -> #N/A | O94: 3 | P94: 0 | Q94: 0 | R94: 0 | S94: 0 | T94: 0 | U94: 3 | V94: #N/A | W94: #N/A
A95: 90 | B95: 伊賀 | C95: AIC-04BE | D95: ｽﾞﾚにくいｲｽ脚ｶﾊﾞｰ 4脚用 | E95: BE | F95: 4518 | G95: 3870 | H95: 3467 | I95: =VLOOKUP(C95,'202310-202403出荷数total2403220951'!B:F,5,0) -> 1429 | J95: =VLOOKUP(C95,'出荷数2307～2406total241008110618'!B:F,5,0) -> 3078 | K95: =VLOOKUP(C95,'出荷数2407-2506total250730101950'!B:F,5,0) -> 3161 | L95: =VLOOKUP(C:C,total251219111800!B:F,5,0) -> 1695 | N95: =L95 -> 1695 | O95: 571 | P95: 0 | Q95: 3000 | R95: 0 | S95: 0 | T95: 0 | U95: 3571 | V95: 1876 | W95: 2.9684764 | X95: 48％発注点よりﾏｲﾅｽ 1695→881
A96: 91 | B96: 伊賀 | C96: AST-3303 | D96: スマホが置けるスタンドライト | F96: 12335 | G96: 8441 | H96: 3599 | I96: =VLOOKUP(C96,'202310-202403出荷数total2403220951'!B:F,5,0) -> 3021 | J96: =VLOOKUP(C96,'出荷数2307～2406total241008110618'!B:F,5,0) -> 4038 | K96: =VLOOKUP(C96,'出荷数2407-2506total250730101950'!B:F,5,0) -> 1769 | L96: =VLOOKUP(C:C,total251219111800!B:F,5,0) -> 560 | N96: =L96 -> 560 | O96: 9006 | P96: 1500 | Q96: 0 | R96: 0 | S96: 1500 | T96: 0 | U96: 7506 | V96: 6946 | W96: 0.053302875
A97: 92 | B97: 伊賀 | C97: AKM-3204PK | D97: 立てて置ける毛だまクリーナー | E97: ピンク | F97: 2663 | G97: 4626 | H97: 4263 | I97: =VLOOKUP(C97,'202310-202403出荷数total2403220951'!B:F,5,0) -> 1415 | J97: =VLOOKUP(C97,'出荷数2307～2406total241008110618'!B:F,5,0) -> 2582 | K97: =VLOOKUP(C97,'出荷数2407-2506total250730101950'!B:F,5,0) -> 2814 | L97: =VLOOKUP(C:C,total251219111800!B:F,5,0) -> 1960 | N97: =L97 -> 1960 | O97: 4341 | P97: 800 | Q97: 0 | R97: 0 | S97: 800 | T97: 0 | U97: 3541 | V97: 1581 | W97: 0.38124878
A98: 93 | B98: 伊賀 | C98: ADR-100 | D98: ドライヤースタンド | F98: 3167 | G98: 3686 | H98: 4490 | I98: =VLOOKUP(C98,'202310-202403出荷数total2403220951'!B:F,5,0) -> 1027 | J98: =VLOOKUP(C98,'出荷数2307～2406total241008110618'!B:F,5,0) -> 2480 | K98: =VLOOKUP(C98,'出荷数2407-2506total250730101950'!B:F,5,0) -> 1578 | L98: =VLOOKUP(C:C,total251219111800!B:F,5,0) -> 247 | N98: =L98 -> 247 | O98: 2780 | P98: 0 | Q98: 0 | R98: 0 | S98: 100 | T98: -100 | U98: 2680 | V98: 2433 | W98: 0.088848921
A99: 94 | B99: 伊賀 | C99: AYC-101BL | D99: 耳すっきりクリーナー | E99: ブルー | F99: 5717 | H99: 3844 | I99: =VLOOKUP(C99,'202310-202403出荷数total2403220951'!B:F,5,0) -> 1058 | J99: =VLOOKUP(C99,'出荷数2307～2406total241008110618'!B:F,5,0) -> 2412 | K99: =VLOOKUP(C99,'出荷数2407-2506total250730101950'!B:F,5,0) -> 2874 | L99: =VLOOKUP(C:C,total251219111800!B:F,5,0) -> 1317 | N99: =L99 -> 1317 | O99: 2221 | P99: 220 | Q99: 0 | R99: 0 | S99: 250 | T99: -30 | U99: 1971 | V99: 654 | W99: 0.53953298
A100: 95 | B100: 伊賀 | C100: AHL-2203 | D100: 単2形LED防雨ライト | F100: 15469 | G100: 8369 | H100: 9994 | I100: =VLOOKUP(C100,'202310-202403出荷数total2403220951'!B:F,5,0) -> 2524 | J100: =VLOOKUP(C100,'出荷数2307～2406total241008110618'!B:F,5,0) -> 7246 | K100: =VLOOKUP(C100,'出荷数2407-2506total250730101950'!B:F,5,0) -> 19015 | L100: =VLOOKUP(C:C,total251219111800!B:F,5,0) -> 3771 | M100: 4500 | N100: 3000 | O100: 7849 | P100: 6870 | Q100: 3000 | R100: 0 | S100: 7270 | T100: -400 | U100: 3579 | V100: 579 | W100: 0.20381819
...

Sheet 80123
B1: 商品センター | C1: 品番 | D1: 商品区分 | E1: カラー | F1: 72期 | G1: 73期 | H1: 74期(1期) | I1: 2023/10/1～2024/3/21（6か月） | J1: 75期(2期) | K1: 76期（３期 ） | L1: 77期（4期 7/1-12/18） | N1: 発注点 5ヶ月分なのでそのまま | O1: 在庫数 ロジザード | Q1: 入荷予定 ロジザード | S1: 確保数 弥生(在庫確保) | T1: 確保数チェック 0じゃなかったらロジザード修正 | U1: 有効数量 フリー在庫の数 | V1: 発注検討フラグ マイナスの場合発注検討 | W1: 在庫回転率 | X1: 前回決定事項（1/16） | Y1: 決定事項 | AE1: 前回決定事項（/） | AG1: 決定事項
A2: 1 | B2: 伊賀 | C2: APL-4312SBL | D2: ミニホイッスル付LEDアルミライトⅡ | H2: 192 | I2: =VLOOKUP(C2,'202310-202403出荷数total2403220951'!B:F,5,0) -> 71 | J2: =VLOOKUP(C2,'出荷数2307～2406total241008110618'!B:F,5,0) -> 281 | K2: =VLOOKUP(C2,'出荷数2407-2506total250730101950'!B:F,5,0) -> 902 | L2: =VLOOKUP(C:C,total251219111800!B:F,5,0) -> 386 | N2: =L2 -> 386 | O2: 427 | P2: 640 | Q2: 0 | R2: 0 | S2: 540 | T2: 100 | U2: -113 | V2: -499 | W2: 0.36176195
A3: 2 | B3: 伊賀 | C3: APL-4312SPK | D3: ミニホイッスル付LEDアルミライトⅡ | H3: 2161 | I3: =VLOOKUP(C3,'202310-202403出荷数total2403220951'!B:F,5,0) -> 1018 | J3: =VLOOKUP(C3,'出荷数2307～2406total241008110618'!B:F,5,0) -> 1930 | K3: =VLOOKUP(C3,'出荷数2407-2506total250730101950'!B:F,5,0) -> 3388 | L3: =VLOOKUP(C:C,total251219111800!B:F,5,0) -> 903 | N3: =L3 -> 903 | O3: 1882 | P3: 1880 | Q3: 0 | R3: 0 | S3: 1790 | T3: 90 | U3: 92 | V3: -811 | W3: 0.2400319
A4: 86 | B4: 伊賀 | C4: ABO-08BL | D4: ミニホイッスル | E4: ブルー | F4: 527 | G4: 2107 | H4: 796 | I4: =VLOOKUP(C4,'202310-202403出荷数total2403220951'!B:F,5,0) -> 1409 | J4: =VLOOKUP(C4,'出荷数2307～2406total241008110618'!B:F,5,0) -> 1708 | K4: =VLOOKUP(C4,'出荷数2407-2506total250730101950'!B:F,5,0) -> 1865 | L4: =VLOOKUP(C:C,total251219111800!B:F,5,0) -> 474 | M4: 1000 | N4: 1000 | O4: 6766 | P4: 0 | Q4: 0 | R4: 0 | S4: 0 | T4: 0 | U4: 6766 | V4: 5766 | W4: 0.14779781
A5: 107 | B5: 伊賀 | C5: ABO-08PK | D5: ミニホイッスル | E5: ピンク | F5: 3939 | G5: 5966 | H5: 5009 | I5: =VLOOKUP(C5,'202310-202403出荷数total2403220951'!B:F,5,0) -> 6490 | J5: =VLOOKUP(C5,'出荷数2307～2406total241008110618'!B:F,5,0) -> 17931 | K5: =VLOOKUP(C5,'出荷数2407-2506total250730101950'!B:F,5,0) -> 28387 | L5: =VLOOKUP(C:C,total251219111800!B:F,5,0) -> 4495 | N5: =L5 -> 4495 | O5: 28550 | P5: 24430 | Q5: 800 | R5: 0 | S5: 24430 | T5: 0 | U5: 4920 | V5: 425 | W5: 0.084843337
A6: 109 | B6: 伊賀 | C6: APL-4302S | D6: ＬＥＤミニアルミライト | F6: 1094 | G6: 3475 | H6: 834 | I6: =VLOOKUP(C6,'202310-202403出荷数total2403220951'!B:F,5,0) -> 444 | J6: =VLOOKUP(C6,'出荷数2307～2406total241008110618'!B:F,5,0) -> 789 | K6: =VLOOKUP(C6,'出荷数2407-2506total250730101950'!B:F,5,0) -> 232 | L6: =VLOOKUP(C:C,total251219111800!B:F,5,0) -> 177 | N6: =L6 -> 177 | O6: 3754 | P6: 0 | Q6: 300 | R6: 0 | S6: 0 | T6: 0 | U6: 4054 | V6: 3877 | W6: 0.047149707
A7: 3 | B7: 伊賀 | C7: ASL-3308SK | D7: ウォールセンサーライト 箱 | E7: しかく | F7: 1 | G7: 0 | H7: 4 | I7: =VLOOKUP(C7,'202310-202403出荷数total2403220951'!B:F,5,0) -> #N/A | J7: =VLOOKUP(C7,'出荷数2307～2406total241008110618'!B:F,5,0) -> #N/A | K7: =VLOOKUP(C7,'出荷数2407-2506total250730101950'!B:F,5,0) -> #N/A | L7: =VLOOKUP(C:C,total251219111800!B:F,5,0) -> #N/A | N7: 0 | O7: 1 | P7: 0 | Q7: 0 | R7: 0 | S7: 0 | T7: 0 | U7: 1 | V7: 1 | W7: 0
A8: 4 | B8: 伊賀 | C8: AHL-3201RD | D8: LEDハンディライト | H8: 2048 | I8: =VLOOKUP(C8,'202310-202403出荷数total2403220951'!B:F,5,0) -> 2098 | J8: =VLOOKUP(C8,'出荷数2307～2406total241008110618'!B:F,5,0) -> 3644 | K8: =VLOOKUP(C8,'出荷数2407-2506total250730101950'!B:F,5,0) -> 2910 | L8: =VLOOKUP(C:C,total251219111800!B:F,5,0) -> 2559 | N8: =L8 -> 2559 | O8: 3061 | P8: 0 | Q8: 0 | R8: 0 | S8: 0 | T8: 0 | U8: 3061 | V8: 502 | W8: 0.83600131
A9: 5 | B9: 伊賀 | C9: AHL-3201WH | D9: LEDハンディライト | H9: 116 | I9: =VLOOKUP(C9,'202310-202403出荷数total2403220951'!B:F,5,0) -> 220 | J9: =VLOOKUP(C9,'出荷数2307～2406total241008110618'!B:F,5,0) -> 378 | K9: =VLOOKUP(C9,'出荷数2407-2506total250730101950'!B:F,5,0) -> 2016 | L9: =VLOOKUP(C:C,total251219111800!B:F,5,0) -> 281 | M9: 1000 | N9: 1000 | O9: 5183 | P9: 0 | Q9: 0 | R9: 0 | S9: 0 | T9: 0 | U9: 5183 | V9: 4183 | W9: 0.19293845
A10: 6 | B10: 伊賀 | C10: AHL-1400 | D10: LED強力ライト | H10: 15126 | I10: =VLOOKUP(C10,'202310-202403出荷数total2403220951'!B:F,5,0) -> 9163 | J10: =VLOOKUP(C10,'出荷数2307～2406total241008110618'!B:F,5,0) -> 19757 | K10: =VLOOKUP(C10,'出荷数2407-2506total250730101950'!B:F,5,0) -> 20812 | L10: =VLOOKUP(C:C,total251219111800!B:F,5,0) -> 4356 | N10: =L10 -> 4356 | O10: 1550 | P10: 13515 | Q10: 0 | R10: 0 | S10: 14405 | T10: -890 | U10: -12855 | V10: -17211 | W10: 0.28914703
A11: 7 | B11: 伊賀 | C11: AHL-1400T | D11: LED強力ライト(トップ) | H11: 2084 | I11: =VLOOKUP(C11,'202310-202403出荷数total2403220951'!B:F,5,0) -> 1160 | J11: =VLOOKUP(C11,'出荷数2307～2406total241008110618'!B:F,5,0) -> 1821 | K11: =VLOOKUP(C11,'出荷数2407-2506total250730101950'!B:F,5,0) -> 1120 | L11: =VLOOKUP(C:C,total251219111800!B:F,5,0) -> 160 | N11: =L11 -> 160 | O11: 2 | P11: 0 | Q11: 0 | R11: 0 | S11: 0 | T11: 0 | U11: 2 | V11: -158 | W11: 80
A12: 8 | B12: 伊賀 | C12: ASL-3308KU | D12: ウォールセンサーライト 箱 | E12: くも | F12: 193 | G12: 1 | H12: 100 | I12: =VLOOKUP(C12,'202310-202403出荷数total2403220951'!B:F,5,0) -> 43 | J12: =VLOOKUP(C12,'出荷数2307～2406total241008110618'!B:F,5,0) -> 51 | K12: =VLOOKUP(C12,'出荷数2407-2506total250730101950'!B:F,5,0) -> 12 | L12: =VLOOKUP(C:C,total251219111800!B:F,5,0) -> 3 | N12: =L12 -> 3 | O12: 999 | P12: 0 | Q12: 0 | R12: 0 | S12: 0 | T12: 0 | U12: 999 | V12: 996 | W12: 0.003003003
A13: 9 | B13: 伊賀 | C13: ANS-502 | D13: テレビ用手もとスピーカー | G13: 6 | H13: 2364 | I13: =VLOOKUP(C13,'202310-202403出荷数total2403220951'!B:F,5,0) -> 1052 | J13: =VLOOKUP(C13,'出荷数2307～2406total241008110618'!B:F,5,0) -> 1711 | K13: =VLOOKUP(C13,'出荷数2407-2506total250730101950'!B:F,5,0) -> 1026 | L13: =VLOOKUP(C:C,total251219111800!B:F,5,0) -> 587 | N13: =L13 -> 587 | O13: 3548 | P13: 0 | Q13: 0 | R13: 0 | S13: 0 | T13: 0 | U13: 3548 | V13: 2961 | W13: 0.16544532
A14: 10 | B14: 伊賀 | C14: ASL-3308US | D14: ウォールセンサーライト 箱 | E14: うさぎ | F14: 0 | G14: 3 | H14: 363 | I14: =VLOOKUP(C14,'202310-202403出荷数total2403220951'!B:F,5,0) -> #N/A | J14: =VLOOKUP(C14,'出荷数2307～2406total241008110618'!B:F,5,0) -> 1 | K14: =VLOOKUP(C14,'出荷数2407-2506total250730101950'!B:F,5,0) -> 7 | L14: =VLOOKUP(C:C,total251219111800!B:F,5,0) -> #N/A | N14: 0 | O14: 744 | P14: 0 | Q14: 0 | R14: 0 | S14: 0 | T14: 0 | U14: 744 | V14: 744 | W14: 0
A15: 11 | B15: 伊賀 | C15: ASL-3308CSK | D15: ウォールセンサーライト ブリスター | E15: しかく | F15: 23 | G15: 4 | H15: 0 | I15: =VLOOKUP(C15,'202310-202403出荷数total2403220951'!B:F,5,0) -> 1 | J15: =VLOOKUP(C15,'出荷数2307～2406total241008110618'!B:F,5,0) -> 705 | K15: =VLOOKUP(C15,'出荷数2407-2506total250730101950'!B:F,5,0) -> 1 | L15: =VLOOKUP(C:C,total251219111800!B:F,5,0) -> 1 | N15: =L15 -> 1 | O15: 0 | P15: 0 | Q15: 0 | R15: 0 | S15: 0 | T15: 0 | U15: 0 | V15: -1 | W15: #DIV/0!
A16: 12 | B16: 伊賀 | C16: ASL-3308CUS | D16: ウォールセンサーライト ブリスター | E16: うさぎ | F16: 35 | G16: 26 | H16: 5 | I16: =VLOOKUP(C16,'202310-202403出荷数total2403220951'!B:F,5,0) -> 3 | J16: =VLOOKUP(C16,'出荷数2307～2406total241008110618'!B:F,5,0) -> 6 | K16: =VLOOKUP(C16,'出荷数2407-2506total250730101950'!B:F,5,0) -> 3 | L16: =VLOOKUP(C:C,total251219111800!B:F,5,0) -> 142 | N16: =L16 -> 142 | O16: 4414 | P16: 0 | Q16: 0 | R16: 0 | S16: 0 | T16: 0 | U16: 4414 | V16: 4272 | W16: 0.032170367
A17: 13 | B17: 伊賀 | C17: AKM-3205PK | D17: 首ふり毛だまクリーナー | E17: ピンク | F17: 33 | G17: 24 | H17: 2990 | I17: =VLOOKUP(C17,'202310-202403出荷数total2403220951'!B:F,5,0) -> 66 | J17: =VLOOKUP(C17,'出荷数2307～2406total241008110618'!B:F,5,0) -> 189 | K17: =VLOOKUP(C17,'出荷数2407-2506total250730101950'!B:F,5,0) -> 97 | L17: =VLOOKUP(C:C,total251219111800!B:F,5,0) -> 77 | N17: =L17 -> 77 | O17: 2106 | P17: 0 | Q17: 0 | R17: 0 | S17: 0 | T17: 0 | U17: 2106 | V17: 2029 | W17: 0.036562203
A18: 14 | B18: 伊賀 | C18: ASN-4302 | D18: マグネット付ＬＥＤ信号灯 | F18: 149 | G18: 62 | H18: 132 | I18: =VLOOKUP(C18,'202310-202403出荷数total2403220951'!B:F,5,0) -> 245 | J18: =VLOOKUP(C18,'出荷数2307～2406total241008110618'!B:F,5,0) -> 322 | K18: =VLOOKUP(C18,'出荷数2407-2506total250730101950'!B:F,5,0) -> 206 | L18: =VLOOKUP(C:C,total251219111800!B:F,5,0) -> 17 | N18: =L18 -> 17 | O18: 2258 | P18: 0 | Q18: 0 | R18: 0 | S18: 0 | T18: 0 | U18: 2258 | V18: 2241 | W18: 0.0075287865 | X18: 売り切り廃盤予定
A19: 15 | B19: 伊賀 | C19: AIC-01IV | D19: ｷｽﾞつきにくいｲｽ脚ｶﾊﾞｰ | E19: IV | F19: 228 | G19: 270 | H19: 231 | I19: =VLOOKUP(C19,'202310-202403出荷数total2403220951'!B:F,5,0) -> 121 | J19: =VLOOKUP(C19,'出荷数2307～2406total241008110618'!B:F,5,0) -> 177 | K19: =VLOOKUP(C19,'出荷数2407-2506total250730101950'!B:F,5,0) -> 110 | L19: =VLOOKUP(C:C,total251219111800!B:F,5,0) -> 53 | N19: =L19 -> 53 | O19: 8059 | P19: 0 | Q19: 0 | R19: 0 | S19: 0 | T19: 0 | U19: 8059 | V19: 8006 | W19: 0.0065764983
A20: 16 | B20: 伊賀 | C20: ANS-603 | D20: お経の流れるスピーカーⅡ | G20: 128 | H20: 470 | I20: =VLOOKUP(C20,'202310-202403出荷数total2403220951'!B:F,5,0) -> 149 | J20: =VLOOKUP(C20,'出荷数2307～2406total241008110618'!B:F,5,0) -> 418 | K20: =VLOOKUP(C20,'出荷数2407-2506total250730101950'!B:F,5,0) -> 818 | L20: =VLOOKUP(C:C,total251219111800!B:F,5,0) -> 491 | N20: =L20 -> 491 | O20: 598 | P20: 130 | Q20: 0 | R20: 0 | S20: 130 | T20: 0 | U20: 468 | V20: -23 | W20: 0.67445055 | X20: トップ確保3月末まで確保
A21: 17 | B21: 伊賀 | C21: APY-105 | D21: 迷惑電話お断りピンポン | F21: 543 | G21: 321 | H21: 270 | I21: =VLOOKUP(C21,'202310-202403出荷数total2403220951'!B:F,5,0) -> 73 | J21: =VLOOKUP(C21,'出荷数2307～2406total241008110618'!B:F,5,0) -> 181 | K21: =VLOOKUP(C21,'出荷数2407-2506total250730101950'!B:F,5,0) -> 277 | L21: =VLOOKUP(C:C,total251219111800!B:F,5,0) -> 141 | N21: =L21 -> 141 | O21: 3311 | P21: 370 | Q21: 0 | R21: 0 | S21: 370 | T21: 0 | U21: 2941 | V21: 2800 | W21: 0.038304808
A22: 18 | B22: 伊賀 | C22: APL-3207S | D22: LEDのインテリア常備灯 | F22: 904 | G22: 638 | H22: 81 | I22: =VLOOKUP(C22,'202310-202403出荷数total2403220951'!B:F,5,0) -> 2 | J22: =VLOOKUP(C22,'出荷数2307～2406total241008110618'!B:F,5,0) -> 904 | K22: =VLOOKUP(C22,'出荷数2407-2506total250730101950'!B:F,5,0) -> 25 | L22: =VLOOKUP(C:C,total251219111800!B:F,5,0) -> 2 | N22: =L22 -> 2 | O22: 6860 | P22: 0 | Q22: 0 | R22: 0 | S22: 0 | T22: 0 | U22: 6860 | V22: 6858 | W22: 0.00029154519
A23: 19 | B23: 伊賀 | C23: ALA-4308BK-D | D23: ひっぱり点灯ライト 電球色ＬＥＤ | F23: 1137 | G23: 270 | H23: 272 | I23: =VLOOKUP(C23,'202310-202403出荷数total2403220951'!B:F,5,0) -> 153 | J23: =VLOOKUP(C23,'出荷数2307～2406total241008110618'!B:F,5,0) -> 657 | K23: =VLOOKUP(C23,'出荷数2407-2506total250730101950'!B:F,5,0) -> 101 | L23: =VLOOKUP(C:C,total251219111800!B:F,5,0) -> 88 | N23: =L23 -> 88 | O23: 1782 | P23: 0 | Q23: 0 | R23: 0 | S23: 0 | T23: 0 | U23: 1782 | V23: 1694 | W23: 0.049382716
A24: 20 | B24: 伊賀 | C24: ACA-101 | D24: ＬＥＤ帽子ライト | F24: 787 | G24: 450 | H24: 417 | I24: =VLOOKUP(C24,'202310-202403出荷数total2403220951'!B:F,5,0) -> 450 | J24: =VLOOKUP(C24,'出荷数2307～2406total241008110618'!B:F,5,0) -> 550 | K24: =VLOOKUP(C24,'出荷数2407-2506total250730101950'!B:F,5,0) -> 160 | L24: =VLOOKUP(C:C,total251219111800!B:F,5,0) -> 89 | N24: =L24 -> 89 | O24: 3704 | P24: 0 | Q24: 0 | R24: 0 | S24: 0 | T24: 0 | U24: 3704 | V24: 3615 | W24: 0.024028078
A25: 21 | B25: 伊賀 | C25: ASL-3308NE | D25: ウォールセンサーライト 箱 | E25: ねこ | F25: 13 | G25: 4 | H25: 8 | I25: =VLOOKUP(C25,'202310-202403出荷数total2403220951'!B:F,5,0) -> 1 | J25: =VLOOKUP(C25,'出荷数2307～2406total241008110618'!B:F,5,0) -> 4 | K25: =VLOOKUP(C25,'出荷数2407-2506total250730101950'!B:F,5,0) -> 6 | L25: =VLOOKUP(C:C,total251219111800!B:F,5,0) -> #N/A | N25: 0 | O25: 24 | P25: 0 | Q25: 0 | R25: 0 | S25: 0 | T25: 0 | U25: 24 | V25: 24 | W25: 0
A26: 22 | B26: 伊賀 | C26: AKD-20 | D26: アニマルシリコンバンド | F26: 1809 | G26: 790 | H26: 1042 | I26: =VLOOKUP(C26,'202310-202403出荷数total2403220951'!B:F,5,0) -> 164 | J26: =VLOOKUP(C26,'出荷数2307～2406total241008110618'!B:F,5,0) -> 312 | K26: =VLOOKUP(C26,'出荷数2407-2506total250730101950'!B:F,5,0) -> 454 | L26: =VLOOKUP(C:C,total251219111800!B:F,5,0) -> 168 | N26: =L26 -> 168 | O26: 5694 | P26: 300 | Q26: 0 | R26: 0 | S26: 300 | T26: 0 | U26: 5394 | V26: 5226 | W26: 0.028028028
A27: 23 | B27: 伊賀 | C27: ARA-4301 | D27: スマートフォンが使えるラジオライト | F27: 549 | G27: 303 | H27: 236 | I27: =VLOOKUP(C27,'202310-202403出荷数total2403220951'!B:F,5,0) -> 241 | J27: =VLOOKUP(C27,'出荷数2307～2406total241008110618'!B:F,5,0) -> 358 | K27: =VLOOKUP(C27,'出荷数2407-2506total250730101950'!B:F,5,0) -> 392 | L27: =VLOOKUP(C:C,total251219111800!B:F,5,0) -> 29 | N27: =L27 -> 29 | O27: 1917 | P27: 0 | Q27: 0 | R27: 0 | S27: 0 | T27: 0 | U27: 1917 | V27: 1888 | W27: 0.015127804
A28: 24 | B28: 伊賀 | C28: ASK-11BOR | D28: 巻きつく安全反射バンド(OR) | E28: オレンジ | F28: 1160 | G28: 148 | H28: 651 | I28: =VLOOKUP(C28,'202310-202403出荷数total2403220951'!B:F,5,0) -> 60 | J28: =VLOOKUP(C28,'出荷数2307～2406total241008110618'!B:F,5,0) -> 125 | K28: =VLOOKUP(C28,'出荷数2407-2506total250730101950'!B:F,5,0) -> 265 | L28: =VLOOKUP(C:C,total251219111800!B:F,5,0) -> 38 | M28: 500 | N28: 500 | O28: 2309 | P28: 0 | Q28: 0 | R28: 0 | S28: 0 | T28: 0 | U28: 2309 | V28: 1809 | W28: 0.21654396
A29: 25 | B29: 伊賀 | C29: ASK-10YE | D29: 光るホイール反射シール | E29: イエロー | F29: 935 | G29: 77 | H29: 731 | I29: =VLOOKUP(C29,'202310-202403出荷数total2403220951'!B:F,5,0) -> 163 | J29: =VLOOKUP(C29,'出荷数2307～2406total241008110618'!B:F,5,0) -> 235 | K29: =VLOOKUP(C29,'出荷数2407-2506total250730101950'!B:F,5,0) -> 20 | L29: =VLOOKUP(C:C,total251219111800!B:F,5,0) -> 2 | N29: =L29 -> 2 | O29: 5 | P29: 0 | Q29: 0 | R29: 0 | S29: 0 | T29: 0 | U29: 5 | V29: 3 | W29: 0.4
A30: 26 | B30: 伊賀 | C30: ARO-530GD | D30: 自動消灯安心のろうそく | E30: GD | F30: 224 | G30: 198 | H30: 230 | I30: =VLOOKUP(C30,'202310-202403出荷数total2403220951'!B:F,5,0) -> 91 | J30: =VLOOKUP(C30,'出荷数2307～2406total241008110618'!B:F,5,0) -> 168 | K30: =VLOOKUP(C30,'出荷数2407-2506total250730101950'!B:F,5,0) -> 52 | L30: =VLOOKUP(C:C,total251219111800!B:F,5,0) -> 28 | N30: =L30 -> 28 | O30: 920 | P30: 0 | Q30: 0 | R30: 0 | S30: 0 | T30: 0 | U30: 920 | V30: 892 | W30: 0.030434783
A31: 27 | B31: 伊賀 | C31: ALA-4308MO-W | D31: ひっぱり点灯ライト 木目 | E31: 木目 | F31: 714 | G31: 368 | H31: 496 | I31: =VLOOKUP(C31,'202310-202403出荷数total2403220951'!B:F,5,0) -> 150 | J31: =VLOOKUP(C31,'出荷数2307～2406total241008110618'!B:F,5,0) -> 247 | K31: =VLOOKUP(C31,'出荷数2407-2506total250730101950'!B:F,5,0) -> 43 | L31: =VLOOKUP(C:C,total251219111800!B:F,5,0) -> 29 | N31: =L31 -> 29 | O31: 1947 | P31: 0 | Q31: 0 | R31: 0 | S31: 0 | T31: 0 | U31: 1947 | V31: 1918 | W31: 0.01489471
A32: 28 | B32: 伊賀 | C32: AIC-06IV | D32: ｽﾞﾚにくいｲｽ脚ｶﾊﾞｰ 2脚用 | E32: IV | F32: 1116 | G32: 928 | H32: 1098 | I32: =VLOOKUP(C32,'202310-202403出荷数total2403220951'!B:F,5,0) -> 427 | J32: =VLOOKUP(C32,'出荷数2307～2406total241008110618'!B:F,5,0) -> 1008 | K32: =VLOOKUP(C32,'出荷数2407-2506total250730101950'!B:F,5,0) -> 854 | L32: =VLOOKUP(C:C,total251219111800!B:F,5,0) -> 345 | N32: =L32 -> 345 | O32: 3044 | P32: 0 | Q32: 0 | R32: 0 | S32: 0 | T32: 0 | U32: 3044 | V32: 2699 | W32: 0.11333771 | X32: 88％発注点よりﾏｲﾅｽ 345→41
A33: 29 | B33: 伊賀 | C33: ANS-701AD | D33: ＡＣアダプター701用 | F33: 120 | G33: 98 | H33: 141 | I33: =VLOOKUP(C33,'202310-202403出荷数total2403220951'!B:F,5,0) -> 41 | J33: =VLOOKUP(C33,'出荷数2307～2406total241008110618'!B:F,5,0) -> 89 | K33: =VLOOKUP(C33,'出荷数2407-2506total250730101950'!B:F,5,0) -> 92 | L33: =VLOOKUP(C:C,total251219111800!B:F,5,0) -> 49 | N33: =L33 -> 49 | O33: 317 | P33: 0 | Q33: 0 | R33: 0 | S33: 0 | T33: 0 | U33: 317 | V33: 268 | W33: 0.15457413
A34: 30 | B34: 伊賀 | C34: ANS-702 | D34: 大きな手もとスピーカー | F34: 1030 | G34: 390 | H34: 221 | I34: =VLOOKUP(C34,'202310-202403出荷数total2403220951'!B:F,5,0) -> 53 | J34: =VLOOKUP(C34,'出荷数2307～2406total241008110618'!B:F,5,0) -> 103 | K34: =VLOOKUP(C34,'出荷数2407-2506total250730101950'!B:F,5,0) -> 224 | L34: =VLOOKUP(C:C,total251219111800!B:F,5,0) -> 45 | N34: =L34 -> 45 | O34: 2079 | P34: 0 | Q34: 0 | R34: 0 | S34: 0 | T34: 0 | U34: 2079 | V34: 2034 | W34: 0.021645022
A35: 31 | B35: 伊賀 | C35: AKN-15 | D35: ハローキティ コンセントカバー | F35: 1322 | G35: 1075 | H35: 946 | I35: =VLOOKUP(C35,'202310-202403出荷数total2403220951'!B:F,5,0) -> 348 | J35: =VLOOKUP(C35,'出荷数2307～2406total241008110618'!B:F,5,0) -> 766 | K35: =VLOOKUP(C35,'出荷数2407-2506total250730101950'!B:F,5,0) -> 1074 | L35: =VLOOKUP(C:C,total251219111800!B:F,5,0) -> 327 | N35: =L35 -> 327 | O35: 3568 | P35: 0 | Q35: 0 | R35: 0 | S35: 0 | T35: 0 | U35: 3568 | V35: 3241 | W35: 0.091647982
A36: 32 | B36: 伊賀 | C36: ACA-3101 | D36: ＬＥＤアルミヘッドランプ | F36: 1781 | G36: 1472 | H36: 1360 | I36: =VLOOKUP(C36,'202310-202403出荷数total2403220951'!B:F,5,0) -> 3651 | J36: =VLOOKUP(C36,'出荷数2307～2406total241008110618'!B:F,5,0) -> 4452 | K36: =VLOOKUP(C36,'出荷数2407-2506total250730101950'!B:F,5,0) -> 4054 | L36: =VLOOKUP(C:C,total251219111800!B:F,5,0) -> 524 | N36: =L36 -> 524 | O36: 12994 | P36: 0 | Q36: 100 | R36: 0 | S36: 0 | T36: 0 | U36: 13094 | V36: 12570 | W36: 0.040326304
A37: 33 | B37: 伊賀 | C37: ASK-06SI | D37: はめるだけ光る 足腕バンド | E37: シルバー | F37: 1210 | G37: 214 | H37: 13 | I37: =VLOOKUP(C37,'202310-202403出荷数total2403220951'!B:F,5,0) -> 75 | J37: =VLOOKUP(C37,'出荷数2307～2406total241008110618'!B:F,5,0) -> 79 | K37: =VLOOKUP(C37,'出荷数2407-2506total250730101950'!B:F,5,0) -> 1 | L37: =VLOOKUP(C:C,total251219111800!B:F,5,0) -> 3 | N37: =L37 -> 3 | O37: 875 | P37: 0 | Q37: 0 | R37: 0 | S37: 0 | T37: 0 | U37: 875 | V37: 872 | W37: 0.0034285714
A38: 34 | B38: 伊賀 | C38: ASL-3308CNE | D38: ウォールセンサーライト ブリスター | E38: ねこ | F38: 271 | G38: 200 | H38: 124 | I38: =VLOOKUP(C38,'202310-202403出荷数total2403220951'!B:F,5,0) -> 63 | J38: =VLOOKUP(C38,'出荷数2307～2406total241008110618'!B:F,5,0) -> 93 | K38: =VLOOKUP(C38,'出荷数2407-2506total250730101950'!B:F,5,0) -> 14 | L38: =VLOOKUP(C:C,total251219111800!B:F,5,0) -> 140 | N38: =L38 -> 140 | O38: 797 | P38: 0 | Q38: 0 | R38: 0 | S38: 0 | T38: 0 | U38: 797 | V38: 657 | W38: 0.17565872
A39: 35 | B39: 伊賀 | C39: ASL-33082 | D39: ウォールセンサーライト（ショップチャンネル専用） | G39: 9 | H39: 1109 | I39: =VLOOKUP(C39,'202310-202403出荷数total2403220951'!B:F,5,0) -> #N/A | J39: =VLOOKUP(C39,'出荷数2307～2406total241008110618'!B:F,5,0) -> #N/A | K39: =VLOOKUP(C39,'出荷数2407-2506total250730101950'!B:F,5,0) -> #N/A | L39: =VLOOKUP(C:C,total251219111800!B:F,5,0) -> #N/A | M39: 470 | N39: 470 | O39: 106 | P39: 0 | Q39: 0 | R39: 0 | S39: 0 | T39: 0 | U39: 106 | V39: -364 | W39: 4.4339623
A40: 36 | B40: 伊賀 | C40: ADR-3401 | D40: 電動角質リムーバー | F40: 19 | G40: 1283 | H40: 7 | I40: =VLOOKUP(C40,'202310-202403出荷数total2403220951'!B:F,5,0) -> 223 | J40: =VLOOKUP(C40,'出荷数2307～2406total241008110618'!B:F,5,0) -> 598 | K40: =VLOOKUP(C40,'出荷数2407-2506total250730101950'!B:F,5,0) -> 73 | L40: =VLOOKUP(C:C,total251219111800!B:F,5,0) -> 5 | N40: =L40 -> 5 | O40: 4160 | P40: 0 | Q40: 0 | R40: 0 | S40: 0 | T40: 0 | U40: 4160 | V40: 4155 | W40: 0.0012019231
A41: 37 | B41: 伊賀 | C41: ASL-3309 | D41: センサーライト付防犯ダミーカメラ | F41: 825 | G41: 660 | H41: 1314 | I41: =VLOOKUP(C41,'202310-202403出荷数total2403220951'!B:F,5,0) -> 262 | J41: =VLOOKUP(C41,'出荷数2307～2406total241008110618'!B:F,5,0) -> 723 | K41: =VLOOKUP(C41,'出荷数2407-2506total250730101950'!B:F,5,0) -> 1443 | L41: =VLOOKUP(C:C,total251219111800!B:F,5,0) -> 305 | N41: =L41 -> 305 | O41: 3054 | P41: 190 | Q41: 0 | R41: 0 | S41: 300 | T41: -110 | U41: 2754 | V41: 2449 | W41: 0.094019729
A42: 38 | B42: 伊賀 | C42: ADR-3401KR | D42: 電動角質リムーバー交換用ローラー（2PCS) | F42: 33 | G42: 994 | H42: 20 | I42: =VLOOKUP(C42,'202310-202403出荷数total2403220951'!B:F,5,0) -> 14 | J42: =VLOOKUP(C42,'出荷数2307～2406total241008110618'!B:F,5,0) -> 26 | K42: =VLOOKUP(C42,'出荷数2407-2506total250730101950'!B:F,5,0) -> 8 | L42: =VLOOKUP(C:C,total251219111800!B:F,5,0) -> 4 | N42: =L42 -> 4 | O42: 4564 | P42: 0 | Q42: 0 | R42: 0 | S42: 0 | T42: 0 | U42: 4564 | V42: 4560 | W42: 0.00087642419
A43: 39 | B43: 伊賀 | C43: KCA-003 | D43: キューベルク 充電式ヘッドライト340 | F43: 15 | G43: 257 | H43: 96 | I43: =VLOOKUP(C43,'202310-202403出荷数total2403220951'!B:F,5,0) -> 18 | J43: =VLOOKUP(C43,'出荷数2307～2406total241008110618'!B:F,5,0) -> 45 | K43: =VLOOKUP(C43,'出荷数2407-2506total250730101950'!B:F,5,0) -> 101 | L43: =VLOOKUP(C:C,total251219111800!B:F,5,0) -> 21 | N43: =L43 -> 21 | O43: 792 | P43: 0 | Q43: 0 | R43: 0 | S43: 0 | T43: 0 | U43: 792 | V43: 771 | W43: 0.026515152
B44: 伊賀 | C44: KCA-004H | D44: ロータリー式ヘッドライト500 | L44: =VLOOKUP(C:C,total251219111800!B:F,5,0) -> 3 | N44: =L44 -> 3 | O44: 493 | P44: 0 | Q44: 1000 | R44: 0 | S44: 0 | T44: 0 | U44: 1493 | V44: 1490 | W44: 0.0060851927
A45: 40 | B45: 伊賀 | C45: ABO-180 | D45: エアーマット1800 | F45: 940 | G45: 457 | H45: 1013 | I45: =VLOOKUP(C45,'202310-202403出荷数total2403220951'!B:F,5,0) -> 669 | J45: =VLOOKUP(C45,'出荷数2307～2406total241008110618'!B:F,5,0) -> 4147 | K45: =VLOOKUP(C45,'出荷数2407-2506total250730101950'!B:F,5,0) -> 4439 | L45: =VLOOKUP(C:C,total251219111800!B:F,5,0) -> 49 | N45: =L45 -> 49 | O45: 307 | P45: 0 | Q45: 0 | R45: 0 | S45: 0 | T45: 0 | U45: 307 | V45: 258 | W45: 0.15960912
A46: 41 | B46: 伊賀 | C46: ABO-120 | D46: エアーマット1200 | F46: 149 | G46: 373 | H46: 66 | I46: =VLOOKUP(C46,'202310-202403出荷数total2403220951'!B:F,5,0) -> 150 | J46: =VLOOKUP(C46,'出荷数2307～2406total241008110618'!B:F,5,0) -> 203 | K46: =VLOOKUP(C46,'出荷数2407-2506total250730101950'!B:F,5,0) -> 212 | L46: =VLOOKUP(C:C,total251219111800!B:F,5,0) -> 39 | N46: =L46 -> 39 | O46: 958 | P46: 0 | Q46: 0 | R46: 0 | S46: 0 | T46: 0 | U46: 958 | V46: 919 | W46: 0.040709812
A47: 42 | B47: 伊賀 | C47: AIC-01BR | D47: ｷｽﾞつきにくいｲｽ脚ｶﾊﾞｰ | E47: BR | F47: 2264 | G47: 1923 | H47: 1776 | I47: =VLOOKUP(C47,'202310-202403出荷数total2403220951'!B:F,5,0) -> 535 | J47: =VLOOKUP(C47,'出荷数2307～2406total241008110618'!B:F,5,0) -> 2161 | K47: =VLOOKUP(C47,'出荷数2407-2506total250730101950'!B:F,5,0) -> 933 | L47: =VLOOKUP(C:C,total251219111800!B:F,5,0) -> 398 | N47: =L47 -> 398 | O47: 2658 | P47: 0 | Q47: 0 | R47: 0 | S47: 0 | T47: 0 | U47: 2658 | V47: 2260 | W47: 0.14973664
A48: 43 | B48: 伊賀 | C48: AHL-1207 | D48: 単1形LED防雨ライト | F48: 3482 | G48: 1186 | H48: 1004 | I48: =VLOOKUP(C48,'202310-202403出荷数total2403220951'!B:F,5,0) -> 594 | J48: =VLOOKUP(C48,'出荷数2307～2406total241008110618'!B:F,5,0) -> 1198 | K48: =VLOOKUP(C48,'出荷数2407-2506total250730101950'!B:F,5,0) -> 1234 | L48: =VLOOKUP(C:C,total251219111800!B:F,5,0) -> 693 | N48: =L48 -> 693 | O48: 597 | P48: 0 | Q48: 0 | R48: 0 | S48: 0 | T48: 0 | U48: 597 | V48: -96 | W48: 1.160804
A49: 44 | B49: 伊賀 | C49: ABO-11 | D49: 防炎非常持出袋 | F49: 5224 | G49: 1145 | H49: 1174 | I49: =VLOOKUP(C49,'202310-202403出荷数total2403220951'!B:F,5,0) -> 435 | J49: =VLOOKUP(C49,'出荷数2307～2406total241008110618'!B:F,5,0) -> 653 | K49: =VLOOKUP(C49,'出荷数2407-2506total250730101950'!B:F,5,0) -> 1213 | L49: =VLOOKUP(C:C,total251219111800!B:F,5,0) -> 373 | N49: =L49 -> 373 | O49: 3846 | P49: 0 | Q49: 0 | R49: 0 | S49: 0 | T49: 0 | U49: 3846 | V49: 3473 | W49: 0.096983879
A50: 45 | B50: 伊賀 | C50: ANS-302BK | D50: テレビの音も聞こえる 手もとスピーカーⅡ | G50: 537 | H50: 3033 | I50: =VLOOKUP(C50,'202310-202403出荷数total2403220951'!B:F,5,0) -> 1920 | J50: =VLOOKUP(C50,'出荷数2307～2406total241008110618'!B:F,5,0) -> 4184 | K50: =VLOOKUP(C50,'出荷数2407-2506total250730101950'!B:F,5,0) -> 3497 | L50: =VLOOKUP(C:C,total251219111800!B:F,5,0) -> 1086 | M50: 750 | N50: =L50 -> 1086 | O50: 4655 | P50: 840 | Q50: 0 | R50: 0 | S50: 840 | T50: 0 | U50: 3815 | V50: 2729 | W50: 0.19763421
A51: 46 | B51: 伊賀 | C51: APL-3207SMO | D51: LEDのインテリア常備灯(化粧箱) | E51: 木目 | F51: 1023 | G51: 517 | H51: 437 | I51: =VLOOKUP(C51,'202310-202403出荷数total2403220951'!B:F,5,0) -> 346 | J51: =VLOOKUP(C51,'出荷数2307～2406total241008110618'!B:F,5,0) -> 396 | K51: =VLOOKUP(C51,'出荷数2407-2506total250730101950'!B:F,5,0) -> 187 | L51: =VLOOKUP(C:C,total251219111800!B:F,5,0) -> 6 | N51: =L51 -> 6 | O51: 1255 | P51: 600 | Q51: 0 | R51: 0 | S51: 600 | T51: 0 | U51: 655 | V51: 649 | W51: 0.0032345013
A52: 47 | B52: 伊賀 | C52: AST-3304 | D52: LEDスタンドライト | F52: 843 | G52: 647 | H52: 2107 | I52: =VLOOKUP(C52,'202310-202403出荷数total2403220951'!B:F,5,0) -> #N/A | J52: =VLOOKUP(C52,'出荷数2307～2406total241008110618'!B:F,5,0) -> #N/A | K52: =VLOOKUP(C52,'出荷数2407-2506total250730101950'!B:F,5,0) -> #N/A | L52: =VLOOKUP(C:C,total251219111800!B:F,5,0) -> #N/A | M52: 890 | N52: 890 | O52: 0 | P52: 0 | Q52: 0 | R52: 0 | S52: 0 | T52: 0 | U52: 0 | V52: -890 | W52: #DIV/0!
A53: 48 | B53: 伊賀 | C53: ASL-3305 | D53: 足もと安心防雨センサーライト | F53: 1465 | G53: 1744 | H53: 888 | I53: =VLOOKUP(C53,'202310-202403出荷数total2403220951'!B:F,5,0) -> 559 | J53: =VLOOKUP(C53,'出荷数2307～2406total241008110618'!B:F,5,0) -> 1133 | K53: =VLOOKUP(C53,'出荷数2407-2506total250730101950'!B:F,5,0) -> 829 | L53: =VLOOKUP(C:C,total251219111800!B:F,5,0) -> 200 | N53: =L53 -> 200 | O53: 3362 | P53: 0 | Q53: 0 | R53: 0 | S53: 0 | T53: 0 | U53: 3362 | V53: 3162 | W53: 0.0594884
A54: 49 | B54: 伊賀 | C54: AHA-43ENAUTO | D54: 自動点灯ｻｲｸﾙﾗｲﾄ(ﾊﾝﾄﾞﾙﾀﾞｲﾅﾓ取付) | F54: 1087 | G54: 665 | H54: 2030 | I54: =VLOOKUP(C54,'202310-202403出荷数total2403220951'!B:F,5,0) -> #N/A | J54: =VLOOKUP(C54,'出荷数2307～2406total241008110618'!B:F,5,0) -> #N/A | K54: =VLOOKUP(C54,'出荷数2407-2506total250730101950'!B:F,5,0) -> #N/A | L54: =VLOOKUP(C:C,total251219111800!B:F,5,0) -> #N/A | M54: 850 | N54: 850 | O54: 2 | P54: 0 | Q54: 0 | R54: 0 | S54: 0 | T54: 0 | U54: 2 | V54: -848 | W54: 425
A55: 50 | B55: 伊賀 | C55: AIC-04IV | D55: ｽﾞﾚにくいｲｽ脚ｶﾊﾞｰ 4脚用 | E55: IV | F55: 2129 | G55: 2065 | H55: 2439 | I55: =VLOOKUP(C55,'202310-202403出荷数total2403220951'!B:F,5,0) -> 805 | J55: =VLOOKUP(C55,'出荷数2307～2406total241008110618'!B:F,5,0) -> 1939 | K55: =VLOOKUP(C55,'出荷数2407-2506total250730101950'!B:F,5,0) -> 1171 | L55: =VLOOKUP(C:C,total251219111800!B:F,5,0) -> 566 | N55: =L55 -> 566 | O55: 830 | P55: 0 | Q55: 0 | R55: 0 | S55: 0 | T55: 0 | U55: 830 | V55: 264 | W55: 0.68192771 | X55: 48％発注点よりﾏｲﾅｽ 566→295
A56: 51 | B56: 伊賀 | C56: ABO-13M | D56: ぬげにくい安全スリッパM | F56: 1540 | G56: 597 | H56: 361 | I56: =VLOOKUP(C56,'202310-202403出荷数total2403220951'!B:F,5,0) -> 533 | J56: =VLOOKUP(C56,'出荷数2307～2406total241008110618'!B:F,5,0) -> 858 | K56: =VLOOKUP(C56,'出荷数2407-2506total250730101950'!B:F,5,0) -> 574 | L56: =VLOOKUP(C:C,total251219111800!B:F,5,0) -> #N/A | N56: =L56 -> #N/A | O56: 0 | P56: 0 | Q56: 0 | R56: 0 | S56: 0 | T56: 0 | U56: 0 | V56: #N/A | W56: #N/A
A57: 52 | B57: 伊賀 | C57: ABO-2907 | D57: 水タンクにもなる水のう袋 7枚入り | G57: 2665 | H57: 2710 | I57: =VLOOKUP(C57,'202310-202403出荷数total2403220951'!B:F,5,0) -> 1020 | J57: =VLOOKUP(C57,'出荷数2307～2406total241008110618'!B:F,5,0) -> 7751 | K57: =VLOOKUP(C57,'出荷数2407-2506total250730101950'!B:F,5,0) -> 21996 | L57: =VLOOKUP(C:C,total251219111800!B:F,5,0) -> 8163 | M57: 10000 | N57: 10000 | O57: 20447 | P57: 600 | Q57: 0 | R57: 0 | S57: 2110 | T57: -1510 | U57: 18337 | V57: 8337 | W57: 0.4751271
A58: 53 | B58: 伊賀 | C58: ALA-4306 | D58: ＬＥＤポケットランタンⅡ 廃版 | F58: 756 | G58: 52 | H58: 44 | I58: =VLOOKUP(C58,'202310-202403出荷数total2403220951'!B:F,5,0) -> 47 | J58: =VLOOKUP(C58,'出荷数2307～2406total241008110618'!B:F,5,0) -> 67 | K58: =VLOOKUP(C58,'出荷数2407-2506total250730101950'!B:F,5,0) -> 12 | L58: =VLOOKUP(C:C,total251219111800!B:F,5,0) -> 2 | N58: =L58 -> 2 | O58: 37 | P58: 0 | Q58: 0 | R58: 0 | S58: 0 | T58: 0 | U58: 37 | V58: 35 | W58: 0.054054054
A59: 54 | B59: 伊賀 | C59: ADC-311WH | D59: 単３が３個で単１電池アダプター | F59: 5239 | G59: 4870 | H59: 3762 | I59: =VLOOKUP(C59,'202310-202403出荷数total2403220951'!B:F,5,0) -> 1545 | J59: =VLOOKUP(C59,'出荷数2307～2406total241008110618'!B:F,5,0) -> 2638 | K59: =VLOOKUP(C59,'出荷数2407-2506total250730101950'!B:F,5,0) -> 3321 | L59: =VLOOKUP(C:C,total251219111800!B:F,5,0) -> 1045 | N59: =L59 -> 1045 | O59: 4151 | P59: 0 | Q59: 0 | R59: 0 | S59: 0 | T59: 0 | U59: 4151 | V59: 3106 | W59: 0.25174657
A60: 55 | B60: 伊賀 | C60: AKO-10 | D60: こたつ専用収納ポケットS | E60: BR | F60: 1332 | G60: 1490 | H60: 2200 | I60: =VLOOKUP(C60,'202310-202403出荷数total2403220951'!B:F,5,0) -> 339 | J60: =VLOOKUP(C60,'出荷数2307～2406total241008110618'!B:F,5,0) -> 1289 | K60: =VLOOKUP(C60,'出荷数2407-2506total250730101950'!B:F,5,0) -> 1155 | L60: =VLOOKUP(C:C,total251219111800!B:F,5,0) -> 362 | N60: =L60 -> 362 | O60: 3796 | P60: 0 | Q60: 0 | R60: 0 | S60: 0 | T60: 0 | U60: 3796 | V60: 3434 | W60: 0.095363541
A61: 56 | B61: 伊賀 | C61: AHM-108 | D61: 録音できるハンドメガホン | F61: 1177 | G61: 1274 | H61: 1310 | I61: =VLOOKUP(C61,'202310-202403出荷数total2403220951'!B:F,5,0) -> 484 | J61: =VLOOKUP(C61,'出荷数2307～2406total241008110618'!B:F,5,0) -> 984 | K61: =VLOOKUP(C61,'出荷数2407-2506total250730101950'!B:F,5,0) -> 1414 | L61: =VLOOKUP(C:C,total251219111800!B:F,5,0) -> 852 | N61: =L61 -> 852 | O61: 1095 | P61: 100 | Q61: 0 | R61: 0 | S61: 100 | T61: 0 | U61: 995 | V61: 143 | W61: 0.71297071
A62: 57 | B62: 伊賀 | C62: ASK-04 | D62: 光るスポークかざり ビーズ | F62: 2501 | G62: 1137 | H62: 1254 | I62: =VLOOKUP(C62,'202310-202403出荷数total2403220951'!B:F,5,0) -> 1064 | J62: =VLOOKUP(C62,'出荷数2307～2406total241008110618'!B:F,5,0) -> 1296 | K62: =VLOOKUP(C62,'出荷数2407-2506total250730101950'!B:F,5,0) -> 172 | L62: =VLOOKUP(C:C,total251219111800!B:F,5,0) -> 765 | N62: =L62 -> 765 | O62: 2106 | P62: 2000 | Q62: 0 | R62: 0 | S62: 1740 | T62: 260 | U62: 366 | V62: -399 | W62: 0.18631271 | X62: 様子見
A63: 58 | B63: 伊賀 | C63: ASK-10SI | D63: 光るホイール反射シール | E63: シルバー | F63: 600 | G63: 225 | H63: 22 | I63: =VLOOKUP(C63,'202310-202403出荷数total2403220951'!B:F,5,0) -> 1 | J63: =VLOOKUP(C63,'出荷数2307～2406total241008110618'!B:F,5,0) -> 1 | K63: =VLOOKUP(C63,'出荷数2407-2506total250730101950'!B:F,5,0) -> #N/A | L63: =VLOOKUP(C:C,total251219111800!B:F,5,0) -> #N/A | N63: =L63 -> #N/A | O63: 552 | P63: 0 | Q63: 0 | R63: 0 | S63: 0 | T63: 0 | U63: 552 | V63: #N/A | W63: #N/A
A64: 59 | B64: 伊賀 | C64: ASK-13 | D64: 光るホイール反射シール | F64: 600 | G64: 225 | H64: 0 | I64: =VLOOKUP(C64,'202310-202403出荷数total2403220951'!B:F,5,0) -> 10 | J64: =VLOOKUP(C64,'出荷数2307～2406total241008110618'!B:F,5,0) -> 11 | K64: =VLOOKUP(C64,'出荷数2407-2506total250730101950'!B:F,5,0) -> 8 | L64: =VLOOKUP(C:C,total251219111800!B:F,5,0) -> 13 | N64: =L64 -> 13 | O64: 1963 | P64: 0 | Q64: 0 | R64: 0 | S64: 0 | T64: 0 | U64: 1963 | V64: 1950 | W64: 0.0066225166
A65: 60 | B65: 伊賀 | C65: ASK-06YE | D65: はめるだけ光る 足腕バンド | E65: イエロー | F65: 46 | G65: 271 | H65: 10 | I65: =VLOOKUP(C65,'202310-202403出荷数total2403220951'!B:F,5,0) -> 50 | J65: =VLOOKUP(C65,'出荷数2307～2406total241008110618'!B:F,5,0) -> 53 | K65: =VLOOKUP(C65,'出荷数2407-2506total250730101950'!B:F,5,0) -> 93 | L65: =VLOOKUP(C:C,total251219111800!B:F,5,0) -> 13 | M65: 500 | N65: 500 | O65: 2320 | P65: 0 | Q65: 0 | R65: 0 | S65: 0 | T65: 0 | U65: 2320 | V65: 1820 | W65: 0.21551724
A66: 61 | B66: 伊賀 | C66: AHA-4307 | D66: 自動点灯サイクルライトⅡ | F66: 1006 | G66: 417 | H66: 772 | I66: =VLOOKUP(C66,'202310-202403出荷数total2403220951'!B:F,5,0) -> 650 | J66: =VLOOKUP(C66,'出荷数2307～2406total241008110618'!B:F,5,0) -> 1155 | K66: =VLOOKUP(C66,'出荷数2407-2506total250730101950'!B:F,5,0) -> 373 | L66: =VLOOKUP(C:C,total251219111800!B:F,5,0) -> 484 | N66: =L66 -> 484 | O66: 1329 | P66: 0 | Q66: 0 | R66: 0 | S66: 0 | T66: 0 | U66: 1329 | V66: 845 | W66: 0.3641836
A67: 62 | B67: 伊賀 | C67: ALA-4311 | D67: くるっとハンディランタンライト | F67: 856 | G67: 1296 | H67: 948 | I67: =VLOOKUP(C67,'202310-202403出荷数total2403220951'!B:F,5,0) -> 92 | J67: =VLOOKUP(C67,'出荷数2307～2406total241008110618'!B:F,5,0) -> 191 | K67: =VLOOKUP(C67,'出荷数2407-2506total250730101950'!B:F,5,0) -> 1768 | L67: =VLOOKUP(C:C,total251219111800!B:F,5,0) -> 749 | M67: 500 | N67: =L67 -> 749 | O67: 2728 | P67: 0 | Q67: 0 | R67: 0 | S67: 180 | T67: -180 | U67: 2548 | V67: 1799 | W67: 0.27456012
A68: 63 | B68: 伊賀 | C68: AIC-05IV | D68: ｽﾞﾚにくいｲｽ脚ｶﾊﾞｰ 1脚用 | E68: IV | F68: 2715 | G68: 1898 | H68: 1974 | I68: =VLOOKUP(C68,'202310-202403出荷数total2403220951'!B:F,5,0) -> 822 | J68: =VLOOKUP(C68,'出荷数2307～2406total241008110618'!B:F,5,0) -> 1831 | K68: =VLOOKUP(C68,'出荷数2407-2506total250730101950'!B:F,5,0) -> 1431 | L68: =VLOOKUP(C:C,total251219111800!B:F,5,0) -> 874 | N68: =L68 -> 874 | O68: 3973 | P68: 0 | Q68: 0 | R68: 0 | S68: 0 | T68: 0 | U68: 3973 | V68: 3099 | W68: 0.2199849 | X68: 23％発注点よりﾏｲﾅｽ 874→672
A69: 64 | B69: 伊賀 | C69: ABO-19 | D69: 防災用薄型ウォーターバッグ9L | F69: 680 | G69: 2488 | H69: 824 | I69: =VLOOKUP(C69,'202310-202403出荷数total2403220951'!B:F,5,0) -> 454 | J69: =VLOOKUP(C69,'出荷数2307～2406total241008110618'!B:F,5,0) -> 939 | K69: =VLOOKUP(C69,'出荷数2407-2506total250730101950'!B:F,5,0) -> 1427 | L69: =VLOOKUP(C:C,total251219111800!B:F,5,0) -> 203 | N69: =L69 -> 203 | O69: 2681 | P69: 0 | Q69: 0 | R69: 0 | S69: 0 | T69: 0 | U69: 2681 | V69: 2478 | W69: 0.075718016
A70: 65 | B70: 伊賀 | C70: AYC-101PK | D70: 耳すっきりクリーナー | E70: ピンク | F70: 1433 | G70: 1030 | H70: 1015 | I70: =VLOOKUP(C70,'202310-202403出荷数total2403220951'!B:F,5,0) -> 273 | J70: =VLOOKUP(C70,'出荷数2307～2406total241008110618'!B:F,5,0) -> 828 | K70: =VLOOKUP(C70,'出荷数2407-2506total250730101950'!B:F,5,0) -> 776 | L70: =VLOOKUP(C:C,total251219111800!B:F,5,0) -> 430 | N70: =L70 -> 430 | O70: 1871 | P70: 0 | Q70: 0 | R70: 0 | S70: 0 | T70: 0 | U70: 1871 | V70: 1441 | W70: 0.22982362
A71: 66 | B71: 伊賀 | C71: AUV-3301 | D71: 見えにくい汚れの発見ライト | G71: 600 | H71: 106 | I71: =VLOOKUP(C71,'202310-202403出荷数total2403220951'!B:F,5,0) -> 250 | J71: =VLOOKUP(C71,'出荷数2307～2406total241008110618'!B:F,5,0) -> 351 | K71: =VLOOKUP(C71,'出荷数2407-2506total250730101950'!B:F,5,0) -> 157 | L71: =VLOOKUP(C:C,total251219111800!B:F,5,0) -> #N/A | N71: =L71 -> #N/A | O71: 2381 | P71: 0 | Q71: 0 | R71: 0 | S71: 0 | T71: 0 | U71: 2381 | V71: #N/A | W71: #N/A
B72: 伊賀 | C72: AUV-3301C | D72: 365nmUVﾗｲﾄ | H72: 100 | I72: =VLOOKUP(C72,'202310-202403出荷数total2403220951'!B:F,5,0) -> 17 | J72: =VLOOKUP(C72,'出荷数2307～2406total241008110618'!B:F,5,0) -> 35 | K72: =VLOOKUP(C72,'出荷数2407-2506total250730101950'!B:F,5,0) -> 80 | L72: =VLOOKUP(C:C,total251219111800!B:F,5,0) -> 16 | N72: =L72 -> 16 | O72: 303 | P72: 0 | Q72: 0 | R72: 0 | S72: 0 | T72: 0 | U72: 303 | V72: 287 | W72: 0.052805281
A73: 67 | B73: 伊賀 | C73: AHL-1101 | D73: 単３と単１が使ええる防水ライト | F73: 4431 | G73: 2178 | H73: 3224 | I73: =VLOOKUP(C73,'202310-202403出荷数total2403220951'!B:F,5,0) -> 2952 | J73: =VLOOKUP(C73,'出荷数2307～2406total241008110618'!B:F,5,0) -> 5989 | K73: =VLOOKUP(C73,'出荷数2407-2506total250730101950'!B:F,5,0) -> 4689 | L73: =VLOOKUP(C:C,total251219111800!B:F,5,0) -> 1757 | N73: =L73 -> 1757 | O73: 6047 | P73: 200 | Q73: 0 | R73: 0 | S73: 200 | T73: 0 | U73: 5847 | V73: 4090 | W73: 0.281255
A74: 68 | B74: 伊賀 | C74: ABO-03 | D74: 防災用ポリバケツ | F74: 3496 | G74: 2391 | H74: 1985 | I74: =VLOOKUP(C74,'202310-202403出荷数total2403220951'!B:F,5,0) -> 1236 | J74: =VLOOKUP(C74,'出荷数2307～2406total241008110618'!B:F,5,0) -> 2298 | K74: =VLOOKUP(C74,'出荷数2407-2506total250730101950'!B:F,5,0) -> 8616 | L74: =VLOOKUP(C:C,total251219111800!B:F,5,0) -> 1136 | M74: 8000 | N74: 8000 | O74: 14534 | P74: 3200 | Q74: 0 | R74: 0 | S74: 5200 | T74: -2000 | U74: 9334 | V74: 1334 | W74: 0.45111086
A75: 69 | B75: 伊賀 | C75: KCA-002 | D75: キューベルク 充電式ヘッドライト270 | F75: 44 | G75: 866 | H75: 614 | I75: =VLOOKUP(C75,'202310-202403出荷数total2403220951'!B:F,5,0) -> 333 | J75: =VLOOKUP(C75,'出荷数2307～2406total241008110618'!B:F,5,0) -> 1142 | K75: =VLOOKUP(C75,'出荷数2407-2506total250730101950'!B:F,5,0) -> 925 | L75: =VLOOKUP(C:C,total251219111800!B:F,5,0) -> 135 | N75: =L75 -> 135 | O75: 1770 | P75: 0 | Q75: 0 | R75: 0 | S75: 0 | T75: 0 | U75: 1770 | V75: 1635 | W75: 0.076271186
A76: 70 | B76: 伊賀 | C76: AHM-201 | D76: 防雨ハンドメガホン | F76: 410 | G76: 741 | H76: 1112 | I76: =VLOOKUP(C76,'202310-202403出荷数total2403220951'!B:F,5,0) -> 662 | J76: =VLOOKUP(C76,'出荷数2307～2406total241008110618'!B:F,5,0) -> 1332 | K76: =VLOOKUP(C76,'出荷数2407-2506total250730101950'!B:F,5,0) -> 2848 | L76: =VLOOKUP(C:C,total251219111800!B:F,5,0) -> 1014 | M76: 1000 | N76: =L76 -> 1014 | O76: 1650 | P76: 200 | Q76: 3000 | R76: 0 | S76: 200 | T76: 0 | U76: 4450 | V76: 3436 | W76: 0.54810811
A77: 71 | B77: 伊賀 | C77: AAM-200 | D77: 雨ふりセンサーⅡ | F77: 1477 | G77: 1110 | H77: 696 | I77: =VLOOKUP(C77,'202310-202403出荷数total2403220951'!B:F,5,0) -> 116 | J77: =VLOOKUP(C77,'出荷数2307～2406total241008110618'!B:F,5,0) -> 801 | K77: =VLOOKUP(C77,'出荷数2407-2506total250730101950'!B:F,5,0) -> 703 | L77: =VLOOKUP(C:C,total251219111800!B:F,5,0) -> 319 | N77: =L77 -> 319 | O77: 450 | P77: 0 | Q77: 0 | R77: 0 | S77: 0 | T77: 0 | U77: 450 | V77: 131 | W77: 0.70888889 | X77: 在庫減ってから発注。発注ロット2000希望
A78: 72 | B78: 伊賀 | C78: AHA-4306 | D78: 自動点灯前かごクリップライト | F78: 1324 | G78: 1622 | H78: 1792 | I78: =VLOOKUP(C78,'202310-202403出荷数total2403220951'!B:F,5,0) -> 1087 | J78: =VLOOKUP(C78,'出荷数2307～2406total241008110618'!B:F,5,0) -> 1970 | K78: =VLOOKUP(C78,'出荷数2407-2506total250730101950'!B:F,5,0) -> 1824 | L78: =VLOOKUP(C:C,total251219111800!B:F,5,0) -> 900 | N78: =L78 -> 900 | O78: 2841 | P78: 0 | Q78: 0 | R78: 0 | S78: 0 | T78: 0 | U78: 2841 | V78: 1941 | W78: 0.31678986
A79: 73 | B79: 伊賀 | C79: KCA-001 | D79: キューベルク 充電式ヘッドライト220 | F79: 30 | G79: 1288 | H79: 1790 | I79: =VLOOKUP(C79,'202310-202403出荷数total2403220951'!B:F,5,0) -> 845 | J79: =VLOOKUP(C79,'出荷数2307～2406total241008110618'!B:F,5,0) -> 1682 | K79: =VLOOKUP(C79,'出荷数2407-2506total250730101950'!B:F,5,0) -> 1326 | L79: =VLOOKUP(C:C,total251219111800!B:F,5,0) -> 366 | N79: =L79 -> 366 | O79: 1743 | P79: 0 | Q79: 0 | R79: 0 | S79: 0 | T79: 0 | U79: 1743 | V79: 1377 | W79: 0.20998279
A80: 74 | B80: 伊賀 | C80: AOM-01 | D80: かんたんお話メモ | F80: 6851 | G80: 3631 | H80: 3310 | I80: =VLOOKUP(C80,'202310-202403出荷数total2403220951'!B:F,5,0) -> 2276 | J80: =VLOOKUP(C80,'出荷数2307～2406total241008110618'!B:F,5,0) -> 2977 | K80: =VLOOKUP(C80,'出荷数2407-2506total250730101950'!B:F,5,0) -> 1413 | L80: =VLOOKUP(C:C,total251219111800!B:F,5,0) -> 456 | N80: =L80 -> 456 | O80: 2267 | P80: 200 | Q80: 0 | R80: 0 | S80: 200 | T80: 0 | U80: 2067 | V80: 1611 | W80: 0.18483989
A81: 75 | B81: 伊賀 | C81: AKM-3205BL | D81: 首ふり毛だまクリーナー | E81: ブルー | F81: 7367 | G81: 4388 | H81: 521 | I81: =VLOOKUP(C81,'202310-202403出荷数total2403220951'!B:F,5,0) -> 2848 | J81: =VLOOKUP(C81,'出荷数2307～2406total241008110618'!B:F,5,0) -> 3288 | K81: =VLOOKUP(C81,'出荷数2407-2506total250730101950'!B:F,5,0) -> 2304 | L81: =VLOOKUP(C:C,total251219111800!B:F,5,0) -> 744 | N81: =L81 -> 744 | O81: 4345 | P81: 3430 | Q81: 0 | R81: 0 | S81: 3430 | T81: 0 | U81: 915 | V81: 171 | W81: 0.095691318
A82: 76 | B82: 伊賀 | C82: ABO-12 | D82: 防災用ポリタンク 10L | F82: 10633 | G82: 6065 | H82: 2945 | I82: =VLOOKUP(C82,'202310-202403出荷数total2403220951'!B:F,5,0) -> 3324 | J82: =VLOOKUP(C82,'出荷数2307～2406total241008110618'!B:F,5,0) -> 5243 | K82: =VLOOKUP(C82,'出荷数2407-2506total250730101950'!B:F,5,0) -> 13654 | L82: =VLOOKUP(C:C,total251219111800!B:F,5,0) -> 1335 | M82: 4500 | N82: 3000 | O82: 6599 | P82: 3060 | Q82: 0 | R82: 0 | S82: 3160 | T82: -100 | U82: 3439 | V82: 439 | W82: 0.31059116
A83: 77 | B83: 伊賀 | C83: ALA-4310 | D83: ゆれたら点灯ライト(クリアケース) | F83: 270 | G83: 814 | H83: 677 | I83: =VLOOKUP(C83,'202310-202403出荷数total2403220951'!B:F,5,0) -> 269 | J83: =VLOOKUP(C83,'出荷数2307～2406total241008110618'!B:F,5,0) -> 668 | K83: =VLOOKUP(C83,'出荷数2407-2506total250730101950'!B:F,5,0) -> 826 | L83: =VLOOKUP(C:C,total251219111800!B:F,5,0) -> 90 | N83: =L83 -> 90 | O83: 2441 | P83: 0 | Q83: 0 | R83: 0 | S83: 0 | T83: 0 | U83: 2441 | V83: 2351 | W83: 0.036870135
A84: 78 | B84: 伊賀 | C84: ALA-3301 | D84: てるてるランタン | F84: 3306 | G84: 2817 | H84: 1743 | I84: =VLOOKUP(C84,'202310-202403出荷数total2403220951'!B:F,5,0) -> 273 | J84: =VLOOKUP(C84,'出荷数2307～2406total241008110618'!B:F,5,0) -> 477 | K84: =VLOOKUP(C84,'出荷数2407-2506total250730101950'!B:F,5,0) -> 351 | L84: =VLOOKUP(C:C,total251219111800!B:F,5,0) -> 211 | N84: =L84 -> 211 | O84: 7228 | P84: 0 | Q84: 0 | R84: 0 | S84: 0 | T84: 0 | U84: 7228 | V84: 7017 | W84: 0.029192031
A85: 79 | B85: 伊賀 | C85: ARO-02 | D85: 自動消灯安心のろうそくミニ | F85: 1177 | G85: 2128 | H85: 1537 | I85: =VLOOKUP(C85,'202310-202403出荷数total2403220951'!B:F,5,0) -> 834 | J85: =VLOOKUP(C85,'出荷数2307～2406total241008110618'!B:F,5,0) -> 1486 | K85: =VLOOKUP(C85,'出荷数2407-2506total250730101950'!B:F,5,0) -> 1411 | L85: =VLOOKUP(C:C,total251219111800!B:F,5,0) -> 822 | N85: =L85 -> 822 | O85: 2808 | P85: 0 | Q85: 0 | R85: 0 | S85: 0 | T85: 0 | U85: 2808 | V85: 1986 | W85: 0.29273504
A86: 80 | B86: 伊賀 | C86: ACR-01 | D86: スイッチ付きコードリール | F86: 1511 | G86: 1031 | H86: 1052 | I86: =VLOOKUP(C86,'202310-202403出荷数total2403220951'!B:F,5,0) -> 513 | J86: =VLOOKUP(C86,'出荷数2307～2406total241008110618'!B:F,5,0) -> 546 | K86: =VLOOKUP(C86,'出荷数2407-2506total250730101950'!B:F,5,0) -> #N/A | L86: =VLOOKUP(C:C,total251219111800!B:F,5,0) -> #N/A | N86: =L86 -> #N/A | O86: 0 | P86: 0 | Q86: 0 | R86: 0 | S86: 0 | T86: 0 | U86: 0 | V86: #N/A | W86: #N/A
A87: 81 | B87: 伊賀 | C87: AKR-20 | D87: ねこのキーカバー | F87: 3121 | G87: 3233 | H87: 3120 | I87: =VLOOKUP(C87,'202310-202403出荷数total2403220951'!B:F,5,0) -> 1553 | J87: =VLOOKUP(C87,'出荷数2307～2406total241008110618'!B:F,5,0) -> 3072 | K87: =VLOOKUP(C87,'出荷数2407-2506total250730101950'!B:F,5,0) -> 3947 | L87: =VLOOKUP(C:C,total251219111800!B:F,5,0) -> 1574 | N87: =L87 -> 1574 | O87: 4167 | P87: 0 | Q87: 0 | R87: 0 | S87: 0 | T87: 0 | U87: 4167 | V87: 2593 | W87: 0.37772978
A88: 82 | B88: 伊賀 | C88: AYD-102AD | D88: 電話の拡声器 ⅡＡＣアダプター | F88: 1334 | G88: 1879 | H88: 908 | I88: =VLOOKUP(C88,'202310-202403出荷数total2403220951'!B:F,5,0) -> 222 | J88: =VLOOKUP(C88,'出荷数2307～2406total241008110618'!B:F,5,0) -> 732 | K88: =VLOOKUP(C88,'出荷数2407-2506total250730101950'!B:F,5,0) -> 817 | L88: =VLOOKUP(C:C,total251219111800!B:F,5,0) -> 295 | N88: =L88 -> 295 | O88: 254 | P88: 0 | Q88: 0 | R88: 0 | S88: 0 | T88: 0 | U88: 254 | V88: -41 | W88: 1.1614173
A89: 83 | B89: 伊賀 | C89: AKR-11 | D89: シリコンキーカバー | F89: 3215 | G89: 3856 | H89: 4252 | I89: =VLOOKUP(C89,'202310-202403出荷数total2403220951'!B:F,5,0) -> 2413 | J89: =VLOOKUP(C89,'出荷数2307～2406total241008110618'!B:F,5,0) -> 4143 | K89: =VLOOKUP(C89,'出荷数2407-2506total250730101950'!B:F,5,0) -> 6112 | L89: =VLOOKUP(C:C,total251219111800!B:F,5,0) -> 2918 | N89: =L89 -> 2918 | O89: 3833 | P89: 0 | Q89: 0 | R89: 0 | S89: 0 | T89: 0 | U89: 3833 | V89: 915 | W89: 0.76128359
A90: 84 | B90: 伊賀 | C90: AST-3401 | D90: スマホが充電できるスタンドライト | F90: 102 | G90: 340 | H90: 49 | I90: =VLOOKUP(C90,'202310-202403出荷数total2403220951'!B:F,5,0) -> 6 | J90: =VLOOKUP(C90,'出荷数2307～2406total241008110618'!B:F,5,0) -> 434 | K90: =VLOOKUP(C90,'出荷数2407-2506total250730101950'!B:F,5,0) -> #N/A | L90: =VLOOKUP(C:C,total251219111800!B:F,5,0) -> #N/A | N90: =L90 -> #N/A | O90: 0 | P90: 0 | Q90: 0 | R90: 0 | S90: 0 | T90: 0 | U90: 0 | V90: #N/A | W90: #N/A
A91: 85 | B91: 伊賀 | C91: ASL-3310 | D91: マグネット付くるっと回るセンサーライト | F91: 1538 | G91: 2587 | H91: 571 | I91: =VLOOKUP(C91,'202310-202403出荷数total2403220951'!B:F,5,0) -> 874 | J91: =VLOOKUP(C91,'出荷数2307～2406total241008110618'!B:F,5,0) -> 1045 | K91: =VLOOKUP(C91,'出荷数2407-2506total250730101950'!B:F,5,0) -> 429 | L91: =VLOOKUP(C:C,total251219111800!B:F,5,0) -> 22 | M91: 1400 | N91: 1400 | O91: 4407 | P91: 100 | Q91: 0 | R91: 0 | S91: 100 | T91: 0 | U91: 4307 | V91: 2907 | W91: 0.31062791
A92: 87 | B92: 伊賀 | C92: ASL-3303 | D92: ドア用センサーライト | F92: 8125 | G92: 7398 | H92: 4528 | I92: =VLOOKUP(C92,'202310-202403出荷数total2403220951'!B:F,5,0) -> 1614 | J92: =VLOOKUP(C92,'出荷数2307～2406total241008110618'!B:F,5,0) -> 3692 | K92: =VLOOKUP(C92,'出荷数2407-2506total250730101950'!B:F,5,0) -> 3180 | L92: =VLOOKUP(C:C,total251219111800!B:F,5,0) -> 1448 | N92: =L92 -> 1448 | O92: 5191 | P92: 670 | Q92: 40 | R92: 0 | S92: 1200 | T92: -530 | U92: 4031 | V92: 2583 | W92: 0.24705682
A93: 88 | B93: 伊賀 | C93: ASL-33032 | D93: ドア用センサーライト（ｼｮｯﾌﾟﾁｬﾝﾈﾙ） | F93: 0 | G93: 5 | H93: 904 | I93: =VLOOKUP(C93,'202310-202403出荷数total2403220951'!B:F,5,0) -> #N/A | J93: =VLOOKUP(C93,'出荷数2307～2406total241008110618'!B:F,5,0) -> #N/A | K93: =VLOOKUP(C93,'出荷数2407-2506total250730101950'!B:F,5,0) -> #N/A | L93: =VLOOKUP(C:C,total251219111800!B:F,5,0) -> #N/A | M93: 380 | N93: 380 | O93: 781 | P93: 0 | Q93: 0 | R93: 0 | S93: 0 | T93: 0 | U93: 781 | V93: 401 | W93: 0.4865557
A94: 89 | B94: 伊賀 | C94: ASL-3303K | D94: ドア用センサーライト（ケーズ） | F94: 684 | G94: 626 | H94: 772 | I94: =VLOOKUP(C94,'202310-202403出荷数total2403220951'!B:F,5,0) -> 81 | J94: =VLOOKUP(C94,'出荷数2307～2406total241008110618'!B:F,5,0) -> 221 | K94: =VLOOKUP(C94,'出荷数2407-2506total250730101950'!B:F,5,0) -> #N/A | L94: =VLOOKUP(C:C,total251219111800!B:F,5,0) -> #N/A | N94: =L94 -> #N/A | O94: 3 | P94: 0 | Q94: 0 | R94: 0 | S94: 0 | T94: 0 | U94: 3 | V94: #N/A | W94: #N/A
A95: 90 | B95: 伊賀 | C95: AIC-04BE | D95: ｽﾞﾚにくいｲｽ脚ｶﾊﾞｰ 4脚用 | E95: BE | F95: 4518 | G95: 3870 | H95: 3467 | I95: =VLOOKUP(C95,'202310-202403出荷数total2403220951'!B:F,5,0) -> 1429 | J95: =VLOOKUP(C95,'出荷数2307～2406total241008110618'!B:F,5,0) -> 3078 | K95: =VLOOKUP(C95,'出荷数2407-2506total250730101950'!B:F,5,0) -> 3161 | L95: =VLOOKUP(C:C,total251219111800!B:F,5,0) -> 1695 | N95: =L95 -> 1695 | O95: 511 | P95: 0 | Q95: 3000 | R95: 0 | S95: 0 | T95: 0 | U95: 3511 | V95: 1816 | W95: 3.3170254 | X95: 48％発注点よりﾏｲﾅｽ 1695→881
A96: 91 | B96: 伊賀 | C96: AST-3303 | D96: スマホが置けるスタンドライト | F96: 12335 | G96: 8441 | H96: 3599 | I96: =VLOOKUP(C96,'202310-202403出荷数total2403220951'!B:F,5,0) -> 3021 | J96: =VLOOKUP(C96,'出荷数2307～2406total241008110618'!B:F,5,0) -> 4038 | K96: =VLOOKUP(C96,'出荷数2407-2506total250730101950'!B:F,5,0) -> 1769 | L96: =VLOOKUP(C:C,total251219111800!B:F,5,0) -> 560 | N96: =L96 -> 560 | O96: 8988 | P96: 1500 | Q96: 0 | R96: 0 | S96: 1500 | T96: 0 | U96: 7488 | V96: 6928 | W96: 0.053394355
A97: 92 | B97: 伊賀 | C97: AKM-3204PK | D97: 立てて置ける毛だまクリーナー | E97: ピンク | F97: 2663 | G97: 4626 | H97: 4263 | I97: =VLOOKUP(C97,'202310-202403出荷数total2403220951'!B:F,5,0) -> 1415 | J97: =VLOOKUP(C97,'出荷数2307～2406total241008110618'!B:F,5,0) -> 2582 | K97: =VLOOKUP(C97,'出荷数2407-2506total250730101950'!B:F,5,0) -> 2814 | L97: =VLOOKUP(C:C,total251219111800!B:F,5,0) -> 1960 | N97: =L97 -> 1960 | O97: 4339 | P97: 800 | Q97: 0 | R97: 0 | S97: 800 | T97: 0 | U97: 3539 | V97: 1579 | W97: 0.38139716
A98: 93 | B98: 伊賀 | C98: ADR-100 | D98: ドライヤースタンド | F98: 3167 | G98: 3686 | H98: 4490 | I98: =VLOOKUP(C98,'202310-202403出荷数total2403220951'!B:F,5,0) -> 1027 | J98: =VLOOKUP(C98,'出荷数2307～2406total241008110618'!B:F,5,0) -> 2480 | K98: =VLOOKUP(C98,'出荷数2407-2506total250730101950'!B:F,5,0) -> 1578 | L98: =VLOOKUP(C:C,total251219111800!B:F,5,0) -> 247 | N98: =L98 -> 247 | O98: 2780 | P98: 0 | Q98: 0 | R98: 0 | S98: 100 | T98: -100 | U98: 2680 | V98: 2433 | W98: 0.088848921
A99: 94 | B99: 伊賀 | C99: AYC-101BL | D99: 耳すっきりクリーナー | E99: ブルー | F99: 5717 | H99: 3844 | I99: =VLOOKUP(C99,'202310-202403出荷数total2403220951'!B:F,5,0) -> 1058 | J99: =VLOOKUP(C99,'出荷数2307～2406total241008110618'!B:F,5,0) -> 2412 | K99: =VLOOKUP(C99,'出荷数2407-2506total250730101950'!B:F,5,0) -> 2874 | L99: =VLOOKUP(C:C,total251219111800!B:F,5,0) -> 1317 | N99: =L99 -> 1317 | O99: 2162 | P99: 120 | Q99: 0 | R99: 0 | S99: 250 | T99: -130 | U99: 1912 | V99: 595 | W99: 0.57712533
A100: 95 | B100: 伊賀 | C100: AHL-2203 | D100: 単2形LED防雨ライト | F100: 15469 | G100: 8369 | H100: 9994 | I100: =VLOOKUP(C100,'202310-202403出荷数total2403220951'!B:F,5,0) -> 2524 | J100: =VLOOKUP(C100,'出荷数2307～2406total241008110618'!B:F,5,0) -> 7246 | K100: =VLOOKUP(C100,'出荷数2407-2506total250730101950'!B:F,5,0) -> 19015 | L100: =VLOOKUP(C:C,total251219111800!B:F,5,0) -> 3771 | M100: 4500 | N100: 3000 | O100: 7285 | P100: 7270 | Q100: 3000 | R100: 0 | S100: 7270 | T100: 0 | U100: 3015 | V100: 15 | W100: 0.20611474
...

Sheet 80130
B1: 商品センター | C1: 品番 | D1: 商品区分 | E1: カラー | F1: 72期 | G1: 73期 | H1: 74期(1期) | I1: 2023/10/1～2024/3/21（6か月） | J1: 75期(2期) | K1: 76期（３期 ） | L1: 77期（4期 7/1-12/18） | N1: 発注点 5ヶ月分なのでそのまま | O1: 在庫数 ロジザード | Q1: 入荷予定 ロジザード | S1: 確保数 弥生(在庫確保) | T1: 確保数チェック 0じゃなかったらロジザード修正 | U1: 有効数量 フリー在庫の数 | V1: 発注検討フラグ マイナスの場合発注検討 | W1: 在庫回転率 | X1: 前回決定事項（1/23） | Y1: 決定事項 | AE1: 前回決定事項（/） | AG1: 決定事項
A2: 1 | B2: 伊賀 | C2: APL-4312SBL | D2: ミニホイッスル付LEDアルミライトⅡ | H2: 192 | I2: =VLOOKUP(C2,'202310-202403出荷数total2403220951'!B:F,5,0) -> 71 | J2: =VLOOKUP(C2,'出荷数2307～2406total241008110618'!B:F,5,0) -> 281 | K2: =VLOOKUP(C2,'出荷数2407-2506total250730101950'!B:F,5,0) -> 902 | L2: =VLOOKUP(C:C,total251219111800!B:F,5,0) -> 386 | N2: =L2 -> 386 | O2: 327 | P2: 700 | Q2: 0 | R2: 0 | S2: 540 | T2: 160 | U2: -213 | V2: -599 | W2: 0.375852
A3: 2 | B3: 伊賀 | C3: APL-4312SPK | D3: ミニホイッスル付LEDアルミライトⅡ | H3: 2161 | I3: =VLOOKUP(C3,'202310-202403出荷数total2403220951'!B:F,5,0) -> 1018 | J3: =VLOOKUP(C3,'出荷数2307～2406total241008110618'!B:F,5,0) -> 1930 | K3: =VLOOKUP(C3,'出荷数2407-2506total250730101950'!B:F,5,0) -> 3388 | L3: =VLOOKUP(C:C,total251219111800!B:F,5,0) -> 903 | N3: =L3 -> 903 | O3: 1782 | P3: 1290 | Q3: 0 | R3: 0 | S3: 1790 | T3: -500 | U3: -8 | V3: -911 | W3: 0.29394531
A4: 86 | B4: 伊賀 | C4: ABO-08BL | D4: ミニホイッスル | E4: ブルー | F4: 527 | G4: 2107 | H4: 796 | I4: =VLOOKUP(C4,'202310-202403出荷数total2403220951'!B:F,5,0) -> 1409 | J4: =VLOOKUP(C4,'出荷数2307～2406total241008110618'!B:F,5,0) -> 1708 | K4: =VLOOKUP(C4,'出荷数2407-2506total250730101950'!B:F,5,0) -> 1865 | L4: =VLOOKUP(C:C,total251219111800!B:F,5,0) -> 474 | M4: 1000 | N4: 1000 | O4: 6744 | P4: 0 | Q4: 0 | R4: 0 | S4: 0 | T4: 0 | U4: 6744 | V4: 5744 | W4: 0.14827995
A5: 107 | B5: 伊賀 | C5: ABO-08PK | D5: ミニホイッスル | E5: ピンク | F5: 3939 | G5: 5966 | H5: 5009 | I5: =VLOOKUP(C5,'202310-202403出荷数total2403220951'!B:F,5,0) -> 6490 | J5: =VLOOKUP(C5,'出荷数2307～2406total241008110618'!B:F,5,0) -> 17931 | K5: =VLOOKUP(C5,'出荷数2407-2506total250730101950'!B:F,5,0) -> 28387 | L5: =VLOOKUP(C:C,total251219111800!B:F,5,0) -> 4495 | N5: =L5 -> 4495 | O5: 27847 | P5: 28180 | Q5: 800 | R5: 0 | S5: 28180 | T5: 0 | U5: 467 | V5: -4028 | W5: 0.080229175
A6: 109 | B6: 伊賀 | C6: APL-4302S | D6: ＬＥＤミニアルミライト | F6: 1094 | G6: 3475 | H6: 834 | I6: =VLOOKUP(C6,'202310-202403出荷数total2403220951'!B:F,5,0) -> 444 | J6: =VLOOKUP(C6,'出荷数2307～2406total241008110618'!B:F,5,0) -> 789 | K6: =VLOOKUP(C6,'出荷数2407-2506total250730101950'!B:F,5,0) -> 232 | L6: =VLOOKUP(C:C,total251219111800!B:F,5,0) -> 177 | N6: =L6 -> 177 | O6: 3754 | P6: 0 | Q6: 300 | R6: 0 | S6: 0 | T6: 0 | U6: 4054 | V6: 3877 | W6: 0.047149707
A7: 3 | B7: 伊賀 | C7: ASL-3308SK | D7: ウォールセンサーライト 箱 | E7: しかく | F7: 1 | G7: 0 | H7: 4 | I7: =VLOOKUP(C7,'202310-202403出荷数total2403220951'!B:F,5,0) -> #N/A | J7: =VLOOKUP(C7,'出荷数2307～2406total241008110618'!B:F,5,0) -> #N/A | K7: =VLOOKUP(C7,'出荷数2407-2506total250730101950'!B:F,5,0) -> #N/A | L7: =VLOOKUP(C:C,total251219111800!B:F,5,0) -> #N/A | N7: 0 | O7: 1 | P7: 0 | Q7: 0 | R7: 0 | S7: 0 | T7: 0 | U7: 1 | V7: 1 | W7: 0
A8: 4 | B8: 伊賀 | C8: AHL-3201RD | D8: LEDハンディライト | H8: 2048 | I8: =VLOOKUP(C8,'202310-202403出荷数total2403220951'!B:F,5,0) -> 2098 | J8: =VLOOKUP(C8,'出荷数2307～2406total241008110618'!B:F,5,0) -> 3644 | K8: =VLOOKUP(C8,'出荷数2407-2506total250730101950'!B:F,5,0) -> 2910 | L8: =VLOOKUP(C:C,total251219111800!B:F,5,0) -> 2559 | N8: =L8 -> 2559 | O8: 3061 | P8: 0 | Q8: 0 | R8: 0 | S8: 0 | T8: 0 | U8: 3061 | V8: 502 | W8: 0.83600131
A9: 5 | B9: 伊賀 | C9: AHL-3201WH | D9: LEDハンディライト | H9: 116 | I9: =VLOOKUP(C9,'202310-202403出荷数total2403220951'!B:F,5,0) -> 220 | J9: =VLOOKUP(C9,'出荷数2307～2406total241008110618'!B:F,5,0) -> 378 | K9: =VLOOKUP(C9,'出荷数2407-2506total250730101950'!B:F,5,0) -> 2016 | L9: =VLOOKUP(C:C,total251219111800!B:F,5,0) -> 281 | M9: 1000 | N9: 1000 | O9: 5183 | P9: 0 | Q9: 0 | R9: 0 | S9: 0 | T9: 0 | U9: 5183 | V9: 4183 | W9: 0.19293845
A10: 6 | B10: 伊賀 | C10: AHL-1400 | D10: LED強力ライト | H10: 15126 | I10: =VLOOKUP(C10,'202310-202403出荷数total2403220951'!B:F,5,0) -> 9163 | J10: =VLOOKUP(C10,'出荷数2307～2406total241008110618'!B:F,5,0) -> 19757 | K10: =VLOOKUP(C10,'出荷数2407-2506total250730101950'!B:F,5,0) -> 20812 | L10: =VLOOKUP(C:C,total251219111800!B:F,5,0) -> 4356 | N10: =L10 -> 4356 | O10: 1838 | P10: 17595 | Q10: 0 | R10: 0 | S10: 17425 | T10: 170 | U10: -15587 | V10: -19943 | W10: 0.22415479
A11: 7 | B11: 伊賀 | C11: AHL-1400T | D11: LED強力ライト(トップ) | H11: 2084 | I11: =VLOOKUP(C11,'202310-202403出荷数total2403220951'!B:F,5,0) -> 1160 | J11: =VLOOKUP(C11,'出荷数2307～2406total241008110618'!B:F,5,0) -> 1821 | K11: =VLOOKUP(C11,'出荷数2407-2506total250730101950'!B:F,5,0) -> 1120 | L11: =VLOOKUP(C:C,total251219111800!B:F,5,0) -> 160 | N11: =L11 -> 160 | O11: 2 | P11: 0 | Q11: 0 | R11: 0 | S11: 0 | T11: 0 | U11: 2 | V11: -158 | W11: 80
A12: 8 | B12: 伊賀 | C12: ASL-3308KU | D12: ウォールセンサーライト 箱 | E12: くも | F12: 193 | G12: 1 | H12: 100 | I12: =VLOOKUP(C12,'202310-202403出荷数total2403220951'!B:F,5,0) -> 43 | J12: =VLOOKUP(C12,'出荷数2307～2406total241008110618'!B:F,5,0) -> 51 | K12: =VLOOKUP(C12,'出荷数2407-2506total250730101950'!B:F,5,0) -> 12 | L12: =VLOOKUP(C:C,total251219111800!B:F,5,0) -> 3 | N12: =L12 -> 3 | O12: 1000 | P12: 0 | Q12: 0 | R12: 0 | S12: 0 | T12: 0 | U12: 1000 | V12: 997 | W12: 0.003
A13: 9 | B13: 伊賀 | C13: ANS-502 | D13: テレビ用手もとスピーカー | G13: 6 | H13: 2364 | I13: =VLOOKUP(C13,'202310-202403出荷数total2403220951'!B:F,5,0) -> 1052 | J13: =VLOOKUP(C13,'出荷数2307～2406total241008110618'!B:F,5,0) -> 1711 | K13: =VLOOKUP(C13,'出荷数2407-2506total250730101950'!B:F,5,0) -> 1026 | L13: =VLOOKUP(C:C,total251219111800!B:F,5,0) -> 587 | N13: =L13 -> 587 | O13: 3542 | P13: 0 | Q13: 0 | R13: 0 | S13: 0 | T13: 0 | U13: 3542 | V13: 2955 | W13: 0.16572558
A14: 10 | B14: 伊賀 | C14: ASL-3308US | D14: ウォールセンサーライト 箱 | E14: うさぎ | F14: 0 | G14: 3 | H14: 363 | I14: =VLOOKUP(C14,'202310-202403出荷数total2403220951'!B:F,5,0) -> #N/A | J14: =VLOOKUP(C14,'出荷数2307～2406total241008110618'!B:F,5,0) -> 1 | K14: =VLOOKUP(C14,'出荷数2407-2506total250730101950'!B:F,5,0) -> 7 | L14: =VLOOKUP(C:C,total251219111800!B:F,5,0) -> #N/A | N14: 0 | O14: 744 | P14: 0 | Q14: 0 | R14: 0 | S14: 0 | T14: 0 | U14: 744 | V14: 744 | W14: 0
A15: 11 | B15: 伊賀 | C15: ASL-3308CSK | D15: ウォールセンサーライト ブリスター | E15: しかく | F15: 23 | G15: 4 | H15: 0 | I15: =VLOOKUP(C15,'202310-202403出荷数total2403220951'!B:F,5,0) -> 1 | J15: =VLOOKUP(C15,'出荷数2307～2406total241008110618'!B:F,5,0) -> 705 | K15: =VLOOKUP(C15,'出荷数2407-2506total250730101950'!B:F,5,0) -> 1 | L15: =VLOOKUP(C:C,total251219111800!B:F,5,0) -> 1 | N15: =L15 -> 1 | O15: 0 | P15: 0 | Q15: 0 | R15: 0 | S15: 0 | T15: 0 | U15: 0 | V15: -1 | W15: #DIV/0!
A16: 12 | B16: 伊賀 | C16: ASL-3308CUS | D16: ウォールセンサーライト ブリスター | E16: うさぎ | F16: 35 | G16: 26 | H16: 5 | I16: =VLOOKUP(C16,'202310-202403出荷数total2403220951'!B:F,5,0) -> 3 | J16: =VLOOKUP(C16,'出荷数2307～2406total241008110618'!B:F,5,0) -> 6 | K16: =VLOOKUP(C16,'出荷数2407-2506total250730101950'!B:F,5,0) -> 3 | L16: =VLOOKUP(C:C,total251219111800!B:F,5,0) -> 142 | N16: =L16 -> 142 | O16: 4414 | P16: 0 | Q16: 0 | R16: 0 | S16: 0 | T16: 0 | U16: 4414 | V16: 4272 | W16: 0.032170367
A17: 13 | B17: 伊賀 | C17: AKM-3205PK | D17: 首ふり毛だまクリーナー | E17: ピンク | F17: 33 | G17: 24 | H17: 2990 | I17: =VLOOKUP(C17,'202310-202403出荷数total2403220951'!B:F,5,0) -> 66 | J17: =VLOOKUP(C17,'出荷数2307～2406total241008110618'!B:F,5,0) -> 189 | K17: =VLOOKUP(C17,'出荷数2407-2506total250730101950'!B:F,5,0) -> 97 | L17: =VLOOKUP(C:C,total251219111800!B:F,5,0) -> 77 | N17: =L17 -> 77 | O17: 2106 | P17: 0 | Q17: 0 | R17: 0 | S17: 0 | T17: 0 | U17: 2106 | V17: 2029 | W17: 0.036562203
A18: 14 | B18: 伊賀 | C18: ASN-4302 | D18: マグネット付ＬＥＤ信号灯 | F18: 149 | G18: 62 | H18: 132 | I18: =VLOOKUP(C18,'202310-202403出荷数total2403220951'!B:F,5,0) -> 245 | J18: =VLOOKUP(C18,'出荷数2307～2406total241008110618'!B:F,5,0) -> 322 | K18: =VLOOKUP(C18,'出荷数2407-2506total250730101950'!B:F,5,0) -> 206 | L18: =VLOOKUP(C:C,total251219111800!B:F,5,0) -> 17 | N18: =L18 -> 17 | O18: 2255 | P18: 0 | Q18: 0 | R18: 0 | S18: 0 | T18: 0 | U18: 2255 | V18: 2238 | W18: 0.0075388027 | X18: 売り切り廃盤予定
A19: 15 | B19: 伊賀 | C19: AIC-01IV | D19: ｷｽﾞつきにくいｲｽ脚ｶﾊﾞｰ | E19: IV | F19: 228 | G19: 270 | H19: 231 | I19: =VLOOKUP(C19,'202310-202403出荷数total2403220951'!B:F,5,0) -> 121 | J19: =VLOOKUP(C19,'出荷数2307～2406total241008110618'!B:F,5,0) -> 177 | K19: =VLOOKUP(C19,'出荷数2407-2506total250730101950'!B:F,5,0) -> 110 | L19: =VLOOKUP(C:C,total251219111800!B:F,5,0) -> 53 | N19: =L19 -> 53 | O19: 8059 | P19: 0 | Q19: 0 | R19: 0 | S19: 0 | T19: 0 | U19: 8059 | V19: 8006 | W19: 0.0065764983
A20: 16 | B20: 伊賀 | C20: ANS-603 | D20: お経の流れるスピーカーⅡ | G20: 128 | H20: 470 | I20: =VLOOKUP(C20,'202310-202403出荷数total2403220951'!B:F,5,0) -> 149 | J20: =VLOOKUP(C20,'出荷数2307～2406total241008110618'!B:F,5,0) -> 418 | K20: =VLOOKUP(C20,'出荷数2407-2506total250730101950'!B:F,5,0) -> 818 | L20: =VLOOKUP(C:C,total251219111800!B:F,5,0) -> 491 | N20: =L20 -> 491 | O20: 590 | P20: 130 | Q20: 0 | R20: 0 | S20: 130 | T20: 0 | U20: 460 | V20: -31 | W20: 0.68194444 | X20: トップ確保3月末まで確保
A21: 17 | B21: 伊賀 | C21: APY-105 | D21: 迷惑電話お断りピンポン | F21: 543 | G21: 321 | H21: 270 | I21: =VLOOKUP(C21,'202310-202403出荷数total2403220951'!B:F,5,0) -> 73 | J21: =VLOOKUP(C21,'出荷数2307～2406total241008110618'!B:F,5,0) -> 181 | K21: =VLOOKUP(C21,'出荷数2407-2506total250730101950'!B:F,5,0) -> 277 | L21: =VLOOKUP(C:C,total251219111800!B:F,5,0) -> 141 | N21: =L21 -> 141 | O21: 3278 | P21: 370 | Q21: 0 | R21: 0 | S21: 454 | T21: -84 | U21: 2824 | V21: 2683 | W21: 0.038651316
A22: 18 | B22: 伊賀 | C22: APL-3207S | D22: LEDのインテリア常備灯 | F22: 904 | G22: 638 | H22: 81 | I22: =VLOOKUP(C22,'202310-202403出荷数total2403220951'!B:F,5,0) -> 2 | J22: =VLOOKUP(C22,'出荷数2307～2406total241008110618'!B:F,5,0) -> 904 | K22: =VLOOKUP(C22,'出荷数2407-2506total250730101950'!B:F,5,0) -> 25 | L22: =VLOOKUP(C:C,total251219111800!B:F,5,0) -> 2 | N22: =L22 -> 2 | O22: 6860 | P22: 0 | Q22: 0 | R22: 0 | S22: 0 | T22: 0 | U22: 6860 | V22: 6858 | W22: 0.00029154519
A23: 19 | B23: 伊賀 | C23: ALA-4308BK-D | D23: ひっぱり点灯ライト 電球色ＬＥＤ | F23: 1137 | G23: 270 | H23: 272 | I23: =VLOOKUP(C23,'202310-202403出荷数total2403220951'!B:F,5,0) -> 153 | J23: =VLOOKUP(C23,'出荷数2307～2406total241008110618'!B:F,5,0) -> 657 | K23: =VLOOKUP(C23,'出荷数2407-2506total250730101950'!B:F,5,0) -> 101 | L23: =VLOOKUP(C:C,total251219111800!B:F,5,0) -> 88 | N23: =L23 -> 88 | O23: 1782 | P23: 0 | Q23: 0 | R23: 0 | S23: 0 | T23: 0 | U23: 1782 | V23: 1694 | W23: 0.049382716
A24: 20 | B24: 伊賀 | C24: ACA-101 | D24: ＬＥＤ帽子ライト | F24: 787 | G24: 450 | H24: 417 | I24: =VLOOKUP(C24,'202310-202403出荷数total2403220951'!B:F,5,0) -> 450 | J24: =VLOOKUP(C24,'出荷数2307～2406total241008110618'!B:F,5,0) -> 550 | K24: =VLOOKUP(C24,'出荷数2407-2506total250730101950'!B:F,5,0) -> 160 | L24: =VLOOKUP(C:C,total251219111800!B:F,5,0) -> 89 | N24: =L24 -> 89 | O24: 3704 | P24: 0 | Q24: 0 | R24: 0 | S24: 0 | T24: 0 | U24: 3704 | V24: 3615 | W24: 0.024028078
A25: 21 | B25: 伊賀 | C25: ASL-3308NE | D25: ウォールセンサーライト 箱 | E25: ねこ | F25: 13 | G25: 4 | H25: 8 | I25: =VLOOKUP(C25,'202310-202403出荷数total2403220951'!B:F,5,0) -> 1 | J25: =VLOOKUP(C25,'出荷数2307～2406total241008110618'!B:F,5,0) -> 4 | K25: =VLOOKUP(C25,'出荷数2407-2506total250730101950'!B:F,5,0) -> 6 | L25: =VLOOKUP(C:C,total251219111800!B:F,5,0) -> #N/A | N25: 0 | O25: 24 | P25: 0 | Q25: 0 | R25: 0 | S25: 0 | T25: 0 | U25: 24 | V25: 24 | W25: 0
A26: 22 | B26: 伊賀 | C26: AKD-20 | D26: アニマルシリコンバンド | F26: 1809 | G26: 790 | H26: 1042 | I26: =VLOOKUP(C26,'202310-202403出荷数total2403220951'!B:F,5,0) -> 164 | J26: =VLOOKUP(C26,'出荷数2307～2406total241008110618'!B:F,5,0) -> 312 | K26: =VLOOKUP(C26,'出荷数2407-2506total250730101950'!B:F,5,0) -> 454 | L26: =VLOOKUP(C:C,total251219111800!B:F,5,0) -> 168 | N26: =L26 -> 168 | O26: 5689 | P26: 100 | Q26: 0 | R26: 0 | S26: 300 | T26: -200 | U26: 5389 | V26: 5221 | W26: 0.029020556
A27: 23 | B27: 伊賀 | C27: ARA-4301 | D27: スマートフォンが使えるラジオライト | F27: 549 | G27: 303 | H27: 236 | I27: =VLOOKUP(C27,'202310-202403出荷数total2403220951'!B:F,5,0) -> 241 | J27: =VLOOKUP(C27,'出荷数2307～2406total241008110618'!B:F,5,0) -> 358 | K27: =VLOOKUP(C27,'出荷数2407-2506total250730101950'!B:F,5,0) -> 392 | L27: =VLOOKUP(C:C,total251219111800!B:F,5,0) -> 29 | N27: =L27 -> 29 | O27: 1917 | P27: 0 | Q27: 0 | R27: 0 | S27: 0 | T27: 0 | U27: 1917 | V27: 1888 | W27: 0.015127804
A28: 24 | B28: 伊賀 | C28: ASK-11BOR | D28: 巻きつく安全反射バンド(OR) | E28: オレンジ | F28: 1160 | G28: 148 | H28: 651 | I28: =VLOOKUP(C28,'202310-202403出荷数total2403220951'!B:F,5,0) -> 60 | J28: =VLOOKUP(C28,'出荷数2307～2406total241008110618'!B:F,5,0) -> 125 | K28: =VLOOKUP(C28,'出荷数2407-2506total250730101950'!B:F,5,0) -> 265 | L28: =VLOOKUP(C:C,total251219111800!B:F,5,0) -> 38 | M28: 500 | N28: 500 | O28: 2298 | P28: 0 | Q28: 0 | R28: 0 | S28: 0 | T28: 0 | U28: 2298 | V28: 1798 | W28: 0.2175805
A29: 25 | B29: 伊賀 | C29: ASK-10YE | D29: 光るホイール反射シール | E29: イエロー | F29: 935 | G29: 77 | H29: 731 | I29: =VLOOKUP(C29,'202310-202403出荷数total2403220951'!B:F,5,0) -> 163 | J29: =VLOOKUP(C29,'出荷数2307～2406total241008110618'!B:F,5,0) -> 235 | K29: =VLOOKUP(C29,'出荷数2407-2506total250730101950'!B:F,5,0) -> 20 | L29: =VLOOKUP(C:C,total251219111800!B:F,5,0) -> 2 | N29: =L29 -> 2 | O29: 5 | P29: 0 | Q29: 0 | R29: 0 | S29: 0 | T29: 0 | U29: 5 | V29: 3 | W29: 0.4
A30: 26 | B30: 伊賀 | C30: ARO-530GD | D30: 自動消灯安心のろうそく | E30: GD | F30: 224 | G30: 198 | H30: 230 | I30: =VLOOKUP(C30,'202310-202403出荷数total2403220951'!B:F,5,0) -> 91 | J30: =VLOOKUP(C30,'出荷数2307～2406total241008110618'!B:F,5,0) -> 168 | K30: =VLOOKUP(C30,'出荷数2407-2506total250730101950'!B:F,5,0) -> 52 | L30: =VLOOKUP(C:C,total251219111800!B:F,5,0) -> 28 | N30: =L30 -> 28 | O30: 918 | P30: 0 | Q30: 0 | R30: 0 | S30: 0 | T30: 0 | U30: 918 | V30: 890 | W30: 0.030501089
A31: 27 | B31: 伊賀 | C31: ALA-4308MO-W | D31: ひっぱり点灯ライト 木目 | E31: 木目 | F31: 714 | G31: 368 | H31: 496 | I31: =VLOOKUP(C31,'202310-202403出荷数total2403220951'!B:F,5,0) -> 150 | J31: =VLOOKUP(C31,'出荷数2307～2406total241008110618'!B:F,5,0) -> 247 | K31: =VLOOKUP(C31,'出荷数2407-2506total250730101950'!B:F,5,0) -> 43 | L31: =VLOOKUP(C:C,total251219111800!B:F,5,0) -> 29 | N31: =L31 -> 29 | O31: 1947 | P31: 0 | Q31: 0 | R31: 0 | S31: 0 | T31: 0 | U31: 1947 | V31: 1918 | W31: 0.01489471
A32: 28 | B32: 伊賀 | C32: AIC-06IV | D32: ｽﾞﾚにくいｲｽ脚ｶﾊﾞｰ 2脚用 | E32: IV | F32: 1116 | G32: 928 | H32: 1098 | I32: =VLOOKUP(C32,'202310-202403出荷数total2403220951'!B:F,5,0) -> 427 | J32: =VLOOKUP(C32,'出荷数2307～2406total241008110618'!B:F,5,0) -> 1008 | K32: =VLOOKUP(C32,'出荷数2407-2506total250730101950'!B:F,5,0) -> 854 | L32: =VLOOKUP(C:C,total251219111800!B:F,5,0) -> 345 | N32: =L32 -> 345 | O32: 3036 | P32: 0 | Q32: 0 | R32: 0 | S32: 0 | T32: 0 | U32: 3036 | V32: 2691 | W32: 0.11363636 | X32: 88％発注点よりﾏｲﾅｽ 345→41
A33: 29 | B33: 伊賀 | C33: ANS-701AD | D33: ＡＣアダプター701用 | F33: 120 | G33: 98 | H33: 141 | I33: =VLOOKUP(C33,'202310-202403出荷数total2403220951'!B:F,5,0) -> 41 | J33: =VLOOKUP(C33,'出荷数2307～2406total241008110618'!B:F,5,0) -> 89 | K33: =VLOOKUP(C33,'出荷数2407-2506total250730101950'!B:F,5,0) -> 92 | L33: =VLOOKUP(C:C,total251219111800!B:F,5,0) -> 49 | N33: =L33 -> 49 | O33: 317 | P33: 0 | Q33: 0 | R33: 0 | S33: 0 | T33: 0 | U33: 317 | V33: 268 | W33: 0.15457413
A34: 30 | B34: 伊賀 | C34: ANS-702 | D34: 大きな手もとスピーカー | F34: 1030 | G34: 390 | H34: 221 | I34: =VLOOKUP(C34,'202310-202403出荷数total2403220951'!B:F,5,0) -> 53 | J34: =VLOOKUP(C34,'出荷数2307～2406total241008110618'!B:F,5,0) -> 103 | K34: =VLOOKUP(C34,'出荷数2407-2506total250730101950'!B:F,5,0) -> 224 | L34: =VLOOKUP(C:C,total251219111800!B:F,5,0) -> 45 | N34: =L34 -> 45 | O34: 2078 | P34: 0 | Q34: 0 | R34: 0 | S34: 0 | T34: 0 | U34: 2078 | V34: 2033 | W34: 0.021655438
A35: 31 | B35: 伊賀 | C35: AKN-15 | D35: ハローキティ コンセントカバー | F35: 1322 | G35: 1075 | H35: 946 | I35: =VLOOKUP(C35,'202310-202403出荷数total2403220951'!B:F,5,0) -> 348 | J35: =VLOOKUP(C35,'出荷数2307～2406total241008110618'!B:F,5,0) -> 766 | K35: =VLOOKUP(C35,'出荷数2407-2506total250730101950'!B:F,5,0) -> 1074 | L35: =VLOOKUP(C:C,total251219111800!B:F,5,0) -> 327 | N35: =L35 -> 327 | O35: 3528 | P35: 0 | Q35: 0 | R35: 0 | S35: 0 | T35: 0 | U35: 3528 | V35: 3201 | W35: 0.092687075
A36: 32 | B36: 伊賀 | C36: ACA-3101 | D36: ＬＥＤアルミヘッドランプ | F36: 1781 | G36: 1472 | H36: 1360 | I36: =VLOOKUP(C36,'202310-202403出荷数total2403220951'!B:F,5,0) -> 3651 | J36: =VLOOKUP(C36,'出荷数2307～2406total241008110618'!B:F,5,0) -> 4452 | K36: =VLOOKUP(C36,'出荷数2407-2506total250730101950'!B:F,5,0) -> 4054 | L36: =VLOOKUP(C:C,total251219111800!B:F,5,0) -> 524 | N36: =L36 -> 524 | O36: 12994 | P36: 0 | Q36: 100 | R36: 0 | S36: 0 | T36: 0 | U36: 13094 | V36: 12570 | W36: 0.040326304
A37: 33 | B37: 伊賀 | C37: ASK-06SI | D37: はめるだけ光る 足腕バンド | E37: シルバー | F37: 1210 | G37: 214 | H37: 13 | I37: =VLOOKUP(C37,'202310-202403出荷数total2403220951'!B:F,5,0) -> 75 | J37: =VLOOKUP(C37,'出荷数2307～2406total241008110618'!B:F,5,0) -> 79 | K37: =VLOOKUP(C37,'出荷数2407-2506total250730101950'!B:F,5,0) -> 1 | L37: =VLOOKUP(C:C,total251219111800!B:F,5,0) -> 3 | N37: =L37 -> 3 | O37: 875 | P37: 0 | Q37: 0 | R37: 0 | S37: 0 | T37: 0 | U37: 875 | V37: 872 | W37: 0.0034285714
A38: 34 | B38: 伊賀 | C38: ASL-3308CNE | D38: ウォールセンサーライト ブリスター | E38: ねこ | F38: 271 | G38: 200 | H38: 124 | I38: =VLOOKUP(C38,'202310-202403出荷数total2403220951'!B:F,5,0) -> 63 | J38: =VLOOKUP(C38,'出荷数2307～2406total241008110618'!B:F,5,0) -> 93 | K38: =VLOOKUP(C38,'出荷数2407-2506total250730101950'!B:F,5,0) -> 14 | L38: =VLOOKUP(C:C,total251219111800!B:F,5,0) -> 140 | N38: =L38 -> 140 | O38: 797 | P38: 0 | Q38: 0 | R38: 0 | S38: 0 | T38: 0 | U38: 797 | V38: 657 | W38: 0.17565872
A39: 35 | B39: 伊賀 | C39: ASL-33082 | D39: ウォールセンサーライト（ショップチャンネル専用） | G39: 9 | H39: 1109 | I39: =VLOOKUP(C39,'202310-202403出荷数total2403220951'!B:F,5,0) -> #N/A | J39: =VLOOKUP(C39,'出荷数2307～2406total241008110618'!B:F,5,0) -> #N/A | K39: =VLOOKUP(C39,'出荷数2407-2506total250730101950'!B:F,5,0) -> #N/A | L39: =VLOOKUP(C:C,total251219111800!B:F,5,0) -> #N/A | M39: 470 | N39: 470 | O39: 106 | P39: 0 | Q39: 0 | R39: 0 | S39: 0 | T39: 0 | U39: 106 | V39: -364 | W39: 4.4339623
A40: 36 | B40: 伊賀 | C40: ADR-3401 | D40: 電動角質リムーバー | F40: 19 | G40: 1283 | H40: 7 | I40: =VLOOKUP(C40,'202310-202403出荷数total2403220951'!B:F,5,0) -> 223 | J40: =VLOOKUP(C40,'出荷数2307～2406total241008110618'!B:F,5,0) -> 598 | K40: =VLOOKUP(C40,'出荷数2407-2506total250730101950'!B:F,5,0) -> 73 | L40: =VLOOKUP(C:C,total251219111800!B:F,5,0) -> 5 | N40: =L40 -> 5 | O40: 4161 | P40: 0 | Q40: 0 | R40: 0 | S40: 0 | T40: 0 | U40: 4161 | V40: 4156 | W40: 0.0012016342
A41: 37 | B41: 伊賀 | C41: ASL-3309 | D41: センサーライト付防犯ダミーカメラ | F41: 825 | G41: 660 | H41: 1314 | I41: =VLOOKUP(C41,'202310-202403出荷数total2403220951'!B:F,5,0) -> 262 | J41: =VLOOKUP(C41,'出荷数2307～2406total241008110618'!B:F,5,0) -> 723 | K41: =VLOOKUP(C41,'出荷数2407-2506total250730101950'!B:F,5,0) -> 1443 | L41: =VLOOKUP(C:C,total251219111800!B:F,5,0) -> 305 | N41: =L41 -> 305 | O41: 3047 | P41: 190 | Q41: 0 | R41: 0 | S41: 300 | T41: -110 | U41: 2747 | V41: 2442 | W41: 0.094223046
A42: 38 | B42: 伊賀 | C42: ADR-3401KR | D42: 電動角質リムーバー交換用ローラー（2PCS) | F42: 33 | G42: 994 | H42: 20 | I42: =VLOOKUP(C42,'202310-202403出荷数total2403220951'!B:F,5,0) -> 14 | J42: =VLOOKUP(C42,'出荷数2307～2406total241008110618'!B:F,5,0) -> 26 | K42: =VLOOKUP(C42,'出荷数2407-2506total250730101950'!B:F,5,0) -> 8 | L42: =VLOOKUP(C:C,total251219111800!B:F,5,0) -> 4 | N42: =L42 -> 4 | O42: 4563 | P42: 0 | Q42: 0 | R42: 0 | S42: 0 | T42: 0 | U42: 4563 | V42: 4559 | W42: 0.00087661626
A43: 39 | B43: 伊賀 | C43: KCA-003 | D43: キューベルク 充電式ヘッドライト340 | F43: 15 | G43: 257 | H43: 96 | I43: =VLOOKUP(C43,'202310-202403出荷数total2403220951'!B:F,5,0) -> 18 | J43: =VLOOKUP(C43,'出荷数2307～2406total241008110618'!B:F,5,0) -> 45 | K43: =VLOOKUP(C43,'出荷数2407-2506total250730101950'!B:F,5,0) -> 101 | L43: =VLOOKUP(C:C,total251219111800!B:F,5,0) -> 21 | N43: =L43 -> 21 | O43: 787 | P43: 0 | Q43: 0 | R43: 0 | S43: 0 | T43: 0 | U43: 787 | V43: 766 | W43: 0.026683609
B44: 伊賀 | C44: KCA-004H | D44: ロータリー式ヘッドライト500 | L44: =VLOOKUP(C:C,total251219111800!B:F,5,0) -> 3 | N44: =L44 -> 3 | O44: 493 | P44: 0 | Q44: 1000 | R44: 0 | S44: 0 | T44: 0 | U44: 1493 | V44: 1490 | W44: 0.0060851927
A45: 40 | B45: 伊賀 | C45: ABO-180 | D45: エアーマット1800 | F45: 940 | G45: 457 | H45: 1013 | I45: =VLOOKUP(C45,'202310-202403出荷数total2403220951'!B:F,5,0) -> 669 | J45: =VLOOKUP(C45,'出荷数2307～2406total241008110618'!B:F,5,0) -> 4147 | K45: =VLOOKUP(C45,'出荷数2407-2506total250730101950'!B:F,5,0) -> 4439 | L45: =VLOOKUP(C:C,total251219111800!B:F,5,0) -> 49 | N45: =L45 -> 49 | O45: 307 | P45: 0 | Q45: 0 | R45: 0 | S45: 0 | T45: 0 | U45: 307 | V45: 258 | W45: 0.15960912
A46: 41 | B46: 伊賀 | C46: ABO-120 | D46: エアーマット1200 | F46: 149 | G46: 373 | H46: 66 | I46: =VLOOKUP(C46,'202310-202403出荷数total2403220951'!B:F,5,0) -> 150 | J46: =VLOOKUP(C46,'出荷数2307～2406total241008110618'!B:F,5,0) -> 203 | K46: =VLOOKUP(C46,'出荷数2407-2506total250730101950'!B:F,5,0) -> 212 | L46: =VLOOKUP(C:C,total251219111800!B:F,5,0) -> 39 | N46: =L46 -> 39 | O46: 958 | P46: 0 | Q46: 0 | R46: 0 | S46: 0 | T46: 0 | U46: 958 | V46: 919 | W46: 0.040709812
A47: 42 | B47: 伊賀 | C47: AIC-01BR | D47: ｷｽﾞつきにくいｲｽ脚ｶﾊﾞｰ | E47: BR | F47: 2264 | G47: 1923 | H47: 1776 | I47: =VLOOKUP(C47,'202310-202403出荷数total2403220951'!B:F,5,0) -> 535 | J47: =VLOOKUP(C47,'出荷数2307～2406total241008110618'!B:F,5,0) -> 2161 | K47: =VLOOKUP(C47,'出荷数2407-2506total250730101950'!B:F,5,0) -> 933 | L47: =VLOOKUP(C:C,total251219111800!B:F,5,0) -> 398 | N47: =L47 -> 398 | O47: 2625 | P47: 0 | Q47: 0 | R47: 0 | S47: 0 | T47: 0 | U47: 2625 | V47: 2227 | W47: 0.15161905
A48: 43 | B48: 伊賀 | C48: AHL-1207 | D48: 単1形LED防雨ライト | F48: 3482 | G48: 1186 | H48: 1004 | I48: =VLOOKUP(C48,'202310-202403出荷数total2403220951'!B:F,5,0) -> 594 | J48: =VLOOKUP(C48,'出荷数2307～2406total241008110618'!B:F,5,0) -> 1198 | K48: =VLOOKUP(C48,'出荷数2407-2506total250730101950'!B:F,5,0) -> 1234 | L48: =VLOOKUP(C:C,total251219111800!B:F,5,0) -> 693 | N48: =L48 -> 693 | O48: 589 | P48: 0 | Q48: 0 | R48: 0 | S48: 0 | T48: 0 | U48: 589 | V48: -104 | W48: 1.1765705
A49: 44 | B49: 伊賀 | C49: ABO-11 | D49: 防炎非常持出袋 | F49: 5224 | G49: 1145 | H49: 1174 | I49: =VLOOKUP(C49,'202310-202403出荷数total2403220951'!B:F,5,0) -> 435 | J49: =VLOOKUP(C49,'出荷数2307～2406total241008110618'!B:F,5,0) -> 653 | K49: =VLOOKUP(C49,'出荷数2407-2506total250730101950'!B:F,5,0) -> 1213 | L49: =VLOOKUP(C:C,total251219111800!B:F,5,0) -> 373 | N49: =L49 -> 373 | O49: 3846 | P49: 0 | Q49: 0 | R49: 0 | S49: 0 | T49: 0 | U49: 3846 | V49: 3473 | W49: 0.096983879
A50: 45 | B50: 伊賀 | C50: ANS-302BK | D50: テレビの音も聞こえる 手もとスピーカーⅡ | G50: 537 | H50: 3033 | I50: =VLOOKUP(C50,'202310-202403出荷数total2403220951'!B:F,5,0) -> 1920 | J50: =VLOOKUP(C50,'出荷数2307～2406total241008110618'!B:F,5,0) -> 4184 | K50: =VLOOKUP(C50,'出荷数2407-2506total250730101950'!B:F,5,0) -> 3497 | L50: =VLOOKUP(C:C,total251219111800!B:F,5,0) -> 1086 | M50: 750 | N50: =L50 -> 1086 | O50: 4659 | P50: 840 | Q50: 0 | R50: 0 | S50: 840 | T50: 0 | U50: 3819 | V50: 2733 | W50: 0.19749045
A51: 46 | B51: 伊賀 | C51: APL-3207SMO | D51: LEDのインテリア常備灯(化粧箱) | E51: 木目 | F51: 1023 | G51: 517 | H51: 437 | I51: =VLOOKUP(C51,'202310-202403出荷数total2403220951'!B:F,5,0) -> 346 | J51: =VLOOKUP(C51,'出荷数2307～2406total241008110618'!B:F,5,0) -> 396 | K51: =VLOOKUP(C51,'出荷数2407-2506total250730101950'!B:F,5,0) -> 187 | L51: =VLOOKUP(C:C,total251219111800!B:F,5,0) -> 6 | N51: =L51 -> 6 | O51: 1255 | P51: 600 | Q51: 0 | R51: 0 | S51: 600 | T51: 0 | U51: 655 | V51: 649 | W51: 0.0032345013
A52: 47 | B52: 伊賀 | C52: AST-3304 | D52: LEDスタンドライト | F52: 843 | G52: 647 | H52: 2107 | I52: =VLOOKUP(C52,'202310-202403出荷数total2403220951'!B:F,5,0) -> #N/A | J52: =VLOOKUP(C52,'出荷数2307～2406total241008110618'!B:F,5,0) -> #N/A | K52: =VLOOKUP(C52,'出荷数2407-2506total250730101950'!B:F,5,0) -> #N/A | L52: =VLOOKUP(C:C,total251219111800!B:F,5,0) -> #N/A | M52: 890 | N52: 890 | O52: 0 | P52: 0 | Q52: 0 | R52: 0 | S52: 0 | T52: 0 | U52: 0 | V52: -890 | W52: #DIV/0!
A53: 48 | B53: 伊賀 | C53: ASL-3305 | D53: 足もと安心防雨センサーライト | F53: 1465 | G53: 1744 | H53: 888 | I53: =VLOOKUP(C53,'202310-202403出荷数total2403220951'!B:F,5,0) -> 559 | J53: =VLOOKUP(C53,'出荷数2307～2406total241008110618'!B:F,5,0) -> 1133 | K53: =VLOOKUP(C53,'出荷数2407-2506total250730101950'!B:F,5,0) -> 829 | L53: =VLOOKUP(C:C,total251219111800!B:F,5,0) -> 200 | N53: =L53 -> 200 | O53: 3363 | P53: 0 | Q53: 0 | R53: 0 | S53: 0 | T53: 0 | U53: 3363 | V53: 3163 | W53: 0.059470711
A54: 49 | B54: 伊賀 | C54: AHA-43ENAUTO | D54: 自動点灯ｻｲｸﾙﾗｲﾄ(ﾊﾝﾄﾞﾙﾀﾞｲﾅﾓ取付) | F54: 1087 | G54: 665 | H54: 2030 | I54: =VLOOKUP(C54,'202310-202403出荷数total2403220951'!B:F,5,0) -> #N/A | J54: =VLOOKUP(C54,'出荷数2307～2406total241008110618'!B:F,5,0) -> #N/A | K54: =VLOOKUP(C54,'出荷数2407-2506total250730101950'!B:F,5,0) -> #N/A | L54: =VLOOKUP(C:C,total251219111800!B:F,5,0) -> #N/A | M54: 850 | N54: 850 | O54: 2 | P54: 0 | Q54: 0 | R54: 0 | S54: 0 | T54: 0 | U54: 2 | V54: -848 | W54: 425
A55: 50 | B55: 伊賀 | C55: AIC-04IV | D55: ｽﾞﾚにくいｲｽ脚ｶﾊﾞｰ 4脚用 | E55: IV | F55: 2129 | G55: 2065 | H55: 2439 | I55: =VLOOKUP(C55,'202310-202403出荷数total2403220951'!B:F,5,0) -> 805 | J55: =VLOOKUP(C55,'出荷数2307～2406total241008110618'!B:F,5,0) -> 1939 | K55: =VLOOKUP(C55,'出荷数2407-2506total250730101950'!B:F,5,0) -> 1171 | L55: =VLOOKUP(C:C,total251219111800!B:F,5,0) -> 566 | N55: =L55 -> 566 | O55: 700 | P55: 0 | Q55: 0 | R55: 0 | S55: 0 | T55: 0 | U55: 700 | V55: 134 | W55: 0.80857143 | X55: 48％発注点よりﾏｲﾅｽ 566→295
A56: 51 | B56: 伊賀 | C56: ABO-13M | D56: ぬげにくい安全スリッパM | F56: 1540 | G56: 597 | H56: 361 | I56: =VLOOKUP(C56,'202310-202403出荷数total2403220951'!B:F,5,0) -> 533 | J56: =VLOOKUP(C56,'出荷数2307～2406total241008110618'!B:F,5,0) -> 858 | K56: =VLOOKUP(C56,'出荷数2407-2506total250730101950'!B:F,5,0) -> 574 | L56: =VLOOKUP(C:C,total251219111800!B:F,5,0) -> #N/A | N56: =L56 -> #N/A | O56: 0 | P56: 0 | Q56: 0 | R56: 0 | S56: 0 | T56: 0 | U56: 0 | V56: #N/A | W56: #N/A
A57: 52 | B57: 伊賀 | C57: ABO-2907 | D57: 水タンクにもなる水のう袋 7枚入り | G57: 2665 | H57: 2710 | I57: =VLOOKUP(C57,'202310-202403出荷数total2403220951'!B:F,5,0) -> 1020 | J57: =VLOOKUP(C57,'出荷数2307～2406total241008110618'!B:F,5,0) -> 7751 | K57: =VLOOKUP(C57,'出荷数2407-2506total250730101950'!B:F,5,0) -> 21996 | L57: =VLOOKUP(C:C,total251219111800!B:F,5,0) -> 8163 | M57: 10000 | N57: 10000 | O57: 20490 | P57: 1400 | Q57: 0 | R57: 0 | S57: 2910 | T57: -1510 | U57: 17580 | V57: 7580 | W57: 0.4568296
A58: 53 | B58: 伊賀 | C58: ALA-4306 | D58: ＬＥＤポケットランタンⅡ 廃版 | F58: 756 | G58: 52 | H58: 44 | I58: =VLOOKUP(C58,'202310-202403出荷数total2403220951'!B:F,5,0) -> 47 | J58: =VLOOKUP(C58,'出荷数2307～2406total241008110618'!B:F,5,0) -> 67 | K58: =VLOOKUP(C58,'出荷数2407-2506total250730101950'!B:F,5,0) -> 12 | L58: =VLOOKUP(C:C,total251219111800!B:F,5,0) -> 2 | N58: =L58 -> 2 | O58: 37 | P58: 0 | Q58: 0 | R58: 0 | S58: 0 | T58: 0 | U58: 37 | V58: 35 | W58: 0.054054054
A59: 54 | B59: 伊賀 | C59: ADC-311WH | D59: 単３が３個で単１電池アダプター | F59: 5239 | G59: 4870 | H59: 3762 | I59: =VLOOKUP(C59,'202310-202403出荷数total2403220951'!B:F,5,0) -> 1545 | J59: =VLOOKUP(C59,'出荷数2307～2406total241008110618'!B:F,5,0) -> 2638 | K59: =VLOOKUP(C59,'出荷数2407-2506total250730101950'!B:F,5,0) -> 3321 | L59: =VLOOKUP(C:C,total251219111800!B:F,5,0) -> 1045 | N59: =L59 -> 1045 | O59: 4146 | P59: 0 | Q59: 0 | R59: 0 | S59: 0 | T59: 0 | U59: 4146 | V59: 3101 | W59: 0.25205017
A60: 55 | B60: 伊賀 | C60: AKO-10 | D60: こたつ専用収納ポケットS | E60: BR | F60: 1332 | G60: 1490 | H60: 2200 | I60: =VLOOKUP(C60,'202310-202403出荷数total2403220951'!B:F,5,0) -> 339 | J60: =VLOOKUP(C60,'出荷数2307～2406total241008110618'!B:F,5,0) -> 1289 | K60: =VLOOKUP(C60,'出荷数2407-2506total250730101950'!B:F,5,0) -> 1155 | L60: =VLOOKUP(C:C,total251219111800!B:F,5,0) -> 362 | N60: =L60 -> 362 | O60: 3794 | P60: 0 | Q60: 0 | R60: 0 | S60: 0 | T60: 0 | U60: 3794 | V60: 3432 | W60: 0.095413811
A61: 56 | B61: 伊賀 | C61: AHM-108 | D61: 録音できるハンドメガホン | F61: 1177 | G61: 1274 | H61: 1310 | I61: =VLOOKUP(C61,'202310-202403出荷数total2403220951'!B:F,5,0) -> 484 | J61: =VLOOKUP(C61,'出荷数2307～2406total241008110618'!B:F,5,0) -> 984 | K61: =VLOOKUP(C61,'出荷数2407-2506total250730101950'!B:F,5,0) -> 1414 | L61: =VLOOKUP(C:C,total251219111800!B:F,5,0) -> 852 | N61: =L61 -> 852 | O61: 1072 | P61: 100 | Q61: 0 | R61: 0 | S61: 100 | T61: 0 | U61: 972 | V61: 120 | W61: 0.72696246
A62: 57 | B62: 伊賀 | C62: ASK-04 | D62: 光るスポークかざり ビーズ | F62: 2501 | G62: 1137 | H62: 1254 | I62: =VLOOKUP(C62,'202310-202403出荷数total2403220951'!B:F,5,0) -> 1064 | J62: =VLOOKUP(C62,'出荷数2307～2406total241008110618'!B:F,5,0) -> 1296 | K62: =VLOOKUP(C62,'出荷数2407-2506total250730101950'!B:F,5,0) -> 172 | L62: =VLOOKUP(C:C,total251219111800!B:F,5,0) -> 765 | N62: =L62 -> 765 | O62: 2106 | P62: 1740 | Q62: 0 | R62: 0 | S62: 1740 | T62: 0 | U62: 366 | V62: -399 | W62: 0.19890796 | X62: 様子見
A63: 58 | B63: 伊賀 | C63: ASK-10SI | D63: 光るホイール反射シール | E63: シルバー | F63: 600 | G63: 225 | H63: 22 | I63: =VLOOKUP(C63,'202310-202403出荷数total2403220951'!B:F,5,0) -> 1 | J63: =VLOOKUP(C63,'出荷数2307～2406total241008110618'!B:F,5,0) -> 1 | K63: =VLOOKUP(C63,'出荷数2407-2506total250730101950'!B:F,5,0) -> #N/A | L63: =VLOOKUP(C:C,total251219111800!B:F,5,0) -> #N/A | N63: =L63 -> #N/A | O63: 552 | P63: 0 | Q63: 0 | R63: 0 | S63: 0 | T63: 0 | U63: 552 | V63: #N/A | W63: #N/A
A64: 59 | B64: 伊賀 | C64: ASK-13 | D64: 光るホイール反射シール | F64: 600 | G64: 225 | H64: 0 | I64: =VLOOKUP(C64,'202310-202403出荷数total2403220951'!B:F,5,0) -> 10 | J64: =VLOOKUP(C64,'出荷数2307～2406total241008110618'!B:F,5,0) -> 11 | K64: =VLOOKUP(C64,'出荷数2407-2506total250730101950'!B:F,5,0) -> 8 | L64: =VLOOKUP(C:C,total251219111800!B:F,5,0) -> 13 | N64: =L64 -> 13 | O64: 1963 | P64: 0 | Q64: 0 | R64: 0 | S64: 0 | T64: 0 | U64: 1963 | V64: 1950 | W64: 0.0066225166
A65: 60 | B65: 伊賀 | C65: ASK-06YE | D65: はめるだけ光る 足腕バンド | E65: イエロー | F65: 46 | G65: 271 | H65: 10 | I65: =VLOOKUP(C65,'202310-202403出荷数total2403220951'!B:F,5,0) -> 50 | J65: =VLOOKUP(C65,'出荷数2307～2406total241008110618'!B:F,5,0) -> 53 | K65: =VLOOKUP(C65,'出荷数2407-2506total250730101950'!B:F,5,0) -> 93 | L65: =VLOOKUP(C:C,total251219111800!B:F,5,0) -> 13 | M65: 500 | N65: 500 | O65: 2318 | P65: 0 | Q65: 0 | R65: 0 | S65: 0 | T65: 0 | U65: 2318 | V65: 1818 | W65: 0.21570319
A66: 61 | B66: 伊賀 | C66: AHA-4307 | D66: 自動点灯サイクルライトⅡ | F66: 1006 | G66: 417 | H66: 772 | I66: =VLOOKUP(C66,'202310-202403出荷数total2403220951'!B:F,5,0) -> 650 | J66: =VLOOKUP(C66,'出荷数2307～2406total241008110618'!B:F,5,0) -> 1155 | K66: =VLOOKUP(C66,'出荷数2407-2506total250730101950'!B:F,5,0) -> 373 | L66: =VLOOKUP(C:C,total251219111800!B:F,5,0) -> 484 | N66: =L66 -> 484 | O66: 1279 | P66: 0 | Q66: 0 | R66: 0 | S66: 0 | T66: 0 | U66: 1279 | V66: 795 | W66: 0.37842064
A67: 62 | B67: 伊賀 | C67: ALA-4311 | D67: くるっとハンディランタンライト | F67: 856 | G67: 1296 | H67: 948 | I67: =VLOOKUP(C67,'202310-202403出荷数total2403220951'!B:F,5,0) -> 92 | J67: =VLOOKUP(C67,'出荷数2307～2406total241008110618'!B:F,5,0) -> 191 | K67: =VLOOKUP(C67,'出荷数2407-2506total250730101950'!B:F,5,0) -> 1768 | L67: =VLOOKUP(C:C,total251219111800!B:F,5,0) -> 749 | M67: 500 | N67: =L67 -> 749 | O67: 2728 | P67: 0 | Q67: 0 | R67: 0 | S67: 180 | T67: -180 | U67: 2548 | V67: 1799 | W67: 0.27456012
A68: 63 | B68: 伊賀 | C68: AIC-05IV | D68: ｽﾞﾚにくいｲｽ脚ｶﾊﾞｰ 1脚用 | E68: IV | F68: 2715 | G68: 1898 | H68: 1974 | I68: =VLOOKUP(C68,'202310-202403出荷数total2403220951'!B:F,5,0) -> 822 | J68: =VLOOKUP(C68,'出荷数2307～2406total241008110618'!B:F,5,0) -> 1831 | K68: =VLOOKUP(C68,'出荷数2407-2506total250730101950'!B:F,5,0) -> 1431 | L68: =VLOOKUP(C:C,total251219111800!B:F,5,0) -> 874 | N68: =L68 -> 874 | O68: 3973 | P68: 0 | Q68: 0 | R68: 0 | S68: 0 | T68: 0 | U68: 3973 | V68: 3099 | W68: 0.2199849 | X68: 23％発注点よりﾏｲﾅｽ 874→672
A69: 64 | B69: 伊賀 | C69: ABO-19 | D69: 防災用薄型ウォーターバッグ9L | F69: 680 | G69: 2488 | H69: 824 | I69: =VLOOKUP(C69,'202310-202403出荷数total2403220951'!B:F,5,0) -> 454 | J69: =VLOOKUP(C69,'出荷数2307～2406total241008110618'!B:F,5,0) -> 939 | K69: =VLOOKUP(C69,'出荷数2407-2506total250730101950'!B:F,5,0) -> 1427 | L69: =VLOOKUP(C:C,total251219111800!B:F,5,0) -> 203 | N69: =L69 -> 203 | O69: 2681 | P69: 0 | Q69: 0 | R69: 0 | S69: 0 | T69: 0 | U69: 2681 | V69: 2478 | W69: 0.075718016
A70: 65 | B70: 伊賀 | C70: AYC-101PK | D70: 耳すっきりクリーナー | E70: ピンク | F70: 1433 | G70: 1030 | H70: 1015 | I70: =VLOOKUP(C70,'202310-202403出荷数total2403220951'!B:F,5,0) -> 273 | J70: =VLOOKUP(C70,'出荷数2307～2406total241008110618'!B:F,5,0) -> 828 | K70: =VLOOKUP(C70,'出荷数2407-2506total250730101950'!B:F,5,0) -> 776 | L70: =VLOOKUP(C:C,total251219111800!B:F,5,0) -> 430 | N70: =L70 -> 430 | O70: 1946 | P70: 0 | Q70: 0 | R70: 0 | S70: 0 | T70: 0 | U70: 1946 | V70: 1516 | W70: 0.22096608
A71: 66 | B71: 伊賀 | C71: AUV-3301 | D71: 見えにくい汚れの発見ライト | G71: 600 | H71: 106 | I71: =VLOOKUP(C71,'202310-202403出荷数total2403220951'!B:F,5,0) -> 250 | J71: =VLOOKUP(C71,'出荷数2307～2406total241008110618'!B:F,5,0) -> 351 | K71: =VLOOKUP(C71,'出荷数2407-2506total250730101950'!B:F,5,0) -> 157 | L71: =VLOOKUP(C:C,total251219111800!B:F,5,0) -> #N/A | N71: =L71 -> #N/A | O71: 2381 | P71: 0 | Q71: 0 | R71: 0 | S71: 0 | T71: 0 | U71: 2381 | V71: #N/A | W71: #N/A
B72: 伊賀 | C72: AUV-3301C | D72: 365nmUVﾗｲﾄ | H72: 100 | I72: =VLOOKUP(C72,'202310-202403出荷数total2403220951'!B:F,5,0) -> 17 | J72: =VLOOKUP(C72,'出荷数2307～2406total241008110618'!B:F,5,0) -> 35 | K72: =VLOOKUP(C72,'出荷数2407-2506total250730101950'!B:F,5,0) -> 80 | L72: =VLOOKUP(C:C,total251219111800!B:F,5,0) -> 16 | N72: =L72 -> 16 | O72: 302 | P72: 0 | Q72: 0 | R72: 0 | S72: 0 | T72: 0 | U72: 302 | V72: 286 | W72: 0.052980132
A73: 67 | B73: 伊賀 | C73: AHL-1101 | D73: 単３と単１が使ええる防水ライト | F73: 4431 | G73: 2178 | H73: 3224 | I73: =VLOOKUP(C73,'202310-202403出荷数total2403220951'!B:F,5,0) -> 2952 | J73: =VLOOKUP(C73,'出荷数2307～2406total241008110618'!B:F,5,0) -> 5989 | K73: =VLOOKUP(C73,'出荷数2407-2506total250730101950'!B:F,5,0) -> 4689 | L73: =VLOOKUP(C:C,total251219111800!B:F,5,0) -> 1757 | N73: =L73 -> 1757 | O73: 6037 | P73: 200 | Q73: 0 | R73: 0 | S73: 200 | T73: 0 | U73: 5837 | V73: 4080 | W73: 0.28170595
A74: 68 | B74: 伊賀 | C74: ABO-03 | D74: 防災用ポリバケツ | F74: 3496 | G74: 2391 | H74: 1985 | I74: =VLOOKUP(C74,'202310-202403出荷数total2403220951'!B:F,5,0) -> 1236 | J74: =VLOOKUP(C74,'出荷数2307～2406total241008110618'!B:F,5,0) -> 2298 | K74: =VLOOKUP(C74,'出荷数2407-2506total250730101950'!B:F,5,0) -> 8616 | L74: =VLOOKUP(C:C,total251219111800!B:F,5,0) -> 1136 | M74: 8000 | N74: 8000 | O74: 14474 | P74: 3200 | Q74: 0 | R74: 0 | S74: 5200 | T74: -2000 | U74: 9274 | V74: 1274 | W74: 0.4526423
A75: 69 | B75: 伊賀 | C75: KCA-002 | D75: キューベルク 充電式ヘッドライト270 | F75: 44 | G75: 866 | H75: 614 | I75: =VLOOKUP(C75,'202310-202403出荷数total2403220951'!B:F,5,0) -> 333 | J75: =VLOOKUP(C75,'出荷数2307～2406total241008110618'!B:F,5,0) -> 1142 | K75: =VLOOKUP(C75,'出荷数2407-2506total250730101950'!B:F,5,0) -> 925 | L75: =VLOOKUP(C:C,total251219111800!B:F,5,0) -> 135 | N75: =L75 -> 135 | O75: 1770 | P75: 0 | Q75: 0 | R75: 0 | S75: 0 | T75: 0 | U75: 1770 | V75: 1635 | W75: 0.076271186
A76: 70 | B76: 伊賀 | C76: AHM-201 | D76: 防雨ハンドメガホン | F76: 410 | G76: 741 | H76: 1112 | I76: =VLOOKUP(C76,'202310-202403出荷数total2403220951'!B:F,5,0) -> 662 | J76: =VLOOKUP(C76,'出荷数2307～2406total241008110618'!B:F,5,0) -> 1332 | K76: =VLOOKUP(C76,'出荷数2407-2506total250730101950'!B:F,5,0) -> 2848 | L76: =VLOOKUP(C:C,total251219111800!B:F,5,0) -> 1014 | M76: 1000 | N76: =L76 -> 1014 | O76: 1668 | P76: 200 | Q76: 3000 | R76: 0 | S76: 200 | T76: 0 | U76: 4468 | V76: 3454 | W76: 0.54282655
A77: 71 | B77: 伊賀 | C77: AAM-200 | D77: 雨ふりセンサーⅡ | F77: 1477 | G77: 1110 | H77: 696 | I77: =VLOOKUP(C77,'202310-202403出荷数total2403220951'!B:F,5,0) -> 116 | J77: =VLOOKUP(C77,'出荷数2307～2406total241008110618'!B:F,5,0) -> 801 | K77: =VLOOKUP(C77,'出荷数2407-2506total250730101950'!B:F,5,0) -> 703 | L77: =VLOOKUP(C:C,total251219111800!B:F,5,0) -> 319 | N77: =L77 -> 319 | O77: 450 | P77: 0 | Q77: 0 | R77: 0 | S77: 0 | T77: 0 | U77: 450 | V77: 131 | W77: 0.70888889 | X77: 在庫減ってから発注。発注ロット2000希望 | Y77: 廃版予定？2000で交渉してもらう。
A78: 72 | B78: 伊賀 | C78: AHA-4306 | D78: 自動点灯前かごクリップライト | F78: 1324 | G78: 1622 | H78: 1792 | I78: =VLOOKUP(C78,'202310-202403出荷数total2403220951'!B:F,5,0) -> 1087 | J78: =VLOOKUP(C78,'出荷数2307～2406total241008110618'!B:F,5,0) -> 1970 | K78: =VLOOKUP(C78,'出荷数2407-2506total250730101950'!B:F,5,0) -> 1824 | L78: =VLOOKUP(C:C,total251219111800!B:F,5,0) -> 900 | N78: =L78 -> 900 | O78: 2841 | P78: 0 | Q78: 0 | R78: 0 | S78: 0 | T78: 0 | U78: 2841 | V78: 1941 | W78: 0.31678986
A79: 73 | B79: 伊賀 | C79: KCA-001 | D79: キューベルク 充電式ヘッドライト220 | F79: 30 | G79: 1288 | H79: 1790 | I79: =VLOOKUP(C79,'202310-202403出荷数total2403220951'!B:F,5,0) -> 845 | J79: =VLOOKUP(C79,'出荷数2307～2406total241008110618'!B:F,5,0) -> 1682 | K79: =VLOOKUP(C79,'出荷数2407-2506total250730101950'!B:F,5,0) -> 1326 | L79: =VLOOKUP(C:C,total251219111800!B:F,5,0) -> 366 | N79: =L79 -> 366 | O79: 1744 | P79: 0 | Q79: 0 | R79: 0 | S79: 0 | T79: 0 | U79: 1744 | V79: 1378 | W79: 0.20986239
A80: 74 | B80: 伊賀 | C80: AOM-01 | D80: かんたんお話メモ | F80: 6851 | G80: 3631 | H80: 3310 | I80: =VLOOKUP(C80,'202310-202403出荷数total2403220951'!B:F,5,0) -> 2276 | J80: =VLOOKUP(C80,'出荷数2307～2406total241008110618'!B:F,5,0) -> 2977 | K80: =VLOOKUP(C80,'出荷数2407-2506total250730101950'!B:F,5,0) -> 1413 | L80: =VLOOKUP(C:C,total251219111800!B:F,5,0) -> 456 | N80: =L80 -> 456 | O80: 2264 | P80: 0 | Q80: 0 | R80: 0 | S80: 200 | T80: -200 | U80: 2064 | V80: 1608 | W80: 0.20141343
A81: 75 | B81: 伊賀 | C81: AKM-3205BL | D81: 首ふり毛だまクリーナー | E81: ブルー | F81: 7367 | G81: 4388 | H81: 521 | I81: =VLOOKUP(C81,'202310-202403出荷数total2403220951'!B:F,5,0) -> 2848 | J81: =VLOOKUP(C81,'出荷数2307～2406total241008110618'!B:F,5,0) -> 3288 | K81: =VLOOKUP(C81,'出荷数2407-2506total250730101950'!B:F,5,0) -> 2304 | L81: =VLOOKUP(C:C,total251219111800!B:F,5,0) -> 744 | N81: =L81 -> 744 | O81: 4157 | P81: 3430 | Q81: 0 | R81: 0 | S81: 3430 | T81: 0 | U81: 727 | V81: -17 | W81: 0.098062475 | Y81: 5月に発注検討
A82: 76 | B82: 伊賀 | C82: ABO-12 | D82: 防災用ポリタンク 10L | F82: 10633 | G82: 6065 | H82: 2945 | I82: =VLOOKUP(C82,'202310-202403出荷数total2403220951'!B:F,5,0) -> 3324 | J82: =VLOOKUP(C82,'出荷数2307～2406total241008110618'!B:F,5,0) -> 5243 | K82: =VLOOKUP(C82,'出荷数2407-2506total250730101950'!B:F,5,0) -> 13654 | L82: =VLOOKUP(C:C,total251219111800!B:F,5,0) -> 1335 | M82: 4500 | N82: 3000 | O82: 6459 | P82: 2460 | Q82: 0 | R82: 0 | S82: 3160 | T82: -700 | U82: 3299 | V82: 299 | W82: 0.33636058
A83: 77 | B83: 伊賀 | C83: ALA-4310 | D83: ゆれたら点灯ライト(クリアケース) | F83: 270 | G83: 814 | H83: 677 | I83: =VLOOKUP(C83,'202310-202403出荷数total2403220951'!B:F,5,0) -> 269 | J83: =VLOOKUP(C83,'出荷数2307～2406total241008110618'!B:F,5,0) -> 668 | K83: =VLOOKUP(C83,'出荷数2407-2506total250730101950'!B:F,5,0) -> 826 | L83: =VLOOKUP(C:C,total251219111800!B:F,5,0) -> 90 | N83: =L83 -> 90 | O83: 2439 | P83: 0 | Q83: 0 | R83: 0 | S83: 0 | T83: 0 | U83: 2439 | V83: 2349 | W83: 0.036900369
A84: 78 | B84: 伊賀 | C84: ALA-3301 | D84: てるてるランタン | F84: 3306 | G84: 2817 | H84: 1743 | I84: =VLOOKUP(C84,'202310-202403出荷数total2403220951'!B:F,5,0) -> 273 | J84: =VLOOKUP(C84,'出荷数2307～2406total241008110618'!B:F,5,0) -> 477 | K84: =VLOOKUP(C84,'出荷数2407-2506total250730101950'!B:F,5,0) -> 351 | L84: =VLOOKUP(C:C,total251219111800!B:F,5,0) -> 211 | N84: =L84 -> 211 | O84: 7223 | P84: 0 | Q84: 0 | R84: 0 | S84: 0 | T84: 0 | U84: 7223 | V84: 7012 | W84: 0.029212239
A85: 79 | B85: 伊賀 | C85: ARO-02 | D85: 自動消灯安心のろうそくミニ | F85: 1177 | G85: 2128 | H85: 1537 | I85: =VLOOKUP(C85,'202310-202403出荷数total2403220951'!B:F,5,0) -> 834 | J85: =VLOOKUP(C85,'出荷数2307～2406total241008110618'!B:F,5,0) -> 1486 | K85: =VLOOKUP(C85,'出荷数2407-2506total250730101950'!B:F,5,0) -> 1411 | L85: =VLOOKUP(C:C,total251219111800!B:F,5,0) -> 822 | N85: =L85 -> 822 | O85: 2753 | P85: 0 | Q85: 0 | R85: 0 | S85: 0 | T85: 0 | U85: 2753 | V85: 1931 | W85: 0.29858336
A86: 80 | B86: 伊賀 | C86: ACR-01 | D86: スイッチ付きコードリール | F86: 1511 | G86: 1031 | H86: 1052 | I86: =VLOOKUP(C86,'202310-202403出荷数total2403220951'!B:F,5,0) -> 513 | J86: =VLOOKUP(C86,'出荷数2307～2406total241008110618'!B:F,5,0) -> 546 | K86: =VLOOKUP(C86,'出荷数2407-2506total250730101950'!B:F,5,0) -> #N/A | L86: =VLOOKUP(C:C,total251219111800!B:F,5,0) -> #N/A | N86: =L86 -> #N/A | O86: 0 | P86: 0 | Q86: 0 | R86: 0 | S86: 0 | T86: 0 | U86: 0 | V86: #N/A | W86: #N/A
A87: 81 | B87: 伊賀 | C87: AKR-20 | D87: ねこのキーカバー | F87: 3121 | G87: 3233 | H87: 3120 | I87: =VLOOKUP(C87,'202310-202403出荷数total2403220951'!B:F,5,0) -> 1553 | J87: =VLOOKUP(C87,'出荷数2307～2406total241008110618'!B:F,5,0) -> 3072 | K87: =VLOOKUP(C87,'出荷数2407-2506total250730101950'!B:F,5,0) -> 3947 | L87: =VLOOKUP(C:C,total251219111800!B:F,5,0) -> 1574 | N87: =L87 -> 1574 | O87: 4130 | P87: 0 | Q87: 0 | R87: 0 | S87: 0 | T87: 0 | U87: 4130 | V87: 2556 | W87: 0.3811138
A88: 82 | B88: 伊賀 | C88: AYD-102AD | D88: 電話の拡声器 ⅡＡＣアダプター | F88: 1334 | G88: 1879 | H88: 908 | I88: =VLOOKUP(C88,'202310-202403出荷数total2403220951'!B:F,5,0) -> 222 | J88: =VLOOKUP(C88,'出荷数2307～2406total241008110618'!B:F,5,0) -> 732 | K88: =VLOOKUP(C88,'出荷数2407-2506total250730101950'!B:F,5,0) -> 817 | L88: =VLOOKUP(C:C,total251219111800!B:F,5,0) -> 295 | N88: =L88 -> 295 | O88: 248 | P88: 0 | Q88: 0 | R88: 0 | S88: 0 | T88: 0 | U88: 248 | V88: -47 | W88: 1.1895161
A89: 83 | B89: 伊賀 | C89: AKR-11 | D89: シリコンキーカバー | F89: 3215 | G89: 3856 | H89: 4252 | I89: =VLOOKUP(C89,'202310-202403出荷数total2403220951'!B:F,5,0) -> 2413 | J89: =VLOOKUP(C89,'出荷数2307～2406total241008110618'!B:F,5,0) -> 4143 | K89: =VLOOKUP(C89,'出荷数2407-2506total250730101950'!B:F,5,0) -> 6112 | L89: =VLOOKUP(C:C,total251219111800!B:F,5,0) -> 2918 | N89: =L89 -> 2918 | O89: 3656 | P89: 0 | Q89: 0 | R89: 0 | S89: 0 | T89: 0 | U89: 3656 | V89: 738 | W89: 0.79814004
A90: 84 | B90: 伊賀 | C90: AST-3401 | D90: スマホが充電できるスタンドライト | F90: 102 | G90: 340 | H90: 49 | I90: =VLOOKUP(C90,'202310-202403出荷数total2403220951'!B:F,5,0) -> 6 | J90: =VLOOKUP(C90,'出荷数2307～2406total241008110618'!B:F,5,0) -> 434 | K90: =VLOOKUP(C90,'出荷数2407-2506total250730101950'!B:F,5,0) -> #N/A | L90: =VLOOKUP(C:C,total251219111800!B:F,5,0) -> #N/A | N90: =L90 -> #N/A | O90: 0 | P90: 0 | Q90: 0 | R90: 0 | S90: 0 | T90: 0 | U90: 0 | V90: #N/A | W90: #N/A
A91: 85 | B91: 伊賀 | C91: ASL-3310 | D91: マグネット付くるっと回るセンサーライト | F91: 1538 | G91: 2587 | H91: 571 | I91: =VLOOKUP(C91,'202310-202403出荷数total2403220951'!B:F,5,0) -> 874 | J91: =VLOOKUP(C91,'出荷数2307～2406total241008110618'!B:F,5,0) -> 1045 | K91: =VLOOKUP(C91,'出荷数2407-2506total250730101950'!B:F,5,0) -> 429 | L91: =VLOOKUP(C:C,total251219111800!B:F,5,0) -> 22 | M91: 1400 | N91: 1400 | O91: 4406 | P91: 0 | Q91: 0 | R91: 0 | S91: 100 | T91: -100 | U91: 4306 | V91: 2906 | W91: 0.31774852
A92: 87 | B92: 伊賀 | C92: ASL-3303 | D92: ドア用センサーライト | F92: 8125 | G92: 7398 | H92: 4528 | I92: =VLOOKUP(C92,'202310-202403出荷数total2403220951'!B:F,5,0) -> 1614 | J92: =VLOOKUP(C92,'出荷数2307～2406total241008110618'!B:F,5,0) -> 3692 | K92: =VLOOKUP(C92,'出荷数2407-2506total250730101950'!B:F,5,0) -> 3180 | L92: =VLOOKUP(C:C,total251219111800!B:F,5,0) -> 1448 | N92: =L92 -> 1448 | O92: 5190 | P92: 870 | Q92: 40 | R92: 0 | S92: 1500 | T92: -630 | U92: 3730 | V92: 2282 | W92: 0.23894389
A93: 88 | B93: 伊賀 | C93: ASL-33032 | D93: ドア用センサーライト（ｼｮｯﾌﾟﾁｬﾝﾈﾙ） | F93: 0 | G93: 5 | H93: 904 | I93: =VLOOKUP(C93,'202310-202403出荷数total2403220951'!B:F,5,0) -> #N/A | J93: =VLOOKUP(C93,'出荷数2307～2406total241008110618'!B:F,5,0) -> #N/A | K93: =VLOOKUP(C93,'出荷数2407-2506total250730101950'!B:F,5,0) -> #N/A | L93: =VLOOKUP(C:C,total251219111800!B:F,5,0) -> #N/A | M93: 380 | N93: 380 | O93: 781 | P93: 0 | Q93: 0 | R93: 0 | S93: 0 | T93: 0 | U93: 781 | V93: 401 | W93: 0.4865557
A94: 89 | B94: 伊賀 | C94: ASL-3303K | D94: ドア用センサーライト（ケーズ） | F94: 684 | G94: 626 | H94: 772 | I94: =VLOOKUP(C94,'202310-202403出荷数total2403220951'!B:F,5,0) -> 81 | J94: =VLOOKUP(C94,'出荷数2307～2406total241008110618'!B:F,5,0) -> 221 | K94: =VLOOKUP(C94,'出荷数2407-2506total250730101950'!B:F,5,0) -> #N/A | L94: =VLOOKUP(C:C,total251219111800!B:F,5,0) -> #N/A | N94: =L94 -> #N/A | O94: 3 | P94: 0 | Q94: 0 | R94: 0 | S94: 0 | T94: 0 | U94: 3 | V94: #N/A | W94: #N/A
A95: 90 | B95: 伊賀 | C95: AIC-04BE | D95: ｽﾞﾚにくいｲｽ脚ｶﾊﾞｰ 4脚用 | E95: BE | F95: 4518 | G95: 3870 | H95: 3467 | I95: =VLOOKUP(C95,'202310-202403出荷数total2403220951'!B:F,5,0) -> 1429 | J95: =VLOOKUP(C95,'出荷数2307～2406total241008110618'!B:F,5,0) -> 3078 | K95: =VLOOKUP(C95,'出荷数2407-2506total250730101950'!B:F,5,0) -> 3161 | L95: =VLOOKUP(C:C,total251219111800!B:F,5,0) -> 1695 | N95: =L95 -> 1695 | O95: 433 | P95: 0 | Q95: 3000 | R95: 0 | S95: 0 | T95: 0 | U95: 3433 | V95: 1738 | W95: 3.9145497 | X95: 48％発注点よりﾏｲﾅｽ 1695→881
A96: 91 | B96: 伊賀 | C96: AST-3303 | D96: スマホが置けるスタンドライト | F96: 12335 | G96: 8441 | H96: 3599 | I96: =VLOOKUP(C96,'202310-202403出荷数total2403220951'!B:F,5,0) -> 3021 | J96: =VLOOKUP(C96,'出荷数2307～2406total241008110618'!B:F,5,0) -> 4038 | K96: =VLOOKUP(C96,'出荷数2407-2506total250730101950'!B:F,5,0) -> 1769 | L96: =VLOOKUP(C:C,total251219111800!B:F,5,0) -> 560 | N96: =L96 -> 560 | O96: 8982 | P96: 1500 | Q96: 0 | R96: 0 | S96: 1500 | T96: 0 | U96: 7482 | V96: 6922 | W96: 0.053424919
A97: 92 | B97: 伊賀 | C97: AKM-3204PK | D97: 立てて置ける毛だまクリーナー | E97: ピンク | F97: 2663 | G97: 4626 | H97: 4263 | I97: =VLOOKUP(C97,'202310-202403出荷数total2403220951'!B:F,5,0) -> 1415 | J97: =VLOOKUP(C97,'出荷数2307～2406total241008110618'!B:F,5,0) -> 2582 | K97: =VLOOKUP(C97,'出荷数2407-2506total250730101950'!B:F,5,0) -> 2814 | L97: =VLOOKUP(C:C,total251219111800!B:F,5,0) -> 1960 | N97: =L97 -> 1960 | O97: 4338 | P97: 800 | Q97: 0 | R97: 0 | S97: 800 | T97: 0 | U97: 3538 | V97: 1578 | W97: 0.38147139
A98: 93 | B98: 伊賀 | C98: ADR-100 | D98: ドライヤースタンド | F98: 3167 | G98: 3686 | H98: 4490 | I98: =VLOOKUP(C98,'202310-202403出荷数total2403220951'!B:F,5,0) -> 1027 | J98: =VLOOKUP(C98,'出荷数2307～2406total241008110618'!B:F,5,0) -> 2480 | K98: =VLOOKUP(C98,'出荷数2407-2506total250730101950'!B:F,5,0) -> 1578 | L98: =VLOOKUP(C:C,total251219111800!B:F,5,0) -> 247 | N98: =L98 -> 247 | O98: 2775 | P98: 0 | Q98: 0 | R98: 0 | S98: 100 | T98: -100 | U98: 2675 | V98: 2428 | W98: 0.089009009
A99: 94 | B99: 伊賀 | C99: AYC-101BL | D99: 耳すっきりクリーナー | E99: ブルー | F99: 5717 | H99: 3844 | I99: =VLOOKUP(C99,'202310-202403出荷数total2403220951'!B:F,5,0) -> 1058 | J99: =VLOOKUP(C99,'出荷数2307～2406total241008110618'!B:F,5,0) -> 2412 | K99: =VLOOKUP(C99,'出荷数2407-2506total250730101950'!B:F,5,0) -> 2874 | L99: =VLOOKUP(C:C,total251219111800!B:F,5,0) -> 1317 | N99: =L99 -> 1317 | O99: 2188 | P99: 120 | Q99: 0 | R99: 0 | S99: 250 | T99: -130 | U99: 1938 | V99: 621 | W99: 0.57062392
A100: 95 | B100: 伊賀 | C100: AHL-2203 | D100: 単2形LED防雨ライト | F100: 15469 | G100: 8369 | H100: 9994 | I100: =VLOOKUP(C100,'202310-202403出荷数total2403220951'!B:F,5,0) -> 2524 | J100: =VLOOKUP(C100,'出荷数2307～2406total241008110618'!B:F,5,0) -> 7246 | K100: =VLOOKUP(C100,'出荷数2407-2506total250730101950'!B:F,5,0) -> 19015 | L100: =VLOOKUP(C:C,total251219111800!B:F,5,0) -> 3771 | M100: 4500 | N100: 3000 | O100: 7285 | P100: 7270 | Q100: 3000 | R100: 0 | S100: 7270 | T100: 0 | U100: 3015 | V100: 15 | W100: 0.20611474
...

Sheet 80213
B1: 商品センター | C1: 品番 | D1: 商品区分 | E1: カラー | F1: 72期 | G1: 73期 | H1: 74期(1期) | I1: 2023/10/1～2024/3/21（6か月） | J1: 75期(2期) | K1: 76期（３期 ） | L1: 77期（4期 7/1-12/18） | N1: 発注点 5ヶ月分なのでそのまま | O1: 在庫数 ロジザード | Q1: 入荷予定 ロジザード | S1: 確保数 弥生(在庫確保) | T1: 確保数チェック 0じゃなかったらロジザード修正 | U1: 有効数量 フリー在庫の数 | V1: 発注検討フラグ マイナスの場合発注検討 | W1: 在庫回転率 | X1: 前回決定事項（1/30） | Y1: 決定事項 | AE1: 前回決定事項（/） | AG1: 決定事項
A2: 1 | B2: 伊賀 | C2: APL-4312SBL | D2: ミニホイッスル付LEDアルミライトⅡ | H2: 192 | I2: =VLOOKUP(C2,'202310-202403出荷数total2403220951'!B:F,5,0) -> 71 | J2: =VLOOKUP(C2,'出荷数2307～2406total241008110618'!B:F,5,0) -> 281 | K2: =VLOOKUP(C2,'出荷数2407-2506total250730101950'!B:F,5,0) -> 902 | L2: =VLOOKUP(C:C,total251219111800!B:F,5,0) -> 386 | N2: =L2 -> 386 | O2: 276 | P2: 390 | Q2: 0 | R2: 0 | S2: 380 | T2: 10 | U2: -104 | V2: -490 | W2: 0.57957958
A3: 2 | B3: 伊賀 | C3: APL-4312SPK | D3: ミニホイッスル付LEDアルミライトⅡ | H3: 2161 | I3: =VLOOKUP(C3,'202310-202403出荷数total2403220951'!B:F,5,0) -> 1018 | J3: =VLOOKUP(C3,'出荷数2307～2406total241008110618'!B:F,5,0) -> 1930 | K3: =VLOOKUP(C3,'出荷数2407-2506total250730101950'!B:F,5,0) -> 3388 | L3: =VLOOKUP(C:C,total251219111800!B:F,5,0) -> 903 | N3: =L3 -> 903 | O3: 1782 | P3: 980 | Q3: 0 | R3: 0 | S3: 1630 | T3: -650 | U3: 152 | V3: -751 | W3: 0.326937
A4: 86 | B4: 伊賀 | C4: ABO-08BL | D4: ミニホイッスル | E4: ブルー | F4: 527 | G4: 2107 | H4: 796 | I4: =VLOOKUP(C4,'202310-202403出荷数total2403220951'!B:F,5,0) -> 1409 | J4: =VLOOKUP(C4,'出荷数2307～2406total241008110618'!B:F,5,0) -> 1708 | K4: =VLOOKUP(C4,'出荷数2407-2506total250730101950'!B:F,5,0) -> 1865 | L4: =VLOOKUP(C:C,total251219111800!B:F,5,0) -> 474 | M4: 1000 | N4: 1000 | O4: 6736 | P4: 0 | Q4: 0 | R4: 0 | S4: 0 | T4: 0 | U4: 6736 | V4: 5736 | W4: 0.14845606
A5: 107 | B5: 伊賀 | C5: ABO-08PK | D5: ミニホイッスル | E5: ピンク | F5: 3939 | G5: 5966 | H5: 5009 | I5: =VLOOKUP(C5,'202310-202403出荷数total2403220951'!B:F,5,0) -> 6490 | J5: =VLOOKUP(C5,'出荷数2307～2406total241008110618'!B:F,5,0) -> 17931 | K5: =VLOOKUP(C5,'出荷数2407-2506total250730101950'!B:F,5,0) -> 28387 | L5: =VLOOKUP(C:C,total251219111800!B:F,5,0) -> 4495 | N5: =L5 -> 4495 | O5: 27847 | P5: 14360 | Q5: 800 | R5: 0 | S5: 14360 | T5: 0 | U5: 14287 | V5: 9792 | W5: 0.10649892
A6: 109 | B6: 伊賀 | C6: APL-4302S | D6: ＬＥＤミニアルミライト | F6: 1094 | G6: 3475 | H6: 834 | I6: =VLOOKUP(C6,'202310-202403出荷数total2403220951'!B:F,5,0) -> 444 | J6: =VLOOKUP(C6,'出荷数2307～2406total241008110618'!B:F,5,0) -> 789 | K6: =VLOOKUP(C6,'出荷数2407-2506total250730101950'!B:F,5,0) -> 232 | L6: =VLOOKUP(C:C,total251219111800!B:F,5,0) -> 177 | N6: =L6 -> 177 | O6: 3754 | P6: 0 | Q6: 300 | R6: 0 | S6: 0 | T6: 0 | U6: 4054 | V6: 3877 | W6: 0.047149707
A7: 3 | B7: 伊賀 | C7: ASL-3308SK | D7: ウォールセンサーライト 箱 | E7: しかく | F7: 1 | G7: 0 | H7: 4 | I7: =VLOOKUP(C7,'202310-202403出荷数total2403220951'!B:F,5,0) -> #N/A | J7: =VLOOKUP(C7,'出荷数2307～2406total241008110618'!B:F,5,0) -> #N/A | K7: =VLOOKUP(C7,'出荷数2407-2506total250730101950'!B:F,5,0) -> #N/A | L7: =VLOOKUP(C:C,total251219111800!B:F,5,0) -> #N/A | N7: 0 | O7: 1 | P7: 0 | Q7: 0 | R7: 0 | S7: 0 | T7: 0 | U7: 1 | V7: 1 | W7: 0
A8: 4 | B8: 伊賀 | C8: AHL-3201RD | D8: LEDハンディライト | H8: 2048 | I8: =VLOOKUP(C8,'202310-202403出荷数total2403220951'!B:F,5,0) -> 2098 | J8: =VLOOKUP(C8,'出荷数2307～2406total241008110618'!B:F,5,0) -> 3644 | K8: =VLOOKUP(C8,'出荷数2407-2506total250730101950'!B:F,5,0) -> 2910 | L8: =VLOOKUP(C:C,total251219111800!B:F,5,0) -> 2559 | N8: =L8 -> 2559 | O8: 3061 | P8: 0 | Q8: 0 | R8: 0 | S8: 0 | T8: 0 | U8: 3061 | V8: 502 | W8: 0.83600131
A9: 5 | B9: 伊賀 | C9: AHL-3201WH | D9: LEDハンディライト | H9: 116 | I9: =VLOOKUP(C9,'202310-202403出荷数total2403220951'!B:F,5,0) -> 220 | J9: =VLOOKUP(C9,'出荷数2307～2406total241008110618'!B:F,5,0) -> 378 | K9: =VLOOKUP(C9,'出荷数2407-2506total250730101950'!B:F,5,0) -> 2016 | L9: =VLOOKUP(C:C,total251219111800!B:F,5,0) -> 281 | M9: 1000 | N9: 1000 | O9: 5179 | P9: 0 | Q9: 0 | R9: 0 | S9: 0 | T9: 0 | U9: 5179 | V9: 4179 | W9: 0.19308747
A10: 6 | B10: 伊賀 | C10: AHL-1400 | D10: LED強力ライト | H10: 15126 | I10: =VLOOKUP(C10,'202310-202403出荷数total2403220951'!B:F,5,0) -> 9163 | J10: =VLOOKUP(C10,'出荷数2307～2406total241008110618'!B:F,5,0) -> 19757 | K10: =VLOOKUP(C10,'出荷数2407-2506total250730101950'!B:F,5,0) -> 20812 | L10: =VLOOKUP(C:C,total251219111800!B:F,5,0) -> 4356 | N10: =L10 -> 4356 | O10: 2377 | P10: 13210 | Q10: 0 | R10: 0 | S10: 13175 | T10: 35 | U10: -10798 | V10: -15154 | W10: 0.27946366
A11: 7 | B11: 伊賀 | C11: AHL-1400T | D11: LED強力ライト(トップ) | H11: 2084 | I11: =VLOOKUP(C11,'202310-202403出荷数total2403220951'!B:F,5,0) -> 1160 | J11: =VLOOKUP(C11,'出荷数2307～2406total241008110618'!B:F,5,0) -> 1821 | K11: =VLOOKUP(C11,'出荷数2407-2506total250730101950'!B:F,5,0) -> 1120 | L11: =VLOOKUP(C:C,total251219111800!B:F,5,0) -> 160 | N11: =L11 -> 160 | O11: 2 | P11: 0 | Q11: 0 | R11: 0 | S11: 0 | T11: 0 | U11: 2 | V11: -158 | W11: 80
A12: 8 | B12: 伊賀 | C12: ASL-3308KU | D12: ウォールセンサーライト 箱 | E12: くも | F12: 193 | G12: 1 | H12: 100 | I12: =VLOOKUP(C12,'202310-202403出荷数total2403220951'!B:F,5,0) -> 43 | J12: =VLOOKUP(C12,'出荷数2307～2406total241008110618'!B:F,5,0) -> 51 | K12: =VLOOKUP(C12,'出荷数2407-2506total250730101950'!B:F,5,0) -> 12 | L12: =VLOOKUP(C:C,total251219111800!B:F,5,0) -> 3 | N12: =L12 -> 3 | O12: 992 | P12: 0 | Q12: 0 | R12: 0 | S12: 0 | T12: 0 | U12: 992 | V12: 989 | W12: 0.0030241935
A13: 9 | B13: 伊賀 | C13: ANS-502 | D13: テレビ用手もとスピーカー | G13: 6 | H13: 2364 | I13: =VLOOKUP(C13,'202310-202403出荷数total2403220951'!B:F,5,0) -> 1052 | J13: =VLOOKUP(C13,'出荷数2307～2406total241008110618'!B:F,5,0) -> 1711 | K13: =VLOOKUP(C13,'出荷数2407-2506total250730101950'!B:F,5,0) -> 1026 | L13: =VLOOKUP(C:C,total251219111800!B:F,5,0) -> 587 | N13: =L13 -> 587 | O13: 3514 | P13: 0 | Q13: 0 | R13: 0 | S13: 0 | T13: 0 | U13: 3514 | V13: 2927 | W13: 0.1670461
A14: 10 | B14: 伊賀 | C14: ASL-3308US | D14: ウォールセンサーライト 箱 | E14: うさぎ | F14: 0 | G14: 3 | H14: 363 | I14: =VLOOKUP(C14,'202310-202403出荷数total2403220951'!B:F,5,0) -> #N/A | J14: =VLOOKUP(C14,'出荷数2307～2406total241008110618'!B:F,5,0) -> 1 | K14: =VLOOKUP(C14,'出荷数2407-2506total250730101950'!B:F,5,0) -> 7 | L14: =VLOOKUP(C:C,total251219111800!B:F,5,0) -> #N/A | N14: 0 | O14: 744 | P14: 0 | Q14: 0 | R14: 0 | S14: 0 | T14: 0 | U14: 744 | V14: 744 | W14: 0
A15: 11 | B15: 伊賀 | C15: ASL-3308CSK | D15: ウォールセンサーライト ブリスター | E15: しかく | F15: 23 | G15: 4 | H15: 0 | I15: =VLOOKUP(C15,'202310-202403出荷数total2403220951'!B:F,5,0) -> 1 | J15: =VLOOKUP(C15,'出荷数2307～2406total241008110618'!B:F,5,0) -> 705 | K15: =VLOOKUP(C15,'出荷数2407-2506total250730101950'!B:F,5,0) -> 1 | L15: =VLOOKUP(C:C,total251219111800!B:F,5,0) -> 1 | N15: =L15 -> 1 | O15: 0 | P15: 0 | Q15: 0 | R15: 0 | S15: 0 | T15: 0 | U15: 0 | V15: -1 | W15: #DIV/0!
A16: 12 | B16: 伊賀 | C16: ASL-3308CUS | D16: ウォールセンサーライト ブリスター | E16: うさぎ | F16: 35 | G16: 26 | H16: 5 | I16: =VLOOKUP(C16,'202310-202403出荷数total2403220951'!B:F,5,0) -> 3 | J16: =VLOOKUP(C16,'出荷数2307～2406total241008110618'!B:F,5,0) -> 6 | K16: =VLOOKUP(C16,'出荷数2407-2506total250730101950'!B:F,5,0) -> 3 | L16: =VLOOKUP(C:C,total251219111800!B:F,5,0) -> 142 | N16: =L16 -> 142 | O16: 4414 | P16: 0 | Q16: 0 | R16: 0 | S16: 0 | T16: 0 | U16: 4414 | V16: 4272 | W16: 0.032170367
A17: 13 | B17: 伊賀 | C17: AKM-3205PK | D17: 首ふり毛だまクリーナー | E17: ピンク | F17: 33 | G17: 24 | H17: 2990 | I17: =VLOOKUP(C17,'202310-202403出荷数total2403220951'!B:F,5,0) -> 66 | J17: =VLOOKUP(C17,'出荷数2307～2406total241008110618'!B:F,5,0) -> 189 | K17: =VLOOKUP(C17,'出荷数2407-2506total250730101950'!B:F,5,0) -> 97 | L17: =VLOOKUP(C:C,total251219111800!B:F,5,0) -> 77 | N17: =L17 -> 77 | O17: 2106 | P17: 0 | Q17: 0 | R17: 0 | S17: 0 | T17: 0 | U17: 2106 | V17: 2029 | W17: 0.036562203
A18: 14 | B18: 伊賀 | C18: ASN-4302 | D18: マグネット付ＬＥＤ信号灯 | F18: 149 | G18: 62 | H18: 132 | I18: =VLOOKUP(C18,'202310-202403出荷数total2403220951'!B:F,5,0) -> 245 | J18: =VLOOKUP(C18,'出荷数2307～2406total241008110618'!B:F,5,0) -> 322 | K18: =VLOOKUP(C18,'出荷数2407-2506total250730101950'!B:F,5,0) -> 206 | L18: =VLOOKUP(C:C,total251219111800!B:F,5,0) -> 17 | N18: =L18 -> 17 | O18: 2255 | P18: 0 | Q18: 0 | R18: 0 | S18: 0 | T18: 0 | U18: 2255 | V18: 2238 | W18: 0.0075388027 | X18: 売り切り廃盤予定
A19: 15 | B19: 伊賀 | C19: AIC-01IV | D19: ｷｽﾞつきにくいｲｽ脚ｶﾊﾞｰ | E19: IV | F19: 228 | G19: 270 | H19: 231 | I19: =VLOOKUP(C19,'202310-202403出荷数total2403220951'!B:F,5,0) -> 121 | J19: =VLOOKUP(C19,'出荷数2307～2406total241008110618'!B:F,5,0) -> 177 | K19: =VLOOKUP(C19,'出荷数2407-2506total250730101950'!B:F,5,0) -> 110 | L19: =VLOOKUP(C:C,total251219111800!B:F,5,0) -> 53 | N19: =L19 -> 53 | O19: 8059 | P19: 0 | Q19: 0 | R19: 0 | S19: 0 | T19: 0 | U19: 8059 | V19: 8006 | W19: 0.0065764983
A20: 16 | B20: 伊賀 | C20: ANS-603 | D20: お経の流れるスピーカーⅡ | G20: 128 | H20: 470 | I20: =VLOOKUP(C20,'202310-202403出荷数total2403220951'!B:F,5,0) -> 149 | J20: =VLOOKUP(C20,'出荷数2307～2406total241008110618'!B:F,5,0) -> 418 | K20: =VLOOKUP(C20,'出荷数2407-2506total250730101950'!B:F,5,0) -> 818 | L20: =VLOOKUP(C:C,total251219111800!B:F,5,0) -> 491 | N20: =L20 -> 491 | O20: 585 | P20: 197 | Q20: 0 | R20: 0 | S20: 197 | T20: 0 | U20: 388 | V20: -103 | W20: 0.62787724 | X20: トップ確保3月末まで確保
A21: 17 | B21: 伊賀 | C21: APY-105 | D21: 迷惑電話お断りピンポン | F21: 543 | G21: 321 | H21: 270 | I21: =VLOOKUP(C21,'202310-202403出荷数total2403220951'!B:F,5,0) -> 73 | J21: =VLOOKUP(C21,'出荷数2307～2406total241008110618'!B:F,5,0) -> 181 | K21: =VLOOKUP(C21,'出荷数2407-2506total250730101950'!B:F,5,0) -> 277 | L21: =VLOOKUP(C:C,total251219111800!B:F,5,0) -> 141 | N21: =L21 -> 141 | O21: 3127 | P21: 370 | Q21: 0 | R21: 0 | S21: 454 | T21: -84 | U21: 2673 | V21: 2532 | W21: 0.040320275
A22: 18 | B22: 伊賀 | C22: APL-3207S | D22: LEDのインテリア常備灯 | F22: 904 | G22: 638 | H22: 81 | I22: =VLOOKUP(C22,'202310-202403出荷数total2403220951'!B:F,5,0) -> 2 | J22: =VLOOKUP(C22,'出荷数2307～2406total241008110618'!B:F,5,0) -> 904 | K22: =VLOOKUP(C22,'出荷数2407-2506total250730101950'!B:F,5,0) -> 25 | L22: =VLOOKUP(C:C,total251219111800!B:F,5,0) -> 2 | N22: =L22 -> 2 | O22: 6860 | P22: 0 | Q22: 0 | R22: 0 | S22: 0 | T22: 0 | U22: 6860 | V22: 6858 | W22: 0.00029154519
A23: 19 | B23: 伊賀 | C23: ALA-4308BK-D | D23: ひっぱり点灯ライト 電球色ＬＥＤ | F23: 1137 | G23: 270 | H23: 272 | I23: =VLOOKUP(C23,'202310-202403出荷数total2403220951'!B:F,5,0) -> 153 | J23: =VLOOKUP(C23,'出荷数2307～2406total241008110618'!B:F,5,0) -> 657 | K23: =VLOOKUP(C23,'出荷数2407-2506total250730101950'!B:F,5,0) -> 101 | L23: =VLOOKUP(C:C,total251219111800!B:F,5,0) -> 88 | N23: =L23 -> 88 | O23: 1779 | P23: 0 | Q23: 0 | R23: 0 | S23: 0 | T23: 0 | U23: 1779 | V23: 1691 | W23: 0.049465992
A24: 20 | B24: 伊賀 | C24: ACA-101 | D24: ＬＥＤ帽子ライト | F24: 787 | G24: 450 | H24: 417 | I24: =VLOOKUP(C24,'202310-202403出荷数total2403220951'!B:F,5,0) -> 450 | J24: =VLOOKUP(C24,'出荷数2307～2406total241008110618'!B:F,5,0) -> 550 | K24: =VLOOKUP(C24,'出荷数2407-2506total250730101950'!B:F,5,0) -> 160 | L24: =VLOOKUP(C:C,total251219111800!B:F,5,0) -> 89 | N24: =L24 -> 89 | O24: 3687 | P24: 0 | Q24: 0 | R24: 0 | S24: 0 | T24: 0 | U24: 3687 | V24: 3598 | W24: 0.024138866
A25: 21 | B25: 伊賀 | C25: ASL-3308NE | D25: ウォールセンサーライト 箱 | E25: ねこ | F25: 13 | G25: 4 | H25: 8 | I25: =VLOOKUP(C25,'202310-202403出荷数total2403220951'!B:F,5,0) -> 1 | J25: =VLOOKUP(C25,'出荷数2307～2406total241008110618'!B:F,5,0) -> 4 | K25: =VLOOKUP(C25,'出荷数2407-2506total250730101950'!B:F,5,0) -> 6 | L25: =VLOOKUP(C:C,total251219111800!B:F,5,0) -> #N/A | N25: 0 | O25: 24 | P25: 0 | Q25: 0 | R25: 0 | S25: 0 | T25: 0 | U25: 24 | V25: 24 | W25: 0
A26: 22 | B26: 伊賀 | C26: AKD-20 | D26: アニマルシリコンバンド | F26: 1809 | G26: 790 | H26: 1042 | I26: =VLOOKUP(C26,'202310-202403出荷数total2403220951'!B:F,5,0) -> 164 | J26: =VLOOKUP(C26,'出荷数2307～2406total241008110618'!B:F,5,0) -> 312 | K26: =VLOOKUP(C26,'出荷数2407-2506total250730101950'!B:F,5,0) -> 454 | L26: =VLOOKUP(C:C,total251219111800!B:F,5,0) -> 168 | N26: =L26 -> 168 | O26: 5678 | P26: 100 | Q26: 0 | R26: 0 | S26: 200 | T26: -100 | U26: 5478 | V26: 5310 | W26: 0.029075805
A27: 23 | B27: 伊賀 | C27: ARA-4301 | D27: スマートフォンが使えるラジオライト | F27: 549 | G27: 303 | H27: 236 | I27: =VLOOKUP(C27,'202310-202403出荷数total2403220951'!B:F,5,0) -> 241 | J27: =VLOOKUP(C27,'出荷数2307～2406total241008110618'!B:F,5,0) -> 358 | K27: =VLOOKUP(C27,'出荷数2407-2506total250730101950'!B:F,5,0) -> 392 | L27: =VLOOKUP(C:C,total251219111800!B:F,5,0) -> 29 | N27: =L27 -> 29 | O27: 1916 | P27: 0 | Q27: 0 | R27: 0 | S27: 0 | T27: 0 | U27: 1916 | V27: 1887 | W27: 0.015135699
A28: 24 | B28: 伊賀 | C28: ASK-11BOR | D28: 巻きつく安全反射バンド(OR) | E28: オレンジ | F28: 1160 | G28: 148 | H28: 651 | I28: =VLOOKUP(C28,'202310-202403出荷数total2403220951'!B:F,5,0) -> 60 | J28: =VLOOKUP(C28,'出荷数2307～2406total241008110618'!B:F,5,0) -> 125 | K28: =VLOOKUP(C28,'出荷数2407-2506total250730101950'!B:F,5,0) -> 265 | L28: =VLOOKUP(C:C,total251219111800!B:F,5,0) -> 38 | M28: 500 | N28: 500 | O28: 2298 | P28: 0 | Q28: 0 | R28: 0 | S28: 0 | T28: 0 | U28: 2298 | V28: 1798 | W28: 0.2175805
A29: 25 | B29: 伊賀 | C29: ASK-10YE | D29: 光るホイール反射シール | E29: イエロー | F29: 935 | G29: 77 | H29: 731 | I29: =VLOOKUP(C29,'202310-202403出荷数total2403220951'!B:F,5,0) -> 163 | J29: =VLOOKUP(C29,'出荷数2307～2406total241008110618'!B:F,5,0) -> 235 | K29: =VLOOKUP(C29,'出荷数2407-2506total250730101950'!B:F,5,0) -> 20 | L29: =VLOOKUP(C:C,total251219111800!B:F,5,0) -> 2 | N29: =L29 -> 2 | O29: 5 | P29: 0 | Q29: 0 | R29: 0 | S29: 0 | T29: 0 | U29: 5 | V29: 3 | W29: 0.4
